Workbook
Name NR_JobTitle: Cleaned_Data!$B$11:$B$444
Name NR_Location: Cleaned_Data!$D$11:$D$444
Name NR_Industry: Cleaned_Data!$E$11:$E$444
Name NR_ExpLevel: Cleaned_Data!$F$11:$F$444
Name NR_WorkMode: Cleaned_Data!$H$11:$H$444
Name NR_SalaryMin: Cleaned_Data!$I$11:$I$444
Name NR_SalaryMax: Cleaned_Data!$J$11:$J$444
Name NR_Skills: Cleaned_Data!$K$11:$K$444
Name NR_AvgSalary: Cleaned_Data!$M$11:$M$444
Name NR_RoleCategory: Cleaned_Data!$P$11:$P$444
Name NR_DupFlag: Cleaned_Data!$Q$11:$Q$444
Name NR_F_Role: Dashboard!$B$4
Name NR_F_Loc: Dashboard!$E$4
Name NR_F_Exp: Dashboard!$H$4
Name NR_F_WM: Dashboard!$K$4
Name NR_F_Ind: Dashboard!$N$4

Sheet Instructions
A1: Job Market Analysis Dashboard
A4: Project Objective
A5: Analyze a real sample of Indian job postings and build an interactive Excel dashboard covering demand by role and location, salary ranges, experience levels, top skills, work mode split, and industry mix — the kind of first analysis a Data Analyst / Business Analyst / MIS Executive is asked to do.
A7: How This Workbook Is Organised
A8: 1. Raw_Data — the original, unprocessed job posting records (intentionally contains a few duplicates, inconsistent spellings, extra spaces and missing values, exactly as raw data usually arrives).
A9: 2. Cleaned_Data — the same data cleaned with formulas (TRIM, PROPER, IF, IFS, SEARCH), plus calculated columns: Average_Salary, Salary_Range, Posting_Month, Job_Role_Category and Duplicate_Flag.
A10: 3. Analysis — pivot-style summary tables built with COUNTIFS / SUMIFS / AVERAGEIFS that answer each business question the dashboard needs.
A11: 4. Dashboard — one-page view with 5 live filter dropdowns, 5 KPI cards and 6 charts, all linked live to the Analysis sheet.
A13: Dataset Note
A14: Records are a real, de-identified sample of job postings collected from a public Indian job-search platform (title, company, location, experience, salary and skills fields), narrowed down to ~420 usable postings for this project. Fields not present in the source (Industry, Experience_Level bucket, Work_Mode, Job_Role_Category) were derived using simple keyword rules so the data could be grouped and charted.
A16: How the Interactive Filters Work
A17: The 5 dropdowns at the top of the Dashboard (Job Role, Location, Experience, Work Mode, Industry) are Data Validation lists pointing at the hidden Lists sheet. Every KPI and summary table formula includes an extra IF(filter="All","*",filter) condition for each dropdown, so a wildcard "*" matches everything when a filter is set to "All", and an exact match narrows the results the moment you pick a specific value — no macros required, just COUNTIFS/AVERAGEIFS reading a cell.
... A23: Data cleaning (TRIM, PROPER, IF/IFS text standardization) • Excel Tables • Sorting & filtering • Data Validation dropdown filters • IF / COUNTIF / COUNTIFS / SUMIFS / AVERAGEIFS • SEARCH & TEXT functions • Calculated columns • Pivot-style summary tables • Native Excel charts (bar, column, doughnut) with custom color coding • KPI cards • Conditional formatting • Clean, colorful one-page dashboard design.

Sheet Raw_Data
A1: Job_ID | B1: Job_Title | C1: Company | D1: Location | E1: Industry | F1: Experience_Level | G1: Employment_Type | H1: Work_Mode | I1: Salary_Min | J1: Salary_Max | K1: Required_Skills | L1: Posting_Date
A2: J0375 | B2: Assistant Highway Maintenance Engineer | C2: Theme Engineering Services | D2: Chennai | E2: Manufacturing & Engineering | F2: Mid Level (3-6 yrs) | G2: Full-time | H2: On-site | I2: 2.5 | J2: 3.5 | K2: inspecting and maintaining, Project Handling, Coordination, Nhai | L2: 45966
A3: J0133 | B3: Site Engineer - Track | C3: Consulting Engineers Group (CEG) | D3: Surat | E3: Real Estate & Construction | F3: Mid Level (3-6 yrs) | G3: Full-time | H3: On-site | I3: 6 | J3: 9.5 | L3: 45966
A4: J0344 | B4: Trainer (9 Positions)- Eletrical / Welder / Fittter / Computer (AMLOH) | C4: Kaamkaaj India | D4: Khanna | E4: IT / Software | F4: Entry Level (0-2 yrs) | G4: Full-time | H4: On-site | I4: 1 | J4: 4 | K4: trainer, welder, computer, teacher | L4: 45970
A5: J0033 | B5: Business Development Manager | C5: Scintilla Kreations | D5: Hyderabad | E5: IT / Software | F5: Mid Level (3-6 yrs) | G5: Full-time | H5: On-site | I5: 4.5 | J5: 6 | K5: Business Development, Business Development And Marketing, Branding And Marketing, It Services Sales | L5: 45966
A6: J0061 | B6: B2B Sales Executive | C6: ANK Solar Energy | D6: Surat | E6: Sales & Business Development | F6: Entry Level (0-2 yrs) | G6: Full-time | H6: On-site | I6: 2.5 | J6: 4.5 | K6: B2B Sales, B2B, B2B Business Development, Business To Business | L6: 45973
A7: J0005 | B7: maintenance engineer | C7: Talent Surge | D7: Pune | E7: Manufacturing & Engineering | F7: Mid Level (3-6 yrs) | G7: Full-time | H7: On-site | I7: 4 | J7: 4.5 | K7: Electrical Maintenance, Pneumatic System, Breakdown Maintenance, Preventive Maintenance | L7: 45970
A8: J0386 | B8: Delivery Excellence - ITIL - SA- Professional | C8: Golden Opportunities | D8: Pune | E8: Other / General Business | F8: Mid Level (3-6 yrs) | G8: Full-time | H8: On-site | K8: ITIL, Delivery Excellence, Program Management, Value stream mapping | L8: 45973
A9: J0255 | B9: Civil Engineer | C9: PRO Hr Complete Solutions | D9: Jaipur | E9: Manufacturing & Engineering | F9: Entry Level (0-2 yrs) | G9: Full-time | H9: On-site | I9: 1.75 | J9: 3 | K9: Design Engineering, Drawing, Structural Design, Technical Reports | L9: 45973
A10: J0107 | B10: Senior Cloud Engineer | C10: ZS | D10: Pune | E10: IT / Software | F10: Mid Level (3-6 yrs) | G10: Full-time | H10: On-site | I10: 18 | J10: 33 | K10: kubernetes, security compliance, microsoft azure, devops | L10: 45968
A11: J0160 | B11: Customer Service Executive | C11: Bangalore Watch Company | D11: Bangalore | E11: Customer Service & BPO | F11: Mid Level (3-6 yrs) | G11: Full-time | H11: On-site | I11: 3.6 | J11: 6 | K11: Customer Relationship, Customer Management, Customer Handling, Handling | L11: 45972
A12: J0339 | B12: Interior Designer | C12: Reflections Designs | D12: Mumbai Suburban | E12: Other / General Business | F12: Entry Level (0-2 yrs) | G12: Full-time | H12: On-site | I12: 26.4 | J12: 64.8 | L12: 45974
A13: J0161 | B13: Corporate Sales Manager | C13: Next Vision Business Solution | D13: Hyderabad | E13: BFSI (Banking/Finance/Insurance) | F13: Entry Level (0-2 yrs) | G13: Full-time | H13: On-site | I13: 4 | J13: 4.75 | K13: Sales, Agency Channel, Life Insurance, Broking | L13: 45976
A14: J0245 | B14: Education Counsellor | C14: PRO Hr Complete Solutions | D14: Kolkata | E14: Marketing & Advertising | F14: Entry Level (0-2 yrs) | G14: Full-time | H14: On-site | I14: 1.75 | J14: 2.5 | K14: Admission Counselling, Educational Sales, Lead Generation, Telesales | L14: 45974
A15: J0048 | B15: Senior Web / Full-Stack Developer | C15: Kiya.ai | D15: Chennai | E15: IT / Software | F15: Mid Level (3-6 yrs) | G15: Full-time | H15: Hybrid | I15: 15 | J15: 25 | K15: Frontend Development Skills, Full-Stack Integration, Performance tuning, CSS | L15: 45969
A16: J0003 | B16: AI Automation Professional | C16: Cognizant | D16: Chennai | E16: Other / General Business | F16: Senior Level (7+ yrs) | G16: Full-time | H16: On-site | K16: AI Automation, AI Services, project execution, Automation Gen AI | L16: 45976
A17: J0247 | B17: ASSOCIATE SOFTWARE ENGINEER | C17: Orcapod Consulting Services | D17: Pune | E17: IT / Software | F17: Mid Level (3-6 yrs) | G17: Full-time | H17: On-site | I17: 4 | J17: 9 | K17: MVVM, WPF, Desktop Application, c# | L17: 45976
A18: J0019 | B18: Node Js Developer | C18: V2soft | D18: Bengaluru | E18: IT / Software | F18: Mid Level (3-6 yrs) | G18: Full-time | H18: On-site | I18: 8 | J18: 18 | K18: Node.Js, Microservices, NoSQL, Docker | L18: 45972
A19: J0167 | B19: Uregently Required - Sales Executive | C19: Tekpillar | D19: Jamnagar | E19: IT / Software | F19: Entry Level (0-2 yrs) | G19: Full-time | H19: On-site | I19: 3.5 | J19: 4 | K19: Sales, Field Sales, Banking And Insurance, B2C Sales | L19: 45976
A20: J0081 | B20: Customer Care Executive | C20: Talent Corner Hr Services | D20: Ahmedabad | E20: Other / General Business | F20: Entry Level (0-2 yrs) | G20: Full-time | H20: On-site | I20: 1.5 | J20: 2.5 | K20: Handling Customer Queries, Complaint Handling, Complaint Management, Customer Complaints | L20: 45973
A21: J0234 | B21: Desktop/ Network Engineer (POS application) (Meerut- Agra) | C21: Team Computers | D21: Meerut | E21: IT / Software | F21: Mid Level (3-6 yrs) | G21: Full-time | H21: On-site | I21: 0.5 | J21: 2.75 | K21: Desktop Support, Network Support, OS Installation, Outlook Configuration | L21: 45966
A22: J0096 | B22: Technical/ Service Desk Engineer - chennai | C22: Nsquare It Solutions | D22: Chennai | E22: IT / Software | F22: Entry Level (0-2 yrs) | G22: Full-time | H22: On-site | I22: 1.5 | J22: 4 | K22: Desktop Administration, System Administration, fresher, Desktop Support | L22: 45968
A23: J0098 | B23: Solution Architect | C23: Nitor | D23: Pune | E23: IT / Software | F23: Senior Level (7+ yrs) | G23: Full-time | H23: Hybrid | I23: 18 | J23: 33 | K23: Solution Architecting, Java, Microservices, Architecting | L23: 45973
A24: J0299 | B24: HR compliance | C24: Executives Corridor | D24: Mumbai | E24: Education & Training | F24: Mid Level (3-6 yrs) | G24: Full-time | H24: On-site | K24: Payroll, statutory compliance, challan, Uan | L24: 45966
A25: J0233 | B25: URGENT HIRING MUSIC TEACHER (ANDHRA PRADESH) | C25: Mdn Edify Education | D25: Anantapur | E25: Education & Training | F25: Entry Level (0-2 yrs) | G25: Full-time | H25: On-site | I25: 1.75 | J25: 3.25 | K25: Singing, Music, Classical, Composing | L25: 45972
A26: J0089 | B26: Sales Manager - Indiamart || Gujarat | C26: IndiaMART | D26: Rajkot | E26: Sales & Business Development | F26: Mid Level (3-6 yrs) | G26: Full-time | H26: On-site | K26: Sales, Team Handling, Territory Sales, New Client Acquisition | L26: 45969
A27: J0432 | B27: Business Development Executive | C27: Wenger & Watson | D27: Pune | E27: HR & Staffing | F27: Entry Level (0-2 yrs) | G27: Full-time | H27: On-site | I27: 1.25 | J27: 3 | K27: Lead Generation, Business Development, B2B, New Client Acquisition | L27: 45968
A28: J0229 | B28: Digital Marketing Executive | C28: Verve Global Services | D28: Pune | E28: Marketing & Advertising | F28: Entry Level (0-2 yrs) | G28: Full-time | H28: On-site | I28: 2.4 | J28: 3 | K28: Content Marketing, Social Media Marketing, SEO, Marketing | L28: 45973
A29: J0403 | B29: Zonal Head Sales | C29: Workex | D29: Ahmedabad | E29: Sales & Business Development | F29: Mid Level (3-6 yrs) | G29: Full-time | H29: On-site | I29: 5 | J29: 10 | K29: Dealer Sales, Distributor Sales, Channel Sales, HVAC | L29: 45967
A30: J0387 | B30: Quality & MR -CNC & VMC Production line , Pune Chakan | C30: HR Innovation Group | D30: Pune | E30: Manufacturing & Engineering | F30: Senior Level (7+ yrs) | G30: Full-time | H30: On-site | I30: 5 | J30: 6 | K30: ISO, IATF, QMS, Quality System Management | L30: 45973
A31: J0221 | B31: Operations Executive | C31: Indian Institute of Emergency Medical Services(IIEMS) | D31: Kottayam | E31: Customer Service & BPO | F31: Entry Level (0-2 yrs) | G31: Full-time | H31: On-site | K31: back office, back office operations, customer service, pivot table | L31: 45968
A32: J0395 | B32: Civil Site Engineer | C32: Workart Hr Solutions | D32: Palitana | E32: Manufacturing & Engineering | F32: Mid Level (3-6 yrs) | G32: Full-time | H32: On-site | I32: 3 | J32: 7 | K32: Site Engineering, Site Planning, Site Management, Site Supervision | L32: 45969
A33: J0100 | B33: Urgent Hiring - Relationship Manager | C33: Supro Consulting | D33: Haldwani | E33: IT / Software | F33: Entry Level (0-2 yrs) | G33: Full-time | H33: On-site | I33: 3 | J33: 3.75 | K33: Sales, Team Handling, Credit Card Sales, Telesales | L33: 45970
A34: J0365 | B34: Accounts Officer | C34: DMart | D34: Rajpura | E34: BFSI (Banking/Finance/Insurance) | F34: Mid Level (3-6 yrs) | G34: Full-time | H34: On-site | I34: 3 | J34: 4.75 | K34: MIS, Daily Expense, Bank Reconciliation, Accounting | L34: 45976
A35: J0423 | B35: Technical/ Service Desk Engineer - chennai | C35: Nsquare It Solutions | D35: Chennai | E35: IT / Software | F35: Entry Level (0-2 yrs) | G35: Full-time | H35: On-site | I35: 1.5 | J35: 4 | K35: Desktop Administration, System Administration, fresher, Desktop Support | L35: 45968
A36: J0340 | B36: Placement Coordinator | C36: The World Of Automation | D36: Pune | E36: Sales & Business Development | F36: Entry Level (0-2 yrs) | G36: Full-time | H36: On-site | I36: 1.8 | J36: 3.6 | K36: Placement Coordination, Business Tie Ups, Corporate Relations, Skill Development | L36: 45970
A37: J0195 | B37: Logistics In charge - Fly Ash | C37: Refex Industries | D37: Ramagundam | E37: Logistics & Supply Chain | F37: Mid Level (3-6 yrs) | G37: Full-time | H37: On-site | I37: 4 | J37: 7 | K37: Fleet Management, Logistics Operations, Logistics, Management | L37: 45973
A38: J0376 | B38: WFH, French Voice process, sal up To 5.4 lpa | C38: Creative Hands HR | D38: Remote | E38: Customer Service & BPO | F38: Entry Level (0-2 yrs) | G38: Full-time | H38: Remote | I38: 3.5 | J38: 5.5 | K38: Marathi, Assamese, Bengali, voice process | L38: 45968
A39: J0346 | B39: SQL Developer | C39: F&F Consulting Services | D39: Panchkula | E39: IT / Software | F39: Mid Level (3-6 yrs) | G39: Full-time | H39: On-site | I39: 6 | J39: 7 | K39: SQL Development, optimizing database, complex SQL queries, SQL queries | L39: 45967
A40: J0128 | B40: SR FrontEnd Developer (Angular) | C40: Seven N Consulting | D40: Pune | E40: IT / Software | F40: Mid Level (3-6 yrs) | G40: Full-time | H40: On-site | K40: IT services, CSS, Web technologies, Front end | L40: 45973
A41: J0016 | B41: Relationship Manager-AGRI-FIN-TRACTOR LOANS AND RETAIL(TFE) | C41: Kotak Mahindra Bank | D41: Udaipur | E41: BFSI (Banking/Finance/Insurance) | F41: Entry Level (0-2 yrs) | G41: Full-time | H41: On-site | K41: Service delivery, Loans, Interpersonal skills, Ticketing | L41: 45969
A42: J0140 | B42: Production Chemist | C42: Sun Chem | D42: Palghar | E42: Manufacturing & Engineering | F42: Entry Level (0-2 yrs) | G42: Full-time | H42: On-site | I42: 0.5 | J42: 3 | K42: Chemistry, Production, GMP, production chemist | L42: 45969
A43: J0378 | B43: Looking For B.Tech Graduate Candidates. | C43: Krezig Consultants | D43: Noida | E43: IT / Software | F43: Entry Level (0-2 yrs) | G43: Full-time | H43: On-site | I43: 4 | J43: 8 | K43: Data Science, Data Analytics, data analyst, Power Bi | L43: 45974
A44: J0058 | B44: Quality Head Paint Shop , chakan | C44: HR Innovation Group | D44: Nashik | E44: IT / Software | F44: Senior Level (7+ yrs) | G44: Full-time | H44: On-site | I44: 8 | J44: 11 | K44: Paint Quality, ISO, Paint Technology, IATF | L44: 45972
A45: J0433 | B45: Lawyer (Chandigarh) | C45: Research Development Office | D45: Chandigarh | E45: Other / General Business | F45: Entry Level (0-2 yrs) | G45: Full-time | H45: On-site | I45: 6.5 | J45: 7.5 | K45: Legal, Law, Llb, Legal Advice | L45: 45969
A46: J0382 | B46: Workday Finance- Manager | C46: Vision Beyond Resources India Private Limited | D46: Bangalore | E46: BFSI (Banking/Finance/Insurance) | F46: Mid Level (3-6 yrs) | G46: Full-time | H46: On-site | K46: Business process, Strategy consulting, ERP, Networking | L46: 45969
A47: J0018 | B47: Quality Engineer - Machine Shop | C47: Motherson | D47: Kanchipuram | E47: Manufacturing & Engineering | F47: Entry Level (0-2 yrs) | G47: Full-time | H47: On-site | I47: 3.5 | J47: 5.5 | K47: Machine Shop Quality, CNC Machines, VMC Machine, Line Inspection | L47: 45969
A48: J0198 | B48: Lawyer (Chandigarh) | C48: Research Development Office | D48: Chandigarh | E48: Other / General Business | F48: Entry Level (0-2 yrs) | G48: Full-time | H48: On-site | I48: 6.5 | J48: 7.5 | K48: Legal, Law, Llb, Legal Advice | L48: 45969
A49: J0294 | B49: Paint Protection Film (PPF) manager -automotive accessories, detailing | C49: HR Innovation Group | D49: Nashik | E49: Media & Entertainment | F49: Mid Level (3-6 yrs) | G49: Full-time | H49: On-site | I49: 5 | J49: 6 | K49: detailing, automotive accessories, Paint Protection Film, Automobile Components | L49: 45970
A50: J0243 | B50: Senior Data Engineer | C50: Assent Inc | D50: Pune | E50: IT / Software | F50: Senior Level (7+ yrs) | G50: Full-time | H50: Hybrid | I50: 30 | J50: 40 | K50: Airflow, Snowflake, AWS, Python | L50: 45968
A51: J0056 | B51: Sales and Outreach Specialist | C51: Early Autism Ventures | D51: Bengaluru | E51: Sales & Business Development | F51: Entry Level (0-2 yrs) | G51: Full-time | H51: Hybrid | K51: Problem Solving/ Analysis, Stratergic Thinking, Communication Proficiency, Presentation Skills | L51: 45972
A52: J0156 | B52: Cad Design Engineer | C52: PRO Hr Complete Solutions | D52: Mumbai | E52: Other / General Business | F52: Mid Level (3-6 yrs) | G52: Full-time | H52: On-site | I52: 2.75 | J52: 3.75 | K52: OHSAS 18001, 14001, Iso Ts 9, AutoCAD 2D | L52: 45973
A53: J0123 | B53: Physics,Chemistry,Math | C53: Jahangeer Edutech | D53: Vijayawada | E53: Other / General Business | F53: Mid Level (3-6 yrs) | G53: Full-time | H53: On-site | I53: 20 | J53: 35 | K53: Physics, Chemistry, Mathematics | L53: 45967
A54: J0090 | B54: Human Resource Intern | C54: Kotak Life Insurance | D54: Goregaon | E54: HR & Staffing | F54: Entry Level (0-2 yrs) | G54: Internship | H54: On-site | I54: 1.5 | J54: 1.75 | K54: HR Coordination, HR Generalist Activities, HR Administration, HR Operations | L54: 45974
A55: J0196 | B55: Job Openings For Surgery Medical Coders @ Vee Healthtek | C55: Vee Healthtek | D55: Hyderabad | E55: Healthcare & Pharma | F55: Entry Level (0-2 yrs) | G55: Full-time | H55: On-site | I55: 1.5 | J55: 5 | K55: medical coder, ICD, Medical Coding, surgery | L55: 45966
A56: J0362 | B56: Voice/Chat CSE, international & domestic both @Mohali | C56: White Bulb Technologies India | D56: Mohali | E56: Customer Service & BPO | F56: Entry Level (0-2 yrs) | G56: Internship | H56: On-site | I56: 1.75 | J56: 4.25 | K56: Query Resolution, Customer Support, Customer Care, VOICE/NON VOICE | L56: 45970
A57: J0166 | B57: E Commerce Executive | C57: PRO Hr Complete Solutions | D57: Mysuru | E57: Marketing & Advertising | F57: Entry Level (0-2 yrs) | G57: Full-time | H57: On-site | I57: 3 | J57: 3.75 | K57: E-commerce, Performance Metrics, PPC, Sales Forecasting | L57: 45974
A58: J0414 | B58: Sales Executive | C58: Shree Ganesh Remedies | D58: Bharuch | E58: Sales & Business Development | F58: Entry Level (0-2 yrs) | G58: Full-time | H58: On-site | I58: 1 | J58: 2.75 | K58: Excellent communication, Good problem-solving, negotiation, Target-driven with a proven track record in sales. | L58: 45968
A59: J0289 | B59: Plc Programmer | C59: Talent Corner Hr Services | D59: Navi Mumbai | E59: Other / General Business | F59: Mid Level (3-6 yrs) | G59: Full-time | H59: On-site | I59: 8 | J59: 12 | K59: Plc Scada, Schneider Plc, PLC, Siemens PLC | L59: 45974
A60: J0357 | B60: Sr. Manager - Loan Servicing/Lending Operations || Chennai | C60: Imaginators Try Going Beyond | D60: Chennai | E60: BFSI (Banking/Finance/Insurance) | F60: Senior Level (7+ yrs) | G60: Full-time | H60: On-site | I60: 18 | J60: 27.5 | K60: Commercial Loans, Commercial Lending, Lending Operations, Loan Processing | L60: 45974
A61: J0125 | B61: Mid Software Developer | C61: Expian Technologies | D61: Bengaluru | E61: IT / Software | F61: Mid Level (3-6 yrs) | G61: Full-time | H61: Hybrid | I61: 20 | J61: 32.5 | K61: Aws Cloud, Ruby Rails, react, Java | L61: 45970
A62: J0322 | B62: Sales Manager (The Fern Residency, Chembur) | C62: Concept Hospitality | D62: Mumbai Suburban | E62: Healthcare & Pharma | F62: Mid Level (3-6 yrs) | G62: Full-time | H62: On-site | I62: 3 | J62: 8 | K62: Room Sales, Hospitality Sales, Hotel Sales, Hotel Management | L62: 45970
A63: J0413 | B63: Indesign Executive- Graphic Designer | C63: Henry Harvin Education | D63: Noida | E63: Other / General Business | F63: Entry Level (0-2 yrs) | G63: Full-time | H63: On-site | I63: 2.25 | J63: 3.5 | K63: Corel Draw, Illustrate Design, Photoshop, Indesign | L63: 45976
... A67: J0311 | B67: Sales Coordinator | M/F | Automotive | 30 To 35k | Bahalgarh | Sonipat | C67: Dharra Advance Business Solutions | D67: Sonipat | E67: Marketing & Advertising | F67: Mid Level (3-6 yrs) | G67: Full-time | H67: On-site | I67: 3.5 | J67: 4.25 | K67: Sales Operations, Excellent Communication In English, Good In Excel, Sales Coordination | L67: 45966
A68: J0427 | B68: Loan Officer - Retail MFB - Sales | C68: Tata Capital | D68: Mumbai | E68: BFSI (Banking/Finance/Insurance) | F68: Entry Level (0-2 yrs) | G68: Full-time | H68: On-site | K68: microfinance, customer service, sourcing, delinquency management | L68: 45967
A69: J0176 | B69: Technical Lead-(GCP/Azure, Node.js & TypeS ,5+ Years,Remote) | C69: Novizco Infotech | D69: Remote | E69: IT / Software | F69: Mid Level (3-6 yrs) | G69: Full-time | H69: Remote | I69: 12 | J69: 20 | K69: Cloud Deployment, Node.Js, GCP, Azure Cloud | L69: 45973
A70: J0024 | B70: Hiring - International Voice Process - Firstsource | Alorica | 247.ai | C70: Circle Consulting | D70: Bengaluru | E70: Customer Service & BPO | F70: Entry Level (0-2 yrs) | G70: Internship | H70: On-site | I70: 2.5 | J70: 4.25 | K70: Customer Service, International Voice, International Call Center, call center | L70: 45974
A71: J0212 | B71: Gen AI Architect | C71: Xebia It Architects | D71: Pune | E71: IT / Software | F71: Senior Level (7+ yrs) | G71: Full-time | H71: Hybrid | I71: 45 | J71: 50 | K71: GenAI, Agentic AI, AWS Bedrock, Python | L71: 45966
A72: J0139 | B72: Lead Sales Officer | C72: Haarvard Management Consultants | D72: Chennai | E72: Manufacturing & Engineering | F72: Mid Level (3-6 yrs) | G72: Full-time | H72: On-site | I72: 10 | J72: 13 | L72: 45973
A73: J0032 | B73: Sales And Logistics Manager | C73: Skyocean Shipping | D73: Malappuram | E73: Logistics & Supply Chain | F73: Entry Level (0-2 yrs) | G73: Full-time | H73: On-site | I73: 3 | J73: 4.8 | K73: Logistics Sales, English, Freight Forwarding, International Logistics | L73: 45973
A74: J0040 | B74: Mechanical Design Engineer - PQA / Chennai | C74: Inncon | D74: Chennai | E74: Manufacturing & Engineering | F74: Mid Level (3-6 yrs) | G74: Full-time | H74: On-site | I74: 5 | J74: 10 | K74: AutoCAD, Piping And Instrumentation Diagram, Water Treatment, Autodesk Inventor | L74: 45968
A75: J0073 | B75: Area Sales Manager | C75: Skillventory | D75: Mysuru | E75: BFSI (Banking/Finance/Insurance) | F75: Entry Level (0-2 yrs) | G75: Full-time | H75: On-site | I75: 7 | J75: 15 | K75: Personal Loans, Team Handling, DSA, Unsecured Loans | L75: 45967
A76: J0035 | B76: Senior Developer | C76: Tata Consultancy Services | D76: Hyderabad | E76: IT / Software | F76: Senior Level (7+ yrs) | G76: Full-time | H76: On-site | K76: Ge Smallworld, Magik, Development, Smallworld | L76: 45973
A77: J0351 | B77: Sr HR Executive - MNC Pune | C77: HR Innovation Group | D77: Nashik | E77: HR & Staffing | F77: Mid Level (3-6 yrs) | G77: Full-time | H77: On-site | I77: 4 | J77: 9 | K77: HR Generalist Activities, Performance Management System, Labour Laws, Employee Grievances | L77: 45972
A78: J0182 | B78: Business Development Executive | C78: Nlet Solutions | D78: Jaipur | E78: Sales & Business Development | G78: Full-time | H78: On-site | I78: 1.44 | J78: 2.88 | K78: B2B Sales, English, Sales, Lead Generation | L78: 45972
A79: J0268 | B79: senior manager - infrastructure procurement | C79: Flipkart | D79: Bengaluru | E79: Logistics & Supply Chain | F79: Senior Level (7+ yrs) | G79: Full-time | H79: On-site | I79: 20 | J79: 25 | K79: Warehouse, infrastructure procurement, storage racking, facility procurement | L79: 45974
A80: J0175 | B80: Front Office Associate | C80: Hilton | D80: Bengaluru | E80: Healthcare & Pharma | F80: Entry Level (0-2 yrs) | G80: Full-time | H80: On-site | K80: Housekeeping, Hospitality, Front Office Associate, Front desk | L80: 45973
A81: J0194 | B81: Gen AI / ML Data Scientist - Lead | C81: Vikruthi Technologies | D81: Chennai | E81: IT / Software | F81: Mid Level (3-6 yrs) | G81: Full-time | H81: On-site | I81: 16 | J81: 20 | K81: Machine Learning, Data Science, Gen AI, Data Scientist | L81: 45973
A82: J0043 | B82: Jr Accountant | C82: Hayat Placement Services | D82: Kanpur | E82: BFSI (Banking/Finance/Insurance) | F82: Entry Level (0-2 yrs) | G82: Full-time | H82: On-site | I82: 1.5 | J82: 2.5 | K82: Junior Accountant, Accounts, Accounting | L82: 45972
A83: J0273 | B83: Video Editor or Videographer | C83: Ifinsol Global | D83: Bengaluru | E83: Media & Entertainment | F83: Mid Level (3-6 yrs) | G83: Full-time | H83: Hybrid | K83: Adobe Creative Suite, Video Editing, Videography, Editing | L83: 45976
A84: J0091 | B84: Video Editor | C84: Reva Hr Consultancy | D84: Noida | E84: Marketing & Advertising | F84: Mid Level (3-6 yrs) | G84: Full-time | H84: On-site | I84: 3.6 | J84: 4.8 | K84: Adobe Premiere Pro, Video Editing, Audio Editing, Composing | L84: 45973
A85: J0410 | B85: Divisional Manager - Tied Agency | C85: Kotak Life Insurance | D85: Nagpur | E85: Sales & Business Development | F85: Senior Level (7+ yrs) | G85: Full-time | H85: On-site | I85: 14 | J85: 17 | K85: Agency Development, Tied Channel, Agency Channel, Branch Management | L85: 45968
A86: J0014 | B86: BPO VOICE Process-Telugu/TAMIL/Malayalam/Kannada | C86: Takecare Manpower Services | D86: Chennai | E86: Customer Service & BPO | F86: Entry Level (0-2 yrs) | G86: Full-time | H86: On-site | I86: 1.5 | J86: 2.25 | K86: Communication Skills, Verbal Communication, Interpersonal Skills, Interpersonal | L86: 45972
A87: J0278 | B87: Individual Relationship Officer - HL | C87: SMFG INDIA CREDIT COMPANY | D87: Nanjangud | E87: BFSI (Banking/Finance/Insurance) | F87: Entry Level (0-2 yrs) | G87: Full-time | H87: On-site | I87: 2.5 | J87: 3.5 | K87: Housing Finance, Housing Loan, Sales, Mortgage Loans | L87: 45970
A88: J0037 | B88: Plant Manager | C88: Dlecta Foods | D88: Khopoli | E88: Manufacturing & Engineering | F88: Senior Level (7+ yrs) | G88: Full-time | H88: On-site | K88: Production, Factory manager, Food Processing, Production head | L88: 45966
A89: J0072 | B89: Wipro-Workday HCM-PAN INDIA | C89: Wroots Global | D89: Pune | E89: Other / General Business | F89: Senior Level (7+ yrs) | G89: Full-time | H89: Hybrid | I89: 25 | J89: 35 | K89: Configuration, Workday Hcm, Core Hcm, Workday | L89: 45974
A90: J0334 | B90: Assistant Sales Manager - Proactive | C90: Naukri Hospitality Jobs | D90: Mumbai | E90: Marketing & Advertising | F90: Mid Level (3-6 yrs) | G90: Full-time | H90: On-site | K90: networking, sales analytics, sales, sales management | L90: 45973
A91: J0070 | B91: Bulk Hiring // Voice Process, Blended & chat proces // Salary upto 38k | C91: Steady Career Consultant | D91: Delhi | E91: Hospitality & Travel | F91: Entry Level (0-2 yrs) | G91: Full-time | H91: On-site | I91: 2 | J91: 6 | K91: Barclays, Admiral Solutions, Us Voice Process, International Voice Process | L91: 45973
A92: J0316 | B92: Orthopedician JOB IN Tiruppur, Tamilnadu, INDIA | C92: Migrate Medico | D92: Tiruppur | E92: Other / General Business | F92: Mid Level (3-6 yrs) | G92: Full-time | H92: On-site | I92: 18 | J92: 25 | K92: MS, ORTHOPEDICIAN, CONSULTANT ORTHOPEDICIAN, Microsoft | L92: 45973
A93: J0259 | B93: Cybersecurity Specialist / Analyst | C93: ti Steps | D93: Hyderabad | E93: IT / Software | F93: Entry Level (0-2 yrs) | G93: Full-time | H93: On-site | I93: 2.5 | J93: 4.5 | K93: Openvas, Cyber Security, SIEM, IDS | L93: 45973
A94: J0110 | B94: Customer Support Executive - Call now - HR HUDA | C94: KVC CONSULTANTS LTD | D94: Gurugram | E94: HR & Staffing | F94: Entry Level (0-2 yrs) | G94: Full-time | H94: On-site | I94: 2.5 | J94: 4.75 | K94: International Voice Process, BPO, Fluent English, Bpo Customer Service | L94: 45973
A95: J0163 | B95: Accessories & Procurement Manager - Delhi | C95: Galaxy Automobiles | D95: Gurugram | E95: Logistics & Supply Chain | F95: Senior Level (7+ yrs) | G95: Full-time | H95: On-site | I95: 0.5 | J95: 0.9 | K95: commodities sales, vehicle accessories, Business Development, corporate sales | L95: 45970
A96: J0022 | B96: Safety Officer | C96: Arvind Limited | D96: Arsikere | E96: BFSI (Banking/Finance/Insurance) | F96: Entry Level (0-2 yrs) | G96: Full-time | H96: On-site | I96: 2.25 | J96: 3.5 | K96: Safety Officer Activities, Safety Compliance, Safety Audit, Auditing | L96: 45973
A97: J0266 | B97: Paintshop Maintenance In-Charge (Mechanical & Electrical) | C97: Shri Ekvira Manufacturers And Coats Private Limite D | D97: Nashik | E97: Manufacturing & Engineering | F97: Mid Level (3-6 yrs) | G97: Full-time | H97: On-site | I97: 0.5 | J97: 0.9 | K97: KNOWLEDGE OF Conveyors, Gearboxes, Paint circulation system maintenance, Spray booth & oven maintenance | L97: 45973
A98: J0075 | B98: CSSD Technician | C98: Surya Hospital | D98: Pune | E98: Other / General Business | F98: Entry Level (0-2 yrs) | G98: Full-time | H98: On-site | I98: 2 | J98: 3 | K98: CSSD TECHNICIAN CERTIFICATION | L98: 45976
A99: J0168 | B99: Environmental Health and Safety Officer | C99: NMS Consultants | D99: Gurugram | E99: Healthcare & Pharma | F99: Senior Level (7+ yrs) | G99: Full-time | H99: On-site | I99: 11 | J99: 12 | K99: Iso Standards, HIRA, EHS training, Ehs Compliance | L99: 45974
A100: J0193 | B100: Sr Java Developer | C100: BMC Software | D100: Pune | E100: IT / Software | F100: Senior Level (7+ yrs) | G100: Full-time | H100: On-site | I100: 30 | J100: 40 | K100: microservices, spring boot, java, java application development | L100: 45966
A101: J0082 | B101: Data Analyst | C101: Techno Facts Solutions | D101: bengaluru | E101: IT / Software | F101: Mid Level (3-6 yrs) | G101: Full-time | H101: On-site | I101: 10 | J101: 20 | K101: data analysis, Power Bi, Big Data, data engineering | L101: 45969
A102: J0306 | B102: Application Specialist RTR | C102: Lixil Asia | D102: Gurugram | E102: IT / Software | F102: Entry Level (0-2 yrs) | G102: Full-time | H102: On-site | K102: sap s hana, sap fiori, sap basis, presentation skills | L102: 45968
A103: J0384 | B103: Accounts Payable Executive | C103: Remunance Systems | D103: Pune | E103: BFSI (Banking/Finance/Insurance) | F103: Entry Level (0-2 yrs) | G103: Full-time | H103: On-site | I103: 3 | J103: 6 | K103: Vendor Payments, Invoice Processing, Gst, Zoho Books | L103: 45972
...

Sheet Cleaned_Data
A1: Data Cleaning Steps Applied (see Raw_Data → Cleaned_Data)
A2: 1. Removed extra spaces from text fields using TRIM.
A3: 2. Standardized text casing (e.g. job titles) using PROPER.
A4: 3. Standardized location spellings (Bangalore→Bengaluru, Gurgaon→Gurugram, New Delhi→Delhi) using IF.
A5: 4. Filled missing Experience_Level and Required_Skills with "Not Specified" using IF, instead of leaving blank cells.
A6: 5. Checked Salary_Min/Salary_Max are numeric; postings with "Not Disclosed" salary are left blank (excluded automatically from salary averages).
A7: 6. Flagged duplicate postings (same title, company, location and date) using a COUNTIFS-based Duplicate_Flag column; duplicates are excluded from the Analysis sheet.
A8: 7. Added calculated columns: Average_Salary, Salary_Range, Posting_Month, and Job_Role_Category (grouping similar job titles using SEARCH + IFS).
A10: Job_ID | B10: Job_Title | C10: Company | D10: Location | E10: Industry | F10: Experience_Level | G10: Employment_Type | H10: Work_Mode | I10: Salary_Min | J10: Salary_Max | K10: Required_Skills | L10: Posting_Date | M10: Average_Salary | N10: Salary_Range | O10: Posting_Month | P10: Job_Role_Category | Q10: Duplicate_Flag
A11: =Raw_Data!A2 | B11: =PROPER(TRIM(Raw_Data!B2)) | C11: =TRIM(Raw_Data!C2) | D11: =IF(PROPER(TRIM(Raw_Data!D2))="Bangalore","Bengaluru",IF(PROPER(TRIM(Raw_Data!D2))="Gurgaon","Gurugram",IF(OR(PROPER(TRIM(Raw_Data!D2))="New Delhi",PROPER(TRIM(Raw_Data!D2))="Delhi"),"Delhi",PROPER(TRIM(Raw_Data!D2))))) | E11: =Raw_Data!E2 | F11: =IF(TRIM(Raw_Data!F2&"")="","Not Specified",Raw_Data!F2) | G11: =Raw_Data!G2 | H11: =Raw_Data!H2 | I11: =IF(Raw_Data!I2="","",Raw_Data!I2) | J11: =IF(Raw_Data!J2="","",Raw_Data!J2) | K11: =IF(TRIM(Raw_Data!K2&"")="","Not Specified",Raw_Data!K2) | L11: =Raw_Data!L2 | M11: =IF(OR(I11="",J11=""),"",(I11+J11)/2) | N11: =IF(OR(I11="",J11=""),"",J11-I11) | O11: =TEXT(L11,"mmm-yyyy") | P11: =_xlfn.IFS(ISNUMBER(SEARCH("data analy",B11)),"Data Analyst",ISNUMBER(SEARCH("business analy",B11)),"Business Analyst",OR(ISNUMBER(SEARCH("developer",B11)),ISNUMBER(SEARCH("software engineer",B11)),ISNUMBER(SEARCH("programmer",B11))),"Software Developer",ISNUMBER(SEARCH("business development",B11)),"Business Development",ISNUMBER(SEARCH("sales",B11)),"Sales Executive",ISNUMBER(SEARCH("marketing",B11)),"Marketing Executive",OR(ISNUMBER(SEARCH("hr ",B11)),ISNUMBER(SEARCH("recruit",B11)),ISNUMBER(SEARCH("human resource",B11))),"HR / Recruiter",OR(ISNUMBER(SEARCH("account",B11)),ISNUMBER(SEARCH("finance",B11)),ISNUMBER(SEARCH("tax",B11)),ISNUMBER(SEARCH("audit",B11))),"Accountant / Finance",OR(ISNUMBER(SEARCH("customer service",B11)),ISNUMBER(SEARCH("customer support",B11)),ISNUMBER(SEARCH("customer care",B11)),ISNUMBER(SEARCH("voice process",B11)),ISNUMBER(SEARCH("bpo",B11))),"Customer Support",ISNUMBER(SEARCH("engineer",B11)),"Engineer (Technical)",ISNUMBER(SEARCH("manager",B11)),"Manager",OR(ISNUMBER(SEARCH("teacher",B11)),ISNUMBER(SEARCH("trainer",B11)),ISNUMBER(SEARCH("faculty",B11))),"Teacher / Trainer",OR(ISNUMBER(SEARCH("doctor",B11)),ISNUMBER(SEARCH("nurse",B11)),ISNUMBER(SEARCH("medical",B11)),ISNUMBER(SEARCH("pharma",B11)),ISNUMBER(SEARCH("clinical",B11))),"Healthcare",TRUE,"Other") | Q11: =IF(COUNTIFS($B$11:B11,B11,$C$11:C11,C11,$D$11:D11,D11,$L$11:L11,L11)>1,"Duplicate","Unique")
A12: =Raw_Data!A3 | B12: =PROPER(TRIM(Raw_Data!B3)) | C12: =TRIM(Raw_Data!C3) | D12: =IF(PROPER(TRIM(Raw_Data!D3))="Bangalore","Bengaluru",IF(PROPER(TRIM(Raw_Data!D3))="Gurgaon","Gurugram",IF(OR(PROPER(TRIM(Raw_Data!D3))="New Delhi",PROPER(TRIM(Raw_Data!D3))="Delhi"),"Delhi",PROPER(TRIM(Raw_Data!D3))))) | E12: =Raw_Data!E3 | F12: =IF(TRIM(Raw_Data!F3&"")="","Not Specified",Raw_Data!F3) | G12: =Raw_Data!G3 | H12: =Raw_Data!H3 | I12: =IF(Raw_Data!I3="","",Raw_Data!I3) | J12: =IF(Raw_Data!J3="","",Raw_Data!J3) | K12: =IF(TRIM(Raw_Data!K3&"")="","Not Specified",Raw_Data!K3) | L12: =Raw_Data!L3 | M12: =IF(OR(I12="",J12=""),"",(I12+J12)/2) | N12: =IF(OR(I12="",J12=""),"",J12-I12) | O12: =TEXT(L12,"mmm-yyyy") | P12: =_xlfn.IFS(ISNUMBER(SEARCH("data analy",B12)),"Data Analyst",ISNUMBER(SEARCH("business analy",B12)),"Business Analyst",OR(ISNUMBER(SEARCH("developer",B12)),ISNUMBER(SEARCH("software engineer",B12)),ISNUMBER(SEARCH("programmer",B12))),"Software Developer",ISNUMBER(SEARCH("business development",B12)),"Business Development",ISNUMBER(SEARCH("sales",B12)),"Sales Executive",ISNUMBER(SEARCH("marketing",B12)),"Marketing Executive",OR(ISNUMBER(SEARCH("hr ",B12)),ISNUMBER(SEARCH("recruit",B12)),ISNUMBER(SEARCH("human resource",B12))),"HR / Recruiter",OR(ISNUMBER(SEARCH("account",B12)),ISNUMBER(SEARCH("finance",B12)),ISNUMBER(SEARCH("tax",B12)),ISNUMBER(SEARCH("audit",B12))),"Accountant / Finance",OR(ISNUMBER(SEARCH("customer service",B12)),ISNUMBER(SEARCH("customer support",B12)),ISNUMBER(SEARCH("customer care",B12)),ISNUMBER(SEARCH("voice process",B12)),ISNUMBER(SEARCH("bpo",B12))),"Customer Support",ISNUMBER(SEARCH("engineer",B12)),"Engineer (Technical)",ISNUMBER(SEARCH("manager",B12)),"Manager",OR(ISNUMBER(SEARCH("teacher",B12)),ISNUMBER(SEARCH("trainer",B12)),ISNUMBER(SEARCH("faculty",B12))),"Teacher / Trainer",OR(ISNUMBER(SEARCH("doctor",B12)),ISNUMBER(SEARCH("nurse",B12)),ISNUMBER(SEARCH("medical",B12)),ISNUMBER(SEARCH("pharma",B12)),ISNUMBER(SEARCH("clinical",B12))),"Healthcare",TRUE,"Other") | Q12: =IF(COUNTIFS($B$11:B12,B12,$C$11:C12,C12,$D$11:D12,D12,$L$11:L12,L12)>1,"Duplicate","Unique")
A13: =Raw_Data!A4 | B13: =PROPER(TRIM(Raw_Data!B4)) | C13: =TRIM(Raw_Data!C4) | D13: =IF(PROPER(TRIM(Raw_Data!D4))="Bangalore","Bengaluru",IF(PROPER(TRIM(Raw_Data!D4))="Gurgaon","Gurugram",IF(OR(PROPER(TRIM(Raw_Data!D4))="New Delhi",PROPER(TRIM(Raw_Data!D4))="Delhi"),"Delhi",PROPER(TRIM(Raw_Data!D4))))) | E13: =Raw_Data!E4 | F13: =IF(TRIM(Raw_Data!F4&"")="","Not Specified",Raw_Data!F4) | G13: =Raw_Data!G4 | H13: =Raw_Data!H4 | I13: =IF(Raw_Data!I4="","",Raw_Data!I4) | J13: =IF(Raw_Data!J4="","",Raw_Data!J4) | K13: =IF(TRIM(Raw_Data!K4&"")="","Not Specified",Raw_Data!K4) | L13: =Raw_Data!L4 | M13: =IF(OR(I13="",J13=""),"",(I13+J13)/2) | N13: =IF(OR(I13="",J13=""),"",J13-I13) | O13: =TEXT(L13,"mmm-yyyy") | P13: =_xlfn.IFS(ISNUMBER(SEARCH("data analy",B13)),"Data Analyst",ISNUMBER(SEARCH("business analy",B13)),"Business Analyst",OR(ISNUMBER(SEARCH("developer",B13)),ISNUMBER(SEARCH("software engineer",B13)),ISNUMBER(SEARCH("programmer",B13))),"Software Developer",ISNUMBER(SEARCH("business development",B13)),"Business Development",ISNUMBER(SEARCH("sales",B13)),"Sales Executive",ISNUMBER(SEARCH("marketing",B13)),"Marketing Executive",OR(ISNUMBER(SEARCH("hr ",B13)),ISNUMBER(SEARCH("recruit",B13)),ISNUMBER(SEARCH("human resource",B13))),"HR / Recruiter",OR(ISNUMBER(SEARCH("account",B13)),ISNUMBER(SEARCH("finance",B13)),ISNUMBER(SEARCH("tax",B13)),ISNUMBER(SEARCH("audit",B13))),"Accountant / Finance",OR(ISNUMBER(SEARCH("customer service",B13)),ISNUMBER(SEARCH("customer support",B13)),ISNUMBER(SEARCH("customer care",B13)),ISNUMBER(SEARCH("voice process",B13)),ISNUMBER(SEARCH("bpo",B13))),"Customer Support",ISNUMBER(SEARCH("engineer",B13)),"Engineer (Technical)",ISNUMBER(SEARCH("manager",B13)),"Manager",OR(ISNUMBER(SEARCH("teacher",B13)),ISNUMBER(SEARCH("trainer",B13)),ISNUMBER(SEARCH("faculty",B13))),"Teacher / Trainer",OR(ISNUMBER(SEARCH("doctor",B13)),ISNUMBER(SEARCH("nurse",B13)),ISNUMBER(SEARCH("medical",B13)),ISNUMBER(SEARCH("pharma",B13)),ISNUMBER(SEARCH("clinical",B13))),"Healthcare",TRUE,"Other") | Q13: =IF(COUNTIFS($B$11:B13,B13,$C$11:C13,C13,$D$11:D13,D13,$L$11:L13,L13)>1,"Duplicate","Unique")
A14: =Raw_Data!A5 | B14: =PROPER(TRIM(Raw_Data!B5)) | C14: =TRIM(Raw_Data!C5) | D14: =IF(PROPER(TRIM(Raw_Data!D5))="Bangalore","Bengaluru",IF(PROPER(TRIM(Raw_Data!D5))="Gurgaon","Gurugram",IF(OR(PROPER(TRIM(Raw_Data!D5))="New Delhi",PROPER(TRIM(Raw_Data!D5))="Delhi"),"Delhi",PROPER(TRIM(Raw_Data!D5))))) | E14: =Raw_Data!E5 | F14: =IF(TRIM(Raw_Data!F5&"")="","Not Specified",Raw_Data!F5) | G14: =Raw_Data!G5 | H14: =Raw_Data!H5 | I14: =IF(Raw_Data!I5="","",Raw_Data!I5) | J14: =IF(Raw_Data!J5="","",Raw_Data!J5) | K14: =IF(TRIM(Raw_Data!K5&"")="","Not Specified",Raw_Data!K5) | L14: =Raw_Data!L5 | M14: =IF(OR(I14="",J14=""),"",(I14+J14)/2) | N14: =IF(OR(I14="",J14=""),"",J14-I14) | O14: =TEXT(L14,"mmm-yyyy") | P14: =_xlfn.IFS(ISNUMBER(SEARCH("data analy",B14)),"Data Analyst",ISNUMBER(SEARCH("business analy",B14)),"Business Analyst",OR(ISNUMBER(SEARCH("developer",B14)),ISNUMBER(SEARCH("software engineer",B14)),ISNUMBER(SEARCH("programmer",B14))),"Software Developer",ISNUMBER(SEARCH("business development",B14)),"Business Development",ISNUMBER(SEARCH("sales",B14)),"Sales Executive",ISNUMBER(SEARCH("marketing",B14)),"Marketing Executive",OR(ISNUMBER(SEARCH("hr ",B14)),ISNUMBER(SEARCH("recruit",B14)),ISNUMBER(SEARCH("human resource",B14))),"HR / Recruiter",OR(ISNUMBER(SEARCH("account",B14)),ISNUMBER(SEARCH("finance",B14)),ISNUMBER(SEARCH("tax",B14)),ISNUMBER(SEARCH("audit",B14))),"Accountant / Finance",OR(ISNUMBER(SEARCH("customer service",B14)),ISNUMBER(SEARCH("customer support",B14)),ISNUMBER(SEARCH("customer care",B14)),ISNUMBER(SEARCH("voice process",B14)),ISNUMBER(SEARCH("bpo",B14))),"Customer Support",ISNUMBER(SEARCH("engineer",B14)),"Engineer (Technical)",ISNUMBER(SEARCH("manager",B14)),"Manager",OR(ISNUMBER(SEARCH("teacher",B14)),ISNUMBER(SEARCH("trainer",B14)),ISNUMBER(SEARCH("faculty",B14))),"Teacher / Trainer",OR(ISNUMBER(SEARCH("doctor",B14)),ISNUMBER(SEARCH("nurse",B14)),ISNUMBER(SEARCH("medical",B14)),ISNUMBER(SEARCH("pharma",B14)),ISNUMBER(SEARCH("clinical",B14))),"Healthcare",TRUE,"Other") | Q14: =IF(COUNTIFS($B$11:B14,B14,$C$11:C14,C14,$D$11:D14,D14,$L$11:L14,L14)>1,"Duplicate","Unique")
A15: =Raw_Data!A6 | B15: =PROPER(TRIM(Raw_Data!B6)) | C15: =TRIM(Raw_Data!C6) | D15: =IF(PROPER(TRIM(Raw_Data!D6))="Bangalore","Bengaluru",IF(PROPER(TRIM(Raw_Data!D6))="Gurgaon","Gurugram",IF(OR(PROPER(TRIM(Raw_Data!D6))="New Delhi",PROPER(TRIM(Raw_Data!D6))="Delhi"),"Delhi",PROPER(TRIM(Raw_Data!D6))))) | E15: =Raw_Data!E6 | F15: =IF(TRIM(Raw_Data!F6&"")="","Not Specified",Raw_Data!F6) | G15: =Raw_Data!G6 | H15: =Raw_Data!H6 | I15: =IF(Raw_Data!I6="","",Raw_Data!I6) | J15: =IF(Raw_Data!J6="","",Raw_Data!J6) | K15: =IF(TRIM(Raw_Data!K6&"")="","Not Specified",Raw_Data!K6) | L15: =Raw_Data!L6 | M15: =IF(OR(I15="",J15=""),"",(I15+J15)/2) | N15: =IF(OR(I15="",J15=""),"",J15-I15) | O15: =TEXT(L15,"mmm-yyyy") | P15: =_xlfn.IFS(ISNUMBER(SEARCH("data analy",B15)),"Data Analyst",ISNUMBER(SEARCH("business analy",B15)),"Business Analyst",OR(ISNUMBER(SEARCH("developer",B15)),ISNUMBER(SEARCH("software engineer",B15)),ISNUMBER(SEARCH("programmer",B15))),"Software Developer",ISNUMBER(SEARCH("business development",B15)),"Business Development",ISNUMBER(SEARCH("sales",B15)),"Sales Executive",ISNUMBER(SEARCH("marketing",B15)),"Marketing Executive",OR(ISNUMBER(SEARCH("hr ",B15)),ISNUMBER(SEARCH("recruit",B15)),ISNUMBER(SEARCH("human resource",B15))),"HR / Recruiter",OR(ISNUMBER(SEARCH("account",B15)),ISNUMBER(SEARCH("finance",B15)),ISNUMBER(SEARCH("tax",B15)),ISNUMBER(SEARCH("audit",B15))),"Accountant / Finance",OR(ISNUMBER(SEARCH("customer service",B15)),ISNUMBER(SEARCH("customer support",B15)),ISNUMBER(SEARCH("customer care",B15)),ISNUMBER(SEARCH("voice process",B15)),ISNUMBER(SEARCH("bpo",B15))),"Customer Support",ISNUMBER(SEARCH("engineer",B15)),"Engineer (Technical)",ISNUMBER(SEARCH("manager",B15)),"Manager",OR(ISNUMBER(SEARCH("teacher",B15)),ISNUMBER(SEARCH("trainer",B15)),ISNUMBER(SEARCH("faculty",B15))),"Teacher / Trainer",OR(ISNUMBER(SEARCH("doctor",B15)),ISNUMBER(SEARCH("nurse",B15)),ISNUMBER(SEARCH("medical",B15)),ISNUMBER(SEARCH("pharma",B15)),ISNUMBER(SEARCH("clinical",B15))),"Healthcare",TRUE,"Other") | Q15: =IF(COUNTIFS($B$11:B15,B15,$C$11:C15,C15,$D$11:D15,D15,$L$11:L15,L15)>1,"Duplicate","Unique")
A16: =Raw_Data!A7 | B16: =PROPER(TRIM(Raw_Data!B7)) | C16: =TRIM(Raw_Data!C7) | D16: =IF(PROPER(TRIM(Raw_Data!D7))="Bangalore","Bengaluru",IF(PROPER(TRIM(Raw_Data!D7))="Gurgaon","Gurugram",IF(OR(PROPER(TRIM(Raw_Data!D7))="New Delhi",PROPER(TRIM(Raw_Data!D7))="Delhi"),"Delhi",PROPER(TRIM(Raw_Data!D7))))) | E16: =Raw_Data!E7 | F16: =IF(TRIM(Raw_Data!F7&"")="","Not Specified",Raw_Data!F7) | G16: =Raw_Data!G7 | H16: =Raw_Data!H7 | I16: =IF(Raw_Data!I7="","",Raw_Data!I7) | J16: =IF(Raw_Data!J7="","",Raw_Data!J7) | K16: =IF(TRIM(Raw_Data!K7&"")="","Not Specified",Raw_Data!K7) | L16: =Raw_Data!L7 | M16: =IF(OR(I16="",J16=""),"",(I16+J16)/2) | N16: =IF(OR(I16="",J16=""),"",J16-I16) | O16: =TEXT(L16,"mmm-yyyy") | P16: =_xlfn.IFS(ISNUMBER(SEARCH("data analy",B16)),"Data Analyst",ISNUMBER(SEARCH("business analy",B16)),"Business Analyst",OR(ISNUMBER(SEARCH("developer",B16)),ISNUMBER(SEARCH("software engineer",B16)),ISNUMBER(SEARCH("programmer",B16))),"Software Developer",ISNUMBER(SEARCH("business development",B16)),"Business Development",ISNUMBER(SEARCH("sales",B16)),"Sales Executive",ISNUMBER(SEARCH("marketing",B16)),"Marketing Executive",OR(ISNUMBER(SEARCH("hr ",B16)),ISNUMBER(SEARCH("recruit",B16)),ISNUMBER(SEARCH("human resource",B16))),"HR / Recruiter",OR(ISNUMBER(SEARCH("account",B16)),ISNUMBER(SEARCH("finance",B16)),ISNUMBER(SEARCH("tax",B16)),ISNUMBER(SEARCH("audit",B16))),"Accountant / Finance",OR(ISNUMBER(SEARCH("customer service",B16)),ISNUMBER(SEARCH("customer support",B16)),ISNUMBER(SEARCH("customer care",B16)),ISNUMBER(SEARCH("voice process",B16)),ISNUMBER(SEARCH("bpo",B16))),"Customer Support",ISNUMBER(SEARCH("engineer",B16)),"Engineer (Technical)",ISNUMBER(SEARCH("manager",B16)),"Manager",OR(ISNUMBER(SEARCH("teacher",B16)),ISNUMBER(SEARCH("trainer",B16)),ISNUMBER(SEARCH("faculty",B16))),"Teacher / Trainer",OR(ISNUMBER(SEARCH("doctor",B16)),ISNUMBER(SEARCH("nurse",B16)),ISNUMBER(SEARCH("medical",B16)),ISNUMBER(SEARCH("pharma",B16)),ISNUMBER(SEARCH("clinical",B16))),"Healthcare",TRUE,"Other") | Q16: =IF(COUNTIFS($B$11:B16,B16,$C$11:C16,C16,$D$11:D16,D16,$L$11:L16,L16)>1,"Duplicate","Unique")
A17: =Raw_Data!A8 | B17: =PROPER(TRIM(Raw_Data!B8)) | C17: =TRIM(Raw_Data!C8) | D17: =IF(PROPER(TRIM(Raw_Data!D8))="Bangalore","Bengaluru",IF(PROPER(TRIM(Raw_Data!D8))="Gurgaon","Gurugram",IF(OR(PROPER(TRIM(Raw_Data!D8))="New Delhi",PROPER(TRIM(Raw_Data!D8))="Delhi"),"Delhi",PROPER(TRIM(Raw_Data!D8))))) | E17: =Raw_Data!E8 | F17: =IF(TRIM(Raw_Data!F8&"")="","Not Specified",Raw_Data!F8) | G17: =Raw_Data!G8 | H17: =Raw_Data!H8 | I17: =IF(Raw_Data!I8="","",Raw_Data!I8) | J17: =IF(Raw_Data!J8="","",Raw_Data!J8) | K17: =IF(TRIM(Raw_Data!K8&"")="","Not Specified",Raw_Data!K8) | L17: =Raw_Data!L8 | M17: =IF(OR(I17="",J17=""),"",(I17+J17)/2) | N17: =IF(OR(I17="",J17=""),"",J17-I17) | O17: =TEXT(L17,"mmm-yyyy") | P17: =_xlfn.IFS(ISNUMBER(SEARCH("data analy",B17)),"Data Analyst",ISNUMBER(SEARCH("business analy",B17)),"Business Analyst",OR(ISNUMBER(SEARCH("developer",B17)),ISNUMBER(SEARCH("software engineer",B17)),ISNUMBER(SEARCH("programmer",B17))),"Software Developer",ISNUMBER(SEARCH("business development",B17)),"Business Development",ISNUMBER(SEARCH("sales",B17)),"Sales Executive",ISNUMBER(SEARCH("marketing",B17)),"Marketing Executive",OR(ISNUMBER(SEARCH("hr ",B17)),ISNUMBER(SEARCH("recruit",B17)),ISNUMBER(SEARCH("human resource",B17))),"HR / Recruiter",OR(ISNUMBER(SEARCH("account",B17)),ISNUMBER(SEARCH("finance",B17)),ISNUMBER(SEARCH("tax",B17)),ISNUMBER(SEARCH("audit",B17))),"Accountant / Finance",OR(ISNUMBER(SEARCH("customer service",B17)),ISNUMBER(SEARCH("customer support",B17)),ISNUMBER(SEARCH("customer care",B17)),ISNUMBER(SEARCH("voice process",B17)),ISNUMBER(SEARCH("bpo",B17))),"Customer Support",ISNUMBER(SEARCH("engineer",B17)),"Engineer (Technical)",ISNUMBER(SEARCH("manager",B17)),"Manager",OR(ISNUMBER(SEARCH("teacher",B17)),ISNUMBER(SEARCH("trainer",B17)),ISNUMBER(SEARCH("faculty",B17))),"Teacher / Trainer",OR(ISNUMBER(SEARCH("doctor",B17)),ISNUMBER(SEARCH("nurse",B17)),ISNUMBER(SEARCH("medical",B17)),ISNUMBER(SEARCH("pharma",B17)),ISNUMBER(SEARCH("clinical",B17))),"Healthcare",TRUE,"Other") | Q17: =IF(COUNTIFS($B$11:B17,B17,$C$11:C17,C17,$D$11:D17,D17,$L$11:L17,L17)>1,"Duplicate","Unique")
A18: =Raw_Data!A9 | B18: =PROPER(TRIM(Raw_Data!B9)) | C18: =TRIM(Raw_Data!C9) | D18: =IF(PROPER(TRIM(Raw_Data!D9))="Bangalore","Bengaluru",IF(PROPER(TRIM(Raw_Data!D9))="Gurgaon","Gurugram",IF(OR(PROPER(TRIM(Raw_Data!D9))="New Delhi",PROPER(TRIM(Raw_Data!D9))="Delhi"),"Delhi",PROPER(TRIM(Raw_Data!D9))))) | E18: =Raw_Data!E9 | F18: =IF(TRIM(Raw_Data!F9&"")="","Not Specified",Raw_Data!F9) | G18: =Raw_Data!G9 | H18: =Raw_Data!H9 | I18: =IF(Raw_Data!I9="","",Raw_Data!I9) | J18: =IF(Raw_Data!J9="","",Raw_Data!J9) | K18: =IF(TRIM(Raw_Data!K9&"")="","Not Specified",Raw_Data!K9) | L18: =Raw_Data!L9 | M18: =IF(OR(I18="",J18=""),"",(I18+J18)/2) | N18: =IF(OR(I18="",J18=""),"",J18-I18) | O18: =TEXT(L18,"mmm-yyyy") | P18: =_xlfn.IFS(ISNUMBER(SEARCH("data analy",B18)),"Data Analyst",ISNUMBER(SEARCH("business analy",B18)),"Business Analyst",OR(ISNUMBER(SEARCH("developer",B18)),ISNUMBER(SEARCH("software engineer",B18)),ISNUMBER(SEARCH("programmer",B18))),"Software Developer",ISNUMBER(SEARCH("business development",B18)),"Business Development",ISNUMBER(SEARCH("sales",B18)),"Sales Executive",ISNUMBER(SEARCH("marketing",B18)),"Marketing Executive",OR(ISNUMBER(SEARCH("hr ",B18)),ISNUMBER(SEARCH("recruit",B18)),ISNUMBER(SEARCH("human resource",B18))),"HR / Recruiter",OR(ISNUMBER(SEARCH("account",B18)),ISNUMBER(SEARCH("finance",B18)),ISNUMBER(SEARCH("tax",B18)),ISNUMBER(SEARCH("audit",B18))),"Accountant / Finance",OR(ISNUMBER(SEARCH("customer service",B18)),ISNUMBER(SEARCH("customer support",B18)),ISNUMBER(SEARCH("customer care",B18)),ISNUMBER(SEARCH("voice process",B18)),ISNUMBER(SEARCH("bpo",B18))),"Customer Support",ISNUMBER(SEARCH("engineer",B18)),"Engineer (Technical)",ISNUMBER(SEARCH("manager",B18)),"Manager",OR(ISNUMBER(SEARCH("teacher",B18)),ISNUMBER(SEARCH("trainer",B18)),ISNUMBER(SEARCH("faculty",B18))),"Teacher / Trainer",OR(ISNUMBER(SEARCH("doctor",B18)),ISNUMBER(SEARCH("nurse",B18)),ISNUMBER(SEARCH("medical",B18)),ISNUMBER(SEARCH("pharma",B18)),ISNUMBER(SEARCH("clinical",B18))),"Healthcare",TRUE,"Other") | Q18: =IF(COUNTIFS($B$11:B18,B18,$C$11:C18,C18,$D$11:D18,D18,$L$11:L18,L18)>1,"Duplicate","Unique")
A19: =Raw_Data!A10 | B19: =PROPER(TRIM(Raw_Data!B10)) | C19: =TRIM(Raw_Data!C10) | D19: =IF(PROPER(TRIM(Raw_Data!D10))="Bangalore","Bengaluru",IF(PROPER(TRIM(Raw_Data!D10))="Gurgaon","Gurugram",IF(OR(PROPER(TRIM(Raw_Data!D10))="New Delhi",PROPER(TRIM(Raw_Data!D10))="Delhi"),"Delhi",PROPER(TRIM(Raw_Data!D10))))) | E19: =Raw_Data!E10 | F19: =IF(TRIM(Raw_Data!F10&"")="","Not Specified",Raw_Data!F10) | G19: =Raw_Data!G10 | H19: =Raw_Data!H10 | I19: =IF(Raw_Data!I10="","",Raw_Data!I10) | J19: =IF(Raw_Data!J10="","",Raw_Data!J10) | K19: =IF(TRIM(Raw_Data!K10&"")="","Not Specified",Raw_Data!K10) | L19: =Raw_Data!L10 | M19: =IF(OR(I19="",J19=""),"",(I19+J19)/2) | N19: =IF(OR(I19="",J19=""),"",J19-I19) | O19: =TEXT(L19,"mmm-yyyy") | P19: =_xlfn.IFS(ISNUMBER(SEARCH("data analy",B19)),"Data Analyst",ISNUMBER(SEARCH("business analy",B19)),"Business Analyst",OR(ISNUMBER(SEARCH("developer",B19)),ISNUMBER(SEARCH("software engineer",B19)),ISNUMBER(SEARCH("programmer",B19))),"Software Developer",ISNUMBER(SEARCH("business development",B19)),"Business Development",ISNUMBER(SEARCH("sales",B19)),"Sales Executive",ISNUMBER(SEARCH("marketing",B19)),"Marketing Executive",OR(ISNUMBER(SEARCH("hr ",B19)),ISNUMBER(SEARCH("recruit",B19)),ISNUMBER(SEARCH("human resource",B19))),"HR / Recruiter",OR(ISNUMBER(SEARCH("account",B19)),ISNUMBER(SEARCH("finance",B19)),ISNUMBER(SEARCH("tax",B19)),ISNUMBER(SEARCH("audit",B19))),"Accountant / Finance",OR(ISNUMBER(SEARCH("customer service",B19)),ISNUMBER(SEARCH("customer support",B19)),ISNUMBER(SEARCH("customer care",B19)),ISNUMBER(SEARCH("voice process",B19)),ISNUMBER(SEARCH("bpo",B19))),"Customer Support",ISNUMBER(SEARCH("engineer",B19)),"Engineer (Technical)",ISNUMBER(SEARCH("manager",B19)),"Manager",OR(ISNUMBER(SEARCH("teacher",B19)),ISNUMBER(SEARCH("trainer",B19)),ISNUMBER(SEARCH("faculty",B19))),"Teacher / Trainer",OR(ISNUMBER(SEARCH("doctor",B19)),ISNUMBER(SEARCH("nurse",B19)),ISNUMBER(SEARCH("medical",B19)),ISNUMBER(SEARCH("pharma",B19)),ISNUMBER(SEARCH("clinical",B19))),"Healthcare",TRUE,"Other") | Q19: =IF(COUNTIFS($B$11:B19,B19,$C$11:C19,C19,$D$11:D19,D19,$L$11:L19,L19)>1,"Duplicate","Unique")
A20: =Raw_Data!A11 | B20: =PROPER(TRIM(Raw_Data!B11)) | C20: =TRIM(Raw_Data!C11) | D20: =IF(PROPER(TRIM(Raw_Data!D11))="Bangalore","Bengaluru",IF(PROPER(TRIM(Raw_Data!D11))="Gurgaon","Gurugram",IF(OR(PROPER(TRIM(Raw_Data!D11))="New Delhi",PROPER(TRIM(Raw_Data!D11))="Delhi"),"Delhi",PROPER(TRIM(Raw_Data!D11))))) | E20: =Raw_Data!E11 | F20: =IF(TRIM(Raw_Data!F11&"")="","Not Specified",Raw_Data!F11) | G20: =Raw_Data!G11 | H20: =Raw_Data!H11 | I20: =IF(Raw_Data!I11="","",Raw_Data!I11) | J20: =IF(Raw_Data!J11="","",Raw_Data!J11) | K20: =IF(TRIM(Raw_Data!K11&"")="","Not Specified",Raw_Data!K11) | L20: =Raw_Data!L11 | M20: =IF(OR(I20="",J20=""),"",(I20+J20)/2) | N20: =IF(OR(I20="",J20=""),"",J20-I20) | O20: =TEXT(L20,"mmm-yyyy") | P20: =_xlfn.IFS(ISNUMBER(SEARCH("data analy",B20)),"Data Analyst",ISNUMBER(SEARCH("business analy",B20)),"Business Analyst",OR(ISNUMBER(SEARCH("developer",B20)),ISNUMBER(SEARCH("software engineer",B20)),ISNUMBER(SEARCH("programmer",B20))),"Software Developer",ISNUMBER(SEARCH("business development",B20)),"Business Development",ISNUMBER(SEARCH("sales",B20)),"Sales Executive",ISNUMBER(SEARCH("marketing",B20)),"Marketing Executive",OR(ISNUMBER(SEARCH("hr ",B20)),ISNUMBER(SEARCH("recruit",B20)),ISNUMBER(SEARCH("human resource",B20))),"HR / Recruiter",OR(ISNUMBER(SEARCH("account",B20)),ISNUMBER(SEARCH("finance",B20)),ISNUMBER(SEARCH("tax",B20)),ISNUMBER(SEARCH("audit",B20))),"Accountant / Finance",OR(ISNUMBER(SEARCH("customer service",B20)),ISNUMBER(SEARCH("customer support",B20)),ISNUMBER(SEARCH("customer care",B20)),ISNUMBER(SEARCH("voice process",B20)),ISNUMBER(SEARCH("bpo",B20))),"Customer Support",ISNUMBER(SEARCH("engineer",B20)),"Engineer (Technical)",ISNUMBER(SEARCH("manager",B20)),"Manager",OR(ISNUMBER(SEARCH("teacher",B20)),ISNUMBER(SEARCH("trainer",B20)),ISNUMBER(SEARCH("faculty",B20))),"Teacher / Trainer",OR(ISNUMBER(SEARCH("doctor",B20)),ISNUMBER(SEARCH("nurse",B20)),ISNUMBER(SEARCH("medical",B20)),ISNUMBER(SEARCH("pharma",B20)),ISNUMBER(SEARCH("clinical",B20))),"Healthcare",TRUE,"Other") | Q20: =IF(COUNTIFS($B$11:B20,B20,$C$11:C20,C20,$D$11:D20,D20,$L$11:L20,L20)>1,"Duplicate","Unique")
A21: =Raw_Data!A12 | B21: =PROPER(TRIM(Raw_Data!B12)) | C21: =TRIM(Raw_Data!C12) | D21: =IF(PROPER(TRIM(Raw_Data!D12))="Bangalore","Bengaluru",IF(PROPER(TRIM(Raw_Data!D12))="Gurgaon","Gurugram",IF(OR(PROPER(TRIM(Raw_Data!D12))="New Delhi",PROPER(TRIM(Raw_Data!D12))="Delhi"),"Delhi",PROPER(TRIM(Raw_Data!D12))))) | E21: =Raw_Data!E12 | F21: =IF(TRIM(Raw_Data!F12&"")="","Not Specified",Raw_Data!F12) | G21: =Raw_Data!G12 | H21: =Raw_Data!H12 | I21: =IF(Raw_Data!I12="","",Raw_Data!I12) | J21: =IF(Raw_Data!J12="","",Raw_Data!J12) | K21: =IF(TRIM(Raw_Data!K12&"")="","Not Specified",Raw_Data!K12) | L21: =Raw_Data!L12 | M21: =IF(OR(I21="",J21=""),"",(I21+J21)/2) | N21: =IF(OR(I21="",J21=""),"",J21-I21) | O21: =TEXT(L21,"mmm-yyyy") | P21: =_xlfn.IFS(ISNUMBER(SEARCH("data analy",B21)),"Data Analyst",ISNUMBER(SEARCH("business analy",B21)),"Business Analyst",OR(ISNUMBER(SEARCH("developer",B21)),ISNUMBER(SEARCH("software engineer",B21)),ISNUMBER(SEARCH("programmer",B21))),"Software Developer",ISNUMBER(SEARCH("business development",B21)),"Business Development",ISNUMBER(SEARCH("sales",B21)),"Sales Executive",ISNUMBER(SEARCH("marketing",B21)),"Marketing Executive",OR(ISNUMBER(SEARCH("hr ",B21)),ISNUMBER(SEARCH("recruit",B21)),ISNUMBER(SEARCH("human resource",B21))),"HR / Recruiter",OR(ISNUMBER(SEARCH("account",B21)),ISNUMBER(SEARCH("finance",B21)),ISNUMBER(SEARCH("tax",B21)),ISNUMBER(SEARCH("audit",B21))),"Accountant / Finance",OR(ISNUMBER(SEARCH("customer service",B21)),ISNUMBER(SEARCH("customer support",B21)),ISNUMBER(SEARCH("customer care",B21)),ISNUMBER(SEARCH("voice process",B21)),ISNUMBER(SEARCH("bpo",B21))),"Customer Support",ISNUMBER(SEARCH("engineer",B21)),"Engineer (Technical)",ISNUMBER(SEARCH("manager",B21)),"Manager",OR(ISNUMBER(SEARCH("teacher",B21)),ISNUMBER(SEARCH("trainer",B21)),ISNUMBER(SEARCH("faculty",B21))),"Teacher / Trainer",OR(ISNUMBER(SEARCH("doctor",B21)),ISNUMBER(SEARCH("nurse",B21)),ISNUMBER(SEARCH("medical",B21)),ISNUMBER(SEARCH("pharma",B21)),ISNUMBER(SEARCH("clinical",B21))),"Healthcare",TRUE,"Other") | Q21: =IF(COUNTIFS($B$11:B21,B21,$C$11:C21,C21,$D$11:D21,D21,$L$11:L21,L21)>1,"Duplicate","Unique")
A22: =Raw_Data!A13 | B22: =PROPER(TRIM(Raw_Data!B13)) | C22: =TRIM(Raw_Data!C13) | D22: =IF(PROPER(TRIM(Raw_Data!D13))="Bangalore","Bengaluru",IF(PROPER(TRIM(Raw_Data!D13))="Gurgaon","Gurugram",IF(OR(PROPER(TRIM(Raw_Data!D13))="New Delhi",PROPER(TRIM(Raw_Data!D13))="Delhi"),"Delhi",PROPER(TRIM(Raw_Data!D13))))) | E22: =Raw_Data!E13 | F22: =IF(TRIM(Raw_Data!F13&"")="","Not Specified",Raw_Data!F13) | G22: =Raw_Data!G13 | H22: =Raw_Data!H13 | I22: =IF(Raw_Data!I13="","",Raw_Data!I13) | J22: =IF(Raw_Data!J13="","",Raw_Data!J13) | K22: =IF(TRIM(Raw_Data!K13&"")="","Not Specified",Raw_Data!K13) | L22: =Raw_Data!L13 | M22: =IF(OR(I22="",J22=""),"",(I22+J22)/2) | N22: =IF(OR(I22="",J22=""),"",J22-I22) | O22: =TEXT(L22,"mmm-yyyy") | P22: =_xlfn.IFS(ISNUMBER(SEARCH("data analy",B22)),"Data Analyst",ISNUMBER(SEARCH("business analy",B22)),"Business Analyst",OR(ISNUMBER(SEARCH("developer",B22)),ISNUMBER(SEARCH("software engineer",B22)),ISNUMBER(SEARCH("programmer",B22))),"Software Developer",ISNUMBER(SEARCH("business development",B22)),"Business Development",ISNUMBER(SEARCH("sales",B22)),"Sales Executive",ISNUMBER(SEARCH("marketing",B22)),"Marketing Executive",OR(ISNUMBER(SEARCH("hr ",B22)),ISNUMBER(SEARCH("recruit",B22)),ISNUMBER(SEARCH("human resource",B22))),"HR / Recruiter",OR(ISNUMBER(SEARCH("account",B22)),ISNUMBER(SEARCH("finance",B22)),ISNUMBER(SEARCH("tax",B22)),ISNUMBER(SEARCH("audit",B22))),"Accountant / Finance",OR(ISNUMBER(SEARCH("customer service",B22)),ISNUMBER(SEARCH("customer support",B22)),ISNUMBER(SEARCH("customer care",B22)),ISNUMBER(SEARCH("voice process",B22)),ISNUMBER(SEARCH("bpo",B22))),"Customer Support",ISNUMBER(SEARCH("engineer",B22)),"Engineer (Technical)",ISNUMBER(SEARCH("manager",B22)),"Manager",OR(ISNUMBER(SEARCH("teacher",B22)),ISNUMBER(SEARCH("trainer",B22)),ISNUMBER(SEARCH("faculty",B22))),"Teacher / Trainer",OR(ISNUMBER(SEARCH("doctor",B22)),ISNUMBER(SEARCH("nurse",B22)),ISNUMBER(SEARCH("medical",B22)),ISNUMBER(SEARCH("pharma",B22)),ISNUMBER(SEARCH("clinical",B22))),"Healthcare",TRUE,"Other") | Q22: =IF(COUNTIFS($B$11:B22,B22,$C$11:C22,C22,$D$11:D22,D22,$L$11:L22,L22)>1,"Duplicate","Unique")
... A444: =Raw_Data!A435 | B444: =PROPER(TRIM(Raw_Data!B435)) | C444: =TRIM(Raw_Data!C435) | D444: =IF(PROPER(TRIM(Raw_Data!D435))="Bangalore","Bengaluru",IF(PROPER(TRIM(Raw_Data!D435))="Gurgaon","Gurugram",IF(OR(PROPER(TRIM(Raw_Data!D435))="New Delhi",PROPER(TRIM(Raw_Data!D435))="Delhi"),"Delhi",PROPER(TRIM(Raw_Data!D435))))) | E444: =Raw_Data!E435 | F444: =IF(TRIM(Raw_Data!F435&"")="","Not Specified",Raw_Data!F435) | G444: =Raw_Data!G435 | H444: =Raw_Data!H435 | I444: =IF(Raw_Data!I435="","",Raw_Data!I435) | J444: =IF(Raw_Data!J435="","",Raw_Data!J435) | K444: =IF(TRIM(Raw_Data!K435&"")="","Not Specified",Raw_Data!K435) | L444: =Raw_Data!L435 | M444: =IF(OR(I444="",J444=""),"",(I444+J444)/2) | N444: =IF(OR(I444="",J444=""),"",J444-I444) | O444: =TEXT(L444,"mmm-yyyy") | P444: =_xlfn.IFS(ISNUMBER(SEARCH("data analy",B444)),"Data Analyst",ISNUMBER(SEARCH("business analy",B444)),"Business Analyst",OR(ISNUMBER(SEARCH("developer",B444)),ISNUMBER(SEARCH("software engineer",B444)),ISNUMBER(SEARCH("programmer",B444))),"Software Developer",ISNUMBER(SEARCH("business development",B444)),"Business Development",ISNUMBER(SEARCH("sales",B444)),"Sales Executive",ISNUMBER(SEARCH("marketing",B444)),"Marketing Executive",OR(ISNUMBER(SEARCH("hr ",B444)),ISNUMBER(SEARCH("recruit",B444)),ISNUMBER(SEARCH("human resource",B444))),"HR / Recruiter",OR(ISNUMBER(SEARCH("account",B444)),ISNUMBER(SEARCH("finance",B444)),ISNUMBER(SEARCH("tax",B444)),ISNUMBER(SEARCH("audit",B444))),"Accountant / Finance",OR(ISNUMBER(SEARCH("customer service",B444)),ISNUMBER(SEARCH("customer support",B444)),ISNUMBER(SEARCH("customer care",B444)),ISNUMBER(SEARCH("voice process",B444)),ISNUMBER(SEARCH("bpo",B444))),"Customer Support",ISNUMBER(SEARCH("engineer",B444)),"Engineer (Technical)",ISNUMBER(SEARCH("manager",B444)),"Manager",OR(ISNUMBER(SEARCH("teacher",B444)),ISNUMBER(SEARCH("trainer",B444)),ISNUMBER(SEARCH("faculty",B444))),"Teacher / Trainer",OR(ISNUMBER(SEARCH("doctor",B444)),ISNUMBER(SEARCH("nurse",B444)),ISNUMBER(SEARCH("medical",B444)),ISNUMBER(SEARCH("pharma",B444)),ISNUMBER(SEARCH("clinical",B444))),"Healthcare",TRUE,"Other") | Q444: =IF(COUNTIFS($B$11:B444,B444,$C$11:C444,C444,$D$11:D444,D444,$L$11:L444,L444)>1,"Duplicate","Unique")

Sheet Analysis
A1: Analysis — Pivot-Style Summary Tables (COUNTIFS / SUMIFS / AVERAGEIFS)
A2: These tables recreate what an Excel PivotTable would show, but are built with formulas so every number stays visible and easy to explain. All tables exclude duplicate postings (Duplicate_Flag = Unique) and respond live to the 5 filter dropdowns on the Dashboard sheet.
A3: Jobs by Job Role | D3: Jobs by Location (Top 20) | G3: Jobs by Industry
A4: Job_Role | B4: Job_Count | D4: Location | E4: Job_Count | G4: Industry | H4: Job_Count
A5: Sales Executive | B5: =COUNTIFS(NR_RoleCategory,A5,NR_RoleCategory,IF(NR_F_Role="All","*",NR_F_Role),NR_Location,IF(NR_F_Loc="All","*",NR_F_Loc),NR_ExpLevel,IF(NR_F_Exp="All","*",NR_F_Exp),NR_WorkMode,IF(NR_F_WM="All","*",NR_F_WM),NR_Industry,IF(NR_F_Ind="All","*",NR_F_Ind),NR_DupFlag,"Unique") | D5: Bengaluru | E5: =COUNTIFS(NR_Location,D5,NR_RoleCategory,IF(NR_F_Role="All","*",NR_F_Role),NR_Location,IF(NR_F_Loc="All","*",NR_F_Loc),NR_ExpLevel,IF(NR_F_Exp="All","*",NR_F_Exp),NR_WorkMode,IF(NR_F_WM="All","*",NR_F_WM),NR_Industry,IF(NR_F_Ind="All","*",NR_F_Ind),NR_DupFlag,"Unique") | G5: IT / Software | H5: =COUNTIFS(NR_Industry,G5,NR_RoleCategory,IF(NR_F_Role="All","*",NR_F_Role),NR_Location,IF(NR_F_Loc="All","*",NR_F_Loc),NR_ExpLevel,IF(NR_F_Exp="All","*",NR_F_Exp),NR_WorkMode,IF(NR_F_WM="All","*",NR_F_WM),NR_Industry,IF(NR_F_Ind="All","*",NR_F_Ind),NR_DupFlag,"Unique")
A6: Engineer (Technical) | B6: =COUNTIFS(NR_RoleCategory,A6,NR_RoleCategory,IF(NR_F_Role="All","*",NR_F_Role),NR_Location,IF(NR_F_Loc="All","*",NR_F_Loc),NR_ExpLevel,IF(NR_F_Exp="All","*",NR_F_Exp),NR_WorkMode,IF(NR_F_WM="All","*",NR_F_WM),NR_Industry,IF(NR_F_Ind="All","*",NR_F_Ind),NR_DupFlag,"Unique") | D6: Pune | E6: =COUNTIFS(NR_Location,D6,NR_RoleCategory,IF(NR_F_Role="All","*",NR_F_Role),NR_Location,IF(NR_F_Loc="All","*",NR_F_Loc),NR_ExpLevel,IF(NR_F_Exp="All","*",NR_F_Exp),NR_WorkMode,IF(NR_F_WM="All","*",NR_F_WM),NR_Industry,IF(NR_F_Ind="All","*",NR_F_Ind),NR_DupFlag,"Unique") | G6: Other / General Business | H6: =COUNTIFS(NR_Industry,G6,NR_RoleCategory,IF(NR_F_Role="All","*",NR_F_Role),NR_Location,IF(NR_F_Loc="All","*",NR_F_Loc),NR_ExpLevel,IF(NR_F_Exp="All","*",NR_F_Exp),NR_WorkMode,IF(NR_F_WM="All","*",NR_F_WM),NR_Industry,IF(NR_F_Ind="All","*",NR_F_Ind),NR_DupFlag,"Unique")
A7: Manager | B7: =COUNTIFS(NR_RoleCategory,A7,NR_RoleCategory,IF(NR_F_Role="All","*",NR_F_Role),NR_Location,IF(NR_F_Loc="All","*",NR_F_Loc),NR_ExpLevel,IF(NR_F_Exp="All","*",NR_F_Exp),NR_WorkMode,IF(NR_F_WM="All","*",NR_F_WM),NR_Industry,IF(NR_F_Ind="All","*",NR_F_Ind),NR_DupFlag,"Unique") | D7: Hyderabad | E7: =COUNTIFS(NR_Location,D7,NR_RoleCategory,IF(NR_F_Role="All","*",NR_F_Role),NR_Location,IF(NR_F_Loc="All","*",NR_F_Loc),NR_ExpLevel,IF(NR_F_Exp="All","*",NR_F_Exp),NR_WorkMode,IF(NR_F_WM="All","*",NR_F_WM),NR_Industry,IF(NR_F_Ind="All","*",NR_F_Ind),NR_DupFlag,"Unique") | G7: BFSI (Banking/Finance/Insurance) | H7: =COUNTIFS(NR_Industry,G7,NR_RoleCategory,IF(NR_F_Role="All","*",NR_F_Role),NR_Location,IF(NR_F_Loc="All","*",NR_F_Loc),NR_ExpLevel,IF(NR_F_Exp="All","*",NR_F_Exp),NR_WorkMode,IF(NR_F_WM="All","*",NR_F_WM),NR_Industry,IF(NR_F_Ind="All","*",NR_F_Ind),NR_DupFlag,"Unique")
A8: Software Developer | B8: =COUNTIFS(NR_RoleCategory,A8,NR_RoleCategory,IF(NR_F_Role="All","*",NR_F_Role),NR_Location,IF(NR_F_Loc="All","*",NR_F_Loc),NR_ExpLevel,IF(NR_F_Exp="All","*",NR_F_Exp),NR_WorkMode,IF(NR_F_WM="All","*",NR_F_WM),NR_Industry,IF(NR_F_Ind="All","*",NR_F_Ind),NR_DupFlag,"Unique") | D8: Chennai | E8: =COUNTIFS(NR_Location,D8,NR_RoleCategory,IF(NR_F_Role="All","*",NR_F_Role),NR_Location,IF(NR_F_Loc="All","*",NR_F_Loc),NR_ExpLevel,IF(NR_F_Exp="All","*",NR_F_Exp),NR_WorkMode,IF(NR_F_WM="All","*",NR_F_WM),NR_Industry,IF(NR_F_Ind="All","*",NR_F_Ind),NR_DupFlag,"Unique") | G8: Manufacturing & Engineering | H8: =COUNTIFS(NR_Industry,G8,NR_RoleCategory,IF(NR_F_Role="All","*",NR_F_Role),NR_Location,IF(NR_F_Loc="All","*",NR_F_Loc),NR_ExpLevel,IF(NR_F_Exp="All","*",NR_F_Exp),NR_WorkMode,IF(NR_F_WM="All","*",NR_F_WM),NR_Industry,IF(NR_F_Ind="All","*",NR_F_Ind),NR_DupFlag,"Unique")
A9: Accountant / Finance | B9: =COUNTIFS(NR_RoleCategory,A9,NR_RoleCategory,IF(NR_F_Role="All","*",NR_F_Role),NR_Location,IF(NR_F_Loc="All","*",NR_F_Loc),NR_ExpLevel,IF(NR_F_Exp="All","*",NR_F_Exp),NR_WorkMode,IF(NR_F_WM="All","*",NR_F_WM),NR_Industry,IF(NR_F_Ind="All","*",NR_F_Ind),NR_DupFlag,"Unique") | D9: Gurugram | E9: =COUNTIFS(NR_Location,D9,NR_RoleCategory,IF(NR_F_Role="All","*",NR_F_Role),NR_Location,IF(NR_F_Loc="All","*",NR_F_Loc),NR_ExpLevel,IF(NR_F_Exp="All","*",NR_F_Exp),NR_WorkMode,IF(NR_F_WM="All","*",NR_F_WM),NR_Industry,IF(NR_F_Ind="All","*",NR_F_Ind),NR_DupFlag,"Unique") | G9: Marketing & Advertising | H9: =COUNTIFS(NR_Industry,G9,NR_RoleCategory,IF(NR_F_Role="All","*",NR_F_Role),NR_Location,IF(NR_F_Loc="All","*",NR_F_Loc),NR_ExpLevel,IF(NR_F_Exp="All","*",NR_F_Exp),NR_WorkMode,IF(NR_F_WM="All","*",NR_F_WM),NR_Industry,IF(NR_F_Ind="All","*",NR_F_Ind),NR_DupFlag,"Unique")
A10: Customer Support | B10: =COUNTIFS(NR_RoleCategory,A10,NR_RoleCategory,IF(NR_F_Role="All","*",NR_F_Role),NR_Location,IF(NR_F_Loc="All","*",NR_F_Loc),NR_ExpLevel,IF(NR_F_Exp="All","*",NR_F_Exp),NR_WorkMode,IF(NR_F_WM="All","*",NR_F_WM),NR_Industry,IF(NR_F_Ind="All","*",NR_F_Ind),NR_DupFlag,"Unique") | D10: Mumbai | E10: =COUNTIFS(NR_Location,D10,NR_RoleCategory,IF(NR_F_Role="All","*",NR_F_Role),NR_Location,IF(NR_F_Loc="All","*",NR_F_Loc),NR_ExpLevel,IF(NR_F_Exp="All","*",NR_F_Exp),NR_WorkMode,IF(NR_F_WM="All","*",NR_F_WM),NR_Industry,IF(NR_F_Ind="All","*",NR_F_Ind),NR_DupFlag,"Unique") | G10: Customer Service & BPO | H10: =COUNTIFS(NR_Industry,G10,NR_RoleCategory,IF(NR_F_Role="All","*",NR_F_Role),NR_Location,IF(NR_F_Loc="All","*",NR_F_Loc),NR_ExpLevel,IF(NR_F_Exp="All","*",NR_F_Exp),NR_WorkMode,IF(NR_F_WM="All","*",NR_F_WM),NR_Industry,IF(NR_F_Ind="All","*",NR_F_Ind),NR_DupFlag,"Unique")
A11: HR / Recruiter | B11: =COUNTIFS(NR_RoleCategory,A11,NR_RoleCategory,IF(NR_F_Role="All","*",NR_F_Role),NR_Location,IF(NR_F_Loc="All","*",NR_F_Loc),NR_ExpLevel,IF(NR_F_Exp="All","*",NR_F_Exp),NR_WorkMode,IF(NR_F_WM="All","*",NR_F_WM),NR_Industry,IF(NR_F_Ind="All","*",NR_F_Ind),NR_DupFlag,"Unique") | D11: Noida | E11: =COUNTIFS(NR_Location,D11,NR_RoleCategory,IF(NR_F_Role="All","*",NR_F_Role),NR_Location,IF(NR_F_Loc="All","*",NR_F_Loc),NR_ExpLevel,IF(NR_F_Exp="All","*",NR_F_Exp),NR_WorkMode,IF(NR_F_WM="All","*",NR_F_WM),NR_Industry,IF(NR_F_Ind="All","*",NR_F_Ind),NR_DupFlag,"Unique") | G11: Sales & Business Development | H11: =COUNTIFS(NR_Industry,G11,NR_RoleCategory,IF(NR_F_Role="All","*",NR_F_Role),NR_Location,IF(NR_F_Loc="All","*",NR_F_Loc),NR_ExpLevel,IF(NR_F_Exp="All","*",NR_F_Exp),NR_WorkMode,IF(NR_F_WM="All","*",NR_F_WM),NR_Industry,IF(NR_F_Ind="All","*",NR_F_Ind),NR_DupFlag,"Unique")
A12: Business Development | B12: =COUNTIFS(NR_RoleCategory,A12,NR_RoleCategory,IF(NR_F_Role="All","*",NR_F_Role),NR_Location,IF(NR_F_Loc="All","*",NR_F_Loc),NR_ExpLevel,IF(NR_F_Exp="All","*",NR_F_Exp),NR_WorkMode,IF(NR_F_WM="All","*",NR_F_WM),NR_Industry,IF(NR_F_Ind="All","*",NR_F_Ind),NR_DupFlag,"Unique") | D12: Ahmedabad | E12: =COUNTIFS(NR_Location,D12,NR_RoleCategory,IF(NR_F_Role="All","*",NR_F_Role),NR_Location,IF(NR_F_Loc="All","*",NR_F_Loc),NR_ExpLevel,IF(NR_F_Exp="All","*",NR_F_Exp),NR_WorkMode,IF(NR_F_WM="All","*",NR_F_WM),NR_Industry,IF(NR_F_Ind="All","*",NR_F_Ind),NR_DupFlag,"Unique") | G12: Healthcare & Pharma | H12: =COUNTIFS(NR_Industry,G12,NR_RoleCategory,IF(NR_F_Role="All","*",NR_F_Role),NR_Location,IF(NR_F_Loc="All","*",NR_F_Loc),NR_ExpLevel,IF(NR_F_Exp="All","*",NR_F_Exp),NR_WorkMode,IF(NR_F_WM="All","*",NR_F_WM),NR_Industry,IF(NR_F_Ind="All","*",NR_F_Ind),NR_DupFlag,"Unique")
A13: Teacher / Trainer | B13: =COUNTIFS(NR_RoleCategory,A13,NR_RoleCategory,IF(NR_F_Role="All","*",NR_F_Role),NR_Location,IF(NR_F_Loc="All","*",NR_F_Loc),NR_ExpLevel,IF(NR_F_Exp="All","*",NR_F_Exp),NR_WorkMode,IF(NR_F_WM="All","*",NR_F_WM),NR_Industry,IF(NR_F_Ind="All","*",NR_F_Ind),NR_DupFlag,"Unique") | D13: Thane | E13: =COUNTIFS(NR_Location,D13,NR_RoleCategory,IF(NR_F_Role="All","*",NR_F_Role),NR_Location,IF(NR_F_Loc="All","*",NR_F_Loc),NR_ExpLevel,IF(NR_F_Exp="All","*",NR_F_Exp),NR_WorkMode,IF(NR_F_WM="All","*",NR_F_WM),NR_Industry,IF(NR_F_Ind="All","*",NR_F_Ind),NR_DupFlag,"Unique") | G13: Education & Training | H13: =COUNTIFS(NR_Industry,G13,NR_RoleCategory,IF(NR_F_Role="All","*",NR_F_Role),NR_Location,IF(NR_F_Loc="All","*",NR_F_Loc),NR_ExpLevel,IF(NR_F_Exp="All","*",NR_F_Exp),NR_WorkMode,IF(NR_F_WM="All","*",NR_F_WM),NR_Industry,IF(NR_F_Ind="All","*",NR_F_Ind),NR_DupFlag,"Unique")
A14: Marketing Executive | B14: =COUNTIFS(NR_RoleCategory,A14,NR_RoleCategory,IF(NR_F_Role="All","*",NR_F_Role),NR_Location,IF(NR_F_Loc="All","*",NR_F_Loc),NR_ExpLevel,IF(NR_F_Exp="All","*",NR_F_Exp),NR_WorkMode,IF(NR_F_WM="All","*",NR_F_WM),NR_Industry,IF(NR_F_Ind="All","*",NR_F_Ind),NR_DupFlag,"Unique") | D14: Remote | E14: =COUNTIFS(NR_Location,D14,NR_RoleCategory,IF(NR_F_Role="All","*",NR_F_Role),NR_Location,IF(NR_F_Loc="All","*",NR_F_Loc),NR_ExpLevel,IF(NR_F_Exp="All","*",NR_F_Exp),NR_WorkMode,IF(NR_F_WM="All","*",NR_F_WM),NR_Industry,IF(NR_F_Ind="All","*",NR_F_Ind),NR_DupFlag,"Unique") | G14: HR & Staffing | H14: =COUNTIFS(NR_Industry,G14,NR_RoleCategory,IF(NR_F_Role="All","*",NR_F_Role),NR_Location,IF(NR_F_Loc="All","*",NR_F_Loc),NR_ExpLevel,IF(NR_F_Exp="All","*",NR_F_Exp),NR_WorkMode,IF(NR_F_WM="All","*",NR_F_WM),NR_Industry,IF(NR_F_Ind="All","*",NR_F_Ind),NR_DupFlag,"Unique")
A15: Healthcare | B15: =COUNTIFS(NR_RoleCategory,A15,NR_RoleCategory,IF(NR_F_Role="All","*",NR_F_Role),NR_Location,IF(NR_F_Loc="All","*",NR_F_Loc),NR_ExpLevel,IF(NR_F_Exp="All","*",NR_F_Exp),NR_WorkMode,IF(NR_F_WM="All","*",NR_F_WM),NR_Industry,IF(NR_F_Ind="All","*",NR_F_Ind),NR_DupFlag,"Unique") | D15: Kolkata | E15: =COUNTIFS(NR_Location,D15,NR_RoleCategory,IF(NR_F_Role="All","*",NR_F_Role),NR_Location,IF(NR_F_Loc="All","*",NR_F_Loc),NR_ExpLevel,IF(NR_F_Exp="All","*",NR_F_Exp),NR_WorkMode,IF(NR_F_WM="All","*",NR_F_WM),NR_Industry,IF(NR_F_Ind="All","*",NR_F_Ind),NR_DupFlag,"Unique") | G15: Logistics & Supply Chain | H15: =COUNTIFS(NR_Industry,G15,NR_RoleCategory,IF(NR_F_Role="All","*",NR_F_Role),NR_Location,IF(NR_F_Loc="All","*",NR_F_Loc),NR_ExpLevel,IF(NR_F_Exp="All","*",NR_F_Exp),NR_WorkMode,IF(NR_F_WM="All","*",NR_F_WM),NR_Industry,IF(NR_F_Ind="All","*",NR_F_Ind),NR_DupFlag,"Unique")
A16: Data Analyst | B16: =COUNTIFS(NR_RoleCategory,A16,NR_RoleCategory,IF(NR_F_Role="All","*",NR_F_Role),NR_Location,IF(NR_F_Loc="All","*",NR_F_Loc),NR_ExpLevel,IF(NR_F_Exp="All","*",NR_F_Exp),NR_WorkMode,IF(NR_F_WM="All","*",NR_F_WM),NR_Industry,IF(NR_F_Ind="All","*",NR_F_Ind),NR_DupFlag,"Unique") | D16: Chandigarh | E16: =COUNTIFS(NR_Location,D16,NR_RoleCategory,IF(NR_F_Role="All","*",NR_F_Role),NR_Location,IF(NR_F_Loc="All","*",NR_F_Loc),NR_ExpLevel,IF(NR_F_Exp="All","*",NR_F_Exp),NR_WorkMode,IF(NR_F_WM="All","*",NR_F_WM),NR_Industry,IF(NR_F_Ind="All","*",NR_F_Ind),NR_DupFlag,"Unique") | G16: Real Estate & Construction | H16: =COUNTIFS(NR_Industry,G16,NR_RoleCategory,IF(NR_F_Role="All","*",NR_F_Role),NR_Location,IF(NR_F_Loc="All","*",NR_F_Loc),NR_ExpLevel,IF(NR_F_Exp="All","*",NR_F_Exp),NR_WorkMode,IF(NR_F_WM="All","*",NR_F_WM),NR_Industry,IF(NR_F_Ind="All","*",NR_F_Ind),NR_DupFlag,"Unique")
A17: Other | B17: =COUNTIFS(NR_RoleCategory,A17,NR_RoleCategory,IF(NR_F_Role="All","*",NR_F_Role),NR_Location,IF(NR_F_Loc="All","*",NR_F_Loc),NR_ExpLevel,IF(NR_F_Exp="All","*",NR_F_Exp),NR_WorkMode,IF(NR_F_WM="All","*",NR_F_WM),NR_Industry,IF(NR_F_Ind="All","*",NR_F_Ind),NR_DupFlag,"Unique") | D17: Mysuru | E17: =COUNTIFS(NR_Location,D17,NR_RoleCategory,IF(NR_F_Role="All","*",NR_F_Role),NR_Location,IF(NR_F_Loc="All","*",NR_F_Loc),NR_ExpLevel,IF(NR_F_Exp="All","*",NR_F_Exp),NR_WorkMode,IF(NR_F_WM="All","*",NR_F_WM),NR_Industry,IF(NR_F_Ind="All","*",NR_F_Ind),NR_DupFlag,"Unique") | G17: Media & Entertainment | H17: =COUNTIFS(NR_Industry,G17,NR_RoleCategory,IF(NR_F_Role="All","*",NR_F_Role),NR_Location,IF(NR_F_Loc="All","*",NR_F_Loc),NR_ExpLevel,IF(NR_F_Exp="All","*",NR_F_Exp),NR_WorkMode,IF(NR_F_WM="All","*",NR_F_WM),NR_Industry,IF(NR_F_Ind="All","*",NR_F_Ind),NR_DupFlag,"Unique")
D18: Surat | E18: =COUNTIFS(NR_Location,D18,NR_RoleCategory,IF(NR_F_Role="All","*",NR_F_Role),NR_Location,IF(NR_F_Loc="All","*",NR_F_Loc),NR_ExpLevel,IF(NR_F_Exp="All","*",NR_F_Exp),NR_WorkMode,IF(NR_F_WM="All","*",NR_F_WM),NR_Industry,IF(NR_F_Ind="All","*",NR_F_Ind),NR_DupFlag,"Unique") | G18: Telecom | H18: =COUNTIFS(NR_Industry,G18,NR_RoleCategory,IF(NR_F_Role="All","*",NR_F_Role),NR_Location,IF(NR_F_Loc="All","*",NR_F_Loc),NR_ExpLevel,IF(NR_F_Exp="All","*",NR_F_Exp),NR_WorkMode,IF(NR_F_WM="All","*",NR_F_WM),NR_Industry,IF(NR_F_Ind="All","*",NR_F_Ind),NR_DupFlag,"Unique")
D19: Jaipur | E19: =COUNTIFS(NR_Location,D19,NR_RoleCategory,IF(NR_F_Role="All","*",NR_F_Role),NR_Location,IF(NR_F_Loc="All","*",NR_F_Loc),NR_ExpLevel,IF(NR_F_Exp="All","*",NR_F_Exp),NR_WorkMode,IF(NR_F_WM="All","*",NR_F_WM),NR_Industry,IF(NR_F_Ind="All","*",NR_F_Ind),NR_DupFlag,"Unique") | G19: Hospitality & Travel | H19: =COUNTIFS(NR_Industry,G19,NR_RoleCategory,IF(NR_F_Role="All","*",NR_F_Role),NR_Location,IF(NR_F_Loc="All","*",NR_F_Loc),NR_ExpLevel,IF(NR_F_Exp="All","*",NR_F_Exp),NR_WorkMode,IF(NR_F_WM="All","*",NR_F_WM),NR_Industry,IF(NR_F_Ind="All","*",NR_F_Ind),NR_DupFlag,"Unique")
D20: Mumbai Suburban | E20: =COUNTIFS(NR_Location,D20,NR_RoleCategory,IF(NR_F_Role="All","*",NR_F_Role),NR_Location,IF(NR_F_Loc="All","*",NR_F_Loc),NR_ExpLevel,IF(NR_F_Exp="All","*",NR_F_Exp),NR_WorkMode,IF(NR_F_WM="All","*",NR_F_WM),NR_Industry,IF(NR_F_Ind="All","*",NR_F_Ind),NR_DupFlag,"Unique") | G20: Retail & E-commerce | H20: =COUNTIFS(NR_Industry,G20,NR_RoleCategory,IF(NR_F_Role="All","*",NR_F_Role),NR_Location,IF(NR_F_Loc="All","*",NR_F_Loc),NR_ExpLevel,IF(NR_F_Exp="All","*",NR_F_Exp),NR_WorkMode,IF(NR_F_WM="All","*",NR_F_WM),NR_Industry,IF(NR_F_Ind="All","*",NR_F_Ind),NR_DupFlag,"Unique")
D21: Udaipur | E21: =COUNTIFS(NR_Location,D21,NR_RoleCategory,IF(NR_F_Role="All","*",NR_F_Role),NR_Location,IF(NR_F_Loc="All","*",NR_F_Loc),NR_ExpLevel,IF(NR_F_Exp="All","*",NR_F_Exp),NR_WorkMode,IF(NR_F_WM="All","*",NR_F_WM),NR_Industry,IF(NR_F_Ind="All","*",NR_F_Ind),NR_DupFlag,"Unique")
D22: Nashik | E22: =COUNTIFS(NR_Location,D22,NR_RoleCategory,IF(NR_F_Role="All","*",NR_F_Role),NR_Location,IF(NR_F_Loc="All","*",NR_F_Loc),NR_ExpLevel,IF(NR_F_Exp="All","*",NR_F_Exp),NR_WorkMode,IF(NR_F_WM="All","*",NR_F_WM),NR_Industry,IF(NR_F_Ind="All","*",NR_F_Ind),NR_DupFlag,"Unique")
D23: Navi Mumbai | E23: =COUNTIFS(NR_Location,D23,NR_RoleCategory,IF(NR_F_Role="All","*",NR_F_Role),NR_Location,IF(NR_F_Loc="All","*",NR_F_Loc),NR_ExpLevel,IF(NR_F_Exp="All","*",NR_F_Exp),NR_WorkMode,IF(NR_F_WM="All","*",NR_F_WM),NR_Industry,IF(NR_F_Ind="All","*",NR_F_Ind),NR_DupFlag,"Unique")
D24: Vasai | E24: =COUNTIFS(NR_Location,D24,NR_RoleCategory,IF(NR_F_Role="All","*",NR_F_Role),NR_Location,IF(NR_F_Loc="All","*",NR_F_Loc),NR_ExpLevel,IF(NR_F_Exp="All","*",NR_F_Exp),NR_WorkMode,IF(NR_F_WM="All","*",NR_F_WM),NR_Industry,IF(NR_F_Ind="All","*",NR_F_Ind),NR_DupFlag,"Unique")
A27: Jobs by Experience Level | D27: Jobs by Work Mode | G27: Average Salary by Experience Level (Lacs PA)
A28: Experience_Level | B28: Job_Count | D28: Work_Mode | E28: Job_Count | G28: Experience_Level | H28: Avg_Salary
A29: Entry Level (0-2 yrs) | B29: =COUNTIFS(NR_ExpLevel,A29,NR_RoleCategory,IF(NR_F_Role="All","*",NR_F_Role),NR_Location,IF(NR_F_Loc="All","*",NR_F_Loc),NR_ExpLevel,IF(NR_F_Exp="All","*",NR_F_Exp),NR_WorkMode,IF(NR_F_WM="All","*",NR_F_WM),NR_Industry,IF(NR_F_Ind="All","*",NR_F_Ind),NR_DupFlag,"Unique") | D29: On-site | E29: =COUNTIFS(NR_WorkMode,D29,NR_RoleCategory,IF(NR_F_Role="All","*",NR_F_Role),NR_Location,IF(NR_F_Loc="All","*",NR_F_Loc),NR_ExpLevel,IF(NR_F_Exp="All","*",NR_F_Exp),NR_WorkMode,IF(NR_F_WM="All","*",NR_F_WM),NR_Industry,IF(NR_F_Ind="All","*",NR_F_Ind),NR_DupFlag,"Unique") | G29: Entry Level (0-2 yrs) | H29: =IFERROR(AVERAGEIFS(NR_AvgSalary,NR_ExpLevel,G29,NR_RoleCategory,IF(NR_F_Role="All","*",NR_F_Role),NR_Location,IF(NR_F_Loc="All","*",NR_F_Loc),NR_ExpLevel,IF(NR_F_Exp="All","*",NR_F_Exp),NR_WorkMode,IF(NR_F_WM="All","*",NR_F_WM),NR_Industry,IF(NR_F_Ind="All","*",NR_F_Ind),NR_DupFlag,"Unique"),"n/a")
A30: Mid Level (3-6 yrs) | B30: =COUNTIFS(NR_ExpLevel,A30,NR_RoleCategory,IF(NR_F_Role="All","*",NR_F_Role),NR_Location,IF(NR_F_Loc="All","*",NR_F_Loc),NR_ExpLevel,IF(NR_F_Exp="All","*",NR_F_Exp),NR_WorkMode,IF(NR_F_WM="All","*",NR_F_WM),NR_Industry,IF(NR_F_Ind="All","*",NR_F_Ind),NR_DupFlag,"Unique") | D30: Hybrid | E30: =COUNTIFS(NR_WorkMode,D30,NR_RoleCategory,IF(NR_F_Role="All","*",NR_F_Role),NR_Location,IF(NR_F_Loc="All","*",NR_F_Loc),NR_ExpLevel,IF(NR_F_Exp="All","*",NR_F_Exp),NR_WorkMode,IF(NR_F_WM="All","*",NR_F_WM),NR_Industry,IF(NR_F_Ind="All","*",NR_F_Ind),NR_DupFlag,"Unique") | G30: Mid Level (3-6 yrs) | H30: =IFERROR(AVERAGEIFS(NR_AvgSalary,NR_ExpLevel,G30,NR_RoleCategory,IF(NR_F_Role="All","*",NR_F_Role),NR_Location,IF(NR_F_Loc="All","*",NR_F_Loc),NR_ExpLevel,IF(NR_F_Exp="All","*",NR_F_Exp),NR_WorkMode,IF(NR_F_WM="All","*",NR_F_WM),NR_Industry,IF(NR_F_Ind="All","*",NR_F_Ind),NR_DupFlag,"Unique"),"n/a")
A31: Senior Level (7+ yrs) | B31: =COUNTIFS(NR_ExpLevel,A31,NR_RoleCategory,IF(NR_F_Role="All","*",NR_F_Role),NR_Location,IF(NR_F_Loc="All","*",NR_F_Loc),NR_ExpLevel,IF(NR_F_Exp="All","*",NR_F_Exp),NR_WorkMode,IF(NR_F_WM="All","*",NR_F_WM),NR_Industry,IF(NR_F_Ind="All","*",NR_F_Ind),NR_DupFlag,"Unique") | D31: Remote | E31: =COUNTIFS(NR_WorkMode,D31,NR_RoleCategory,IF(NR_F_Role="All","*",NR_F_Role),NR_Location,IF(NR_F_Loc="All","*",NR_F_Loc),NR_ExpLevel,IF(NR_F_Exp="All","*",NR_F_Exp),NR_WorkMode,IF(NR_F_WM="All","*",NR_F_WM),NR_Industry,IF(NR_F_Ind="All","*",NR_F_Ind),NR_DupFlag,"Unique") | G31: Senior Level (7+ yrs) | H31: =IFERROR(AVERAGEIFS(NR_AvgSalary,NR_ExpLevel,G31,NR_RoleCategory,IF(NR_F_Role="All","*",NR_F_Role),NR_Location,IF(NR_F_Loc="All","*",NR_F_Loc),NR_ExpLevel,IF(NR_F_Exp="All","*",NR_F_Exp),NR_WorkMode,IF(NR_F_WM="All","*",NR_F_WM),NR_Industry,IF(NR_F_Ind="All","*",NR_F_Ind),NR_DupFlag,"Unique"),"n/a")
A32: Not Specified | B32: =COUNTIFS(NR_ExpLevel,A32,NR_RoleCategory,IF(NR_F_Role="All","*",NR_F_Role),NR_Location,IF(NR_F_Loc="All","*",NR_F_Loc),NR_ExpLevel,IF(NR_F_Exp="All","*",NR_F_Exp),NR_WorkMode,IF(NR_F_WM="All","*",NR_F_WM),NR_Industry,IF(NR_F_Ind="All","*",NR_F_Ind),NR_DupFlag,"Unique") | G32: Not Specified | H32: =IFERROR(AVERAGEIFS(NR_AvgSalary,NR_ExpLevel,G32,NR_RoleCategory,IF(NR_F_Role="All","*",NR_F_Role),NR_Location,IF(NR_F_Loc="All","*",NR_F_Loc),NR_ExpLevel,IF(NR_F_Exp="All","*",NR_F_Exp),NR_WorkMode,IF(NR_F_WM="All","*",NR_F_WM),NR_Industry,IF(NR_F_Ind="All","*",NR_F_Ind),NR_DupFlag,"Unique"),"n/a")
A35: Average Salary by Job Role (Lacs PA) | F35: Top Skills Requested
A36: Job_Role | B36: Avg_Salary_Min | C36: Avg_Salary_Max | D36: Avg_Salary | F36: Skill | G36: Mentions
A37: Sales Executive | B37: =IFERROR(AVERAGEIFS(NR_SalaryMin,NR_RoleCategory,A37,NR_RoleCategory,IF(NR_F_Role="All","*",NR_F_Role),NR_Location,IF(NR_F_Loc="All","*",NR_F_Loc),NR_ExpLevel,IF(NR_F_Exp="All","*",NR_F_Exp),NR_WorkMode,IF(NR_F_WM="All","*",NR_F_WM),NR_Industry,IF(NR_F_Ind="All","*",NR_F_Ind),NR_DupFlag,"Unique"),"n/a") | C37: =IFERROR(AVERAGEIFS(NR_SalaryMax,NR_RoleCategory,A37,NR_RoleCategory,IF(NR_F_Role="All","*",NR_F_Role),NR_Location,IF(NR_F_Loc="All","*",NR_F_Loc),NR_ExpLevel,IF(NR_F_Exp="All","*",NR_F_Exp),NR_WorkMode,IF(NR_F_WM="All","*",NR_F_WM),NR_Industry,IF(NR_F_Ind="All","*",NR_F_Ind),NR_DupFlag,"Unique"),"n/a") | D37: =IFERROR(AVERAGEIFS(NR_AvgSalary,NR_RoleCategory,A37,NR_RoleCategory,IF(NR_F_Role="All","*",NR_F_Role),NR_Location,IF(NR_F_Loc="All","*",NR_F_Loc),NR_ExpLevel,IF(NR_F_Exp="All","*",NR_F_Exp),NR_WorkMode,IF(NR_F_WM="All","*",NR_F_WM),NR_Industry,IF(NR_F_Ind="All","*",NR_F_Ind),NR_DupFlag,"Unique"),"n/a") | F37: Sales | G37: =COUNTIFS(NR_Skills,"*"&F37&"*",NR_RoleCategory,IF(NR_F_Role="All","*",NR_F_Role),NR_Location,IF(NR_F_Loc="All","*",NR_F_Loc),NR_ExpLevel,IF(NR_F_Exp="All","*",NR_F_Exp),NR_WorkMode,IF(NR_F_WM="All","*",NR_F_WM),NR_Industry,IF(NR_F_Ind="All","*",NR_F_Ind),NR_DupFlag,"Unique")
A38: Engineer (Technical) | B38: =IFERROR(AVERAGEIFS(NR_SalaryMin,NR_RoleCategory,A38,NR_RoleCategory,IF(NR_F_Role="All","*",NR_F_Role),NR_Location,IF(NR_F_Loc="All","*",NR_F_Loc),NR_ExpLevel,IF(NR_F_Exp="All","*",NR_F_Exp),NR_WorkMode,IF(NR_F_WM="All","*",NR_F_WM),NR_Industry,IF(NR_F_Ind="All","*",NR_F_Ind),NR_DupFlag,"Unique"),"n/a") | C38: =IFERROR(AVERAGEIFS(NR_SalaryMax,NR_RoleCategory,A38,NR_RoleCategory,IF(NR_F_Role="All","*",NR_F_Role),NR_Location,IF(NR_F_Loc="All","*",NR_F_Loc),NR_ExpLevel,IF(NR_F_Exp="All","*",NR_F_Exp),NR_WorkMode,IF(NR_F_WM="All","*",NR_F_WM),NR_Industry,IF(NR_F_Ind="All","*",NR_F_Ind),NR_DupFlag,"Unique"),"n/a") | D38: =IFERROR(AVERAGEIFS(NR_AvgSalary,NR_RoleCategory,A38,NR_RoleCategory,IF(NR_F_Role="All","*",NR_F_Role),NR_Location,IF(NR_F_Loc="All","*",NR_F_Loc),NR_ExpLevel,IF(NR_F_Exp="All","*",NR_F_Exp),NR_WorkMode,IF(NR_F_WM="All","*",NR_F_WM),NR_Industry,IF(NR_F_Ind="All","*",NR_F_Ind),NR_DupFlag,"Unique"),"n/a") | F38: Customer Service | G38: =COUNTIFS(NR_Skills,"*"&F38&"*",NR_RoleCategory,IF(NR_F_Role="All","*",NR_F_Role),NR_Location,IF(NR_F_Loc="All","*",NR_F_Loc),NR_ExpLevel,IF(NR_F_Exp="All","*",NR_F_Exp),NR_WorkMode,IF(NR_F_WM="All","*",NR_F_WM),NR_Industry,IF(NR_F_Ind="All","*",NR_F_Ind),NR_DupFlag,"Unique")
A39: Manager | B39: =IFERROR(AVERAGEIFS(NR_SalaryMin,NR_RoleCategory,A39,NR_RoleCategory,IF(NR_F_Role="All","*",NR_F_Role),NR_Location,IF(NR_F_Loc="All","*",NR_F_Loc),NR_ExpLevel,IF(NR_F_Exp="All","*",NR_F_Exp),NR_WorkMode,IF(NR_F_WM="All","*",NR_F_WM),NR_Industry,IF(NR_F_Ind="All","*",NR_F_Ind),NR_DupFlag,"Unique"),"n/a") | C39: =IFERROR(AVERAGEIFS(NR_SalaryMax,NR_RoleCategory,A39,NR_RoleCategory,IF(NR_F_Role="All","*",NR_F_Role),NR_Location,IF(NR_F_Loc="All","*",NR_F_Loc),NR_ExpLevel,IF(NR_F_Exp="All","*",NR_F_Exp),NR_WorkMode,IF(NR_F_WM="All","*",NR_F_WM),NR_Industry,IF(NR_F_Ind="All","*",NR_F_Ind),NR_DupFlag,"Unique"),"n/a") | D39: =IFERROR(AVERAGEIFS(NR_AvgSalary,NR_RoleCategory,A39,NR_RoleCategory,IF(NR_F_Role="All","*",NR_F_Role),NR_Location,IF(NR_F_Loc="All","*",NR_F_Loc),NR_ExpLevel,IF(NR_F_Exp="All","*",NR_F_Exp),NR_WorkMode,IF(NR_F_WM="All","*",NR_F_WM),NR_Industry,IF(NR_F_Ind="All","*",NR_F_Ind),NR_DupFlag,"Unique"),"n/a") | F39: Accounting | G39: =COUNTIFS(NR_Skills,"*"&F39&"*",NR_RoleCategory,IF(NR_F_Role="All","*",NR_F_Role),NR_Location,IF(NR_F_Loc="All","*",NR_F_Loc),NR_ExpLevel,IF(NR_F_Exp="All","*",NR_F_Exp),NR_WorkMode,IF(NR_F_WM="All","*",NR_F_WM),NR_Industry,IF(NR_F_Ind="All","*",NR_F_Ind),NR_DupFlag,"Unique")
A40: Software Developer | B40: =IFERROR(AVERAGEIFS(NR_SalaryMin,NR_RoleCategory,A40,NR_RoleCategory,IF(NR_F_Role="All","*",NR_F_Role),NR_Location,IF(NR_F_Loc="All","*",NR_F_Loc),NR_ExpLevel,IF(NR_F_Exp="All","*",NR_F_Exp),NR_WorkMode,IF(NR_F_WM="All","*",NR_F_WM),NR_Industry,IF(NR_F_Ind="All","*",NR_F_Ind),NR_DupFlag,"Unique"),"n/a") | C40: =IFERROR(AVERAGEIFS(NR_SalaryMax,NR_RoleCategory,A40,NR_RoleCategory,IF(NR_F_Role="All","*",NR_F_Role),NR_Location,IF(NR_F_Loc="All","*",NR_F_Loc),NR_ExpLevel,IF(NR_F_Exp="All","*",NR_F_Exp),NR_WorkMode,IF(NR_F_WM="All","*",NR_F_WM),NR_Industry,IF(NR_F_Ind="All","*",NR_F_Ind),NR_DupFlag,"Unique"),"n/a") | D40: =IFERROR(AVERAGEIFS(NR_AvgSalary,NR_RoleCategory,A40,NR_RoleCategory,IF(NR_F_Role="All","*",NR_F_Role),NR_Location,IF(NR_F_Loc="All","*",NR_F_Loc),NR_ExpLevel,IF(NR_F_Exp="All","*",NR_F_Exp),NR_WorkMode,IF(NR_F_WM="All","*",NR_F_WM),NR_Industry,IF(NR_F_Ind="All","*",NR_F_Ind),NR_DupFlag,"Unique"),"n/a") | F40: Lead Generation | G40: =COUNTIFS(NR_Skills,"*"&F40&"*",NR_RoleCategory,IF(NR_F_Role="All","*",NR_F_Role),NR_Location,IF(NR_F_Loc="All","*",NR_F_Loc),NR_ExpLevel,IF(NR_F_Exp="All","*",NR_F_Exp),NR_WorkMode,IF(NR_F_WM="All","*",NR_F_WM),NR_Industry,IF(NR_F_Ind="All","*",NR_F_Ind),NR_DupFlag,"Unique")
A41: Accountant / Finance | B41: =IFERROR(AVERAGEIFS(NR_SalaryMin,NR_RoleCategory,A41,NR_RoleCategory,IF(NR_F_Role="All","*",NR_F_Role),NR_Location,IF(NR_F_Loc="All","*",NR_F_Loc),NR_ExpLevel,IF(NR_F_Exp="All","*",NR_F_Exp),NR_WorkMode,IF(NR_F_WM="All","*",NR_F_WM),NR_Industry,IF(NR_F_Ind="All","*",NR_F_Ind),NR_DupFlag,"Unique"),"n/a") | C41: =IFERROR(AVERAGEIFS(NR_SalaryMax,NR_RoleCategory,A41,NR_RoleCategory,IF(NR_F_Role="All","*",NR_F_Role),NR_Location,IF(NR_F_Loc="All","*",NR_F_Loc),NR_ExpLevel,IF(NR_F_Exp="All","*",NR_F_Exp),NR_WorkMode,IF(NR_F_WM="All","*",NR_F_WM),NR_Industry,IF(NR_F_Ind="All","*",NR_F_Ind),NR_DupFlag,"Unique"),"n/a") | D41: =IFERROR(AVERAGEIFS(NR_AvgSalary,NR_RoleCategory,A41,NR_RoleCategory,IF(NR_F_Role="All","*",NR_F_Role),NR_Location,IF(NR_F_Loc="All","*",NR_F_Loc),NR_ExpLevel,IF(NR_F_Exp="All","*",NR_F_Exp),NR_WorkMode,IF(NR_F_WM="All","*",NR_F_WM),NR_Industry,IF(NR_F_Ind="All","*",NR_F_Ind),NR_DupFlag,"Unique"),"n/a") | F41: Java | G41: =COUNTIFS(NR_Skills,"*"&F41&"*",NR_RoleCategory,IF(NR_F_Role="All","*",NR_F_Role),NR_Location,IF(NR_F_Loc="All","*",NR_F_Loc),NR_ExpLevel,IF(NR_F_Exp="All","*",NR_F_Exp),NR_WorkMode,IF(NR_F_WM="All","*",NR_F_WM),NR_Industry,IF(NR_F_Ind="All","*",NR_F_Ind),NR_DupFlag,"Unique")
A42: Customer Support | B42: =IFERROR(AVERAGEIFS(NR_SalaryMin,NR_RoleCategory,A42,NR_RoleCategory,IF(NR_F_Role="All","*",NR_F_Role),NR_Location,IF(NR_F_Loc="All","*",NR_F_Loc),NR_ExpLevel,IF(NR_F_Exp="All","*",NR_F_Exp),NR_WorkMode,IF(NR_F_WM="All","*",NR_F_WM),NR_Industry,IF(NR_F_Ind="All","*",NR_F_Ind),NR_DupFlag,"Unique"),"n/a") | C42: =IFERROR(AVERAGEIFS(NR_SalaryMax,NR_RoleCategory,A42,NR_RoleCategory,IF(NR_F_Role="All","*",NR_F_Role),NR_Location,IF(NR_F_Loc="All","*",NR_F_Loc),NR_ExpLevel,IF(NR_F_Exp="All","*",NR_F_Exp),NR_WorkMode,IF(NR_F_WM="All","*",NR_F_WM),NR_Industry,IF(NR_F_Ind="All","*",NR_F_Ind),NR_DupFlag,"Unique"),"n/a") | D42: =IFERROR(AVERAGEIFS(NR_AvgSalary,NR_RoleCategory,A42,NR_RoleCategory,IF(NR_F_Role="All","*",NR_F_Role),NR_Location,IF(NR_F_Loc="All","*",NR_F_Loc),NR_ExpLevel,IF(NR_F_Exp="All","*",NR_F_Exp),NR_WorkMode,IF(NR_F_WM="All","*",NR_F_WM),NR_Industry,IF(NR_F_Ind="All","*",NR_F_Ind),NR_DupFlag,"Unique"),"n/a") | F42: Marketing | G42: =COUNTIFS(NR_Skills,"*"&F42&"*",NR_RoleCategory,IF(NR_F_Role="All","*",NR_F_Role),NR_Location,IF(NR_F_Loc="All","*",NR_F_Loc),NR_ExpLevel,IF(NR_F_Exp="All","*",NR_F_Exp),NR_WorkMode,IF(NR_F_WM="All","*",NR_F_WM),NR_Industry,IF(NR_F_Ind="All","*",NR_F_Ind),NR_DupFlag,"Unique")
A43: HR / Recruiter | B43: =IFERROR(AVERAGEIFS(NR_SalaryMin,NR_RoleCategory,A43,NR_RoleCategory,IF(NR_F_Role="All","*",NR_F_Role),NR_Location,IF(NR_F_Loc="All","*",NR_F_Loc),NR_ExpLevel,IF(NR_F_Exp="All","*",NR_F_Exp),NR_WorkMode,IF(NR_F_WM="All","*",NR_F_WM),NR_Industry,IF(NR_F_Ind="All","*",NR_F_Ind),NR_DupFlag,"Unique"),"n/a") | C43: =IFERROR(AVERAGEIFS(NR_SalaryMax,NR_RoleCategory,A43,NR_RoleCategory,IF(NR_F_Role="All","*",NR_F_Role),NR_Location,IF(NR_F_Loc="All","*",NR_F_Loc),NR_ExpLevel,IF(NR_F_Exp="All","*",NR_F_Exp),NR_WorkMode,IF(NR_F_WM="All","*",NR_F_WM),NR_Industry,IF(NR_F_Ind="All","*",NR_F_Ind),NR_DupFlag,"Unique"),"n/a") | D43: =IFERROR(AVERAGEIFS(NR_AvgSalary,NR_RoleCategory,A43,NR_RoleCategory,IF(NR_F_Role="All","*",NR_F_Role),NR_Location,IF(NR_F_Loc="All","*",NR_F_Loc),NR_ExpLevel,IF(NR_F_Exp="All","*",NR_F_Exp),NR_WorkMode,IF(NR_F_WM="All","*",NR_F_WM),NR_Industry,IF(NR_F_Ind="All","*",NR_F_Ind),NR_DupFlag,"Unique"),"n/a") | F43: Business Development | G43: =COUNTIFS(NR_Skills,"*"&F43&"*",NR_RoleCategory,IF(NR_F_Role="All","*",NR_F_Role),NR_Location,IF(NR_F_Loc="All","*",NR_F_Loc),NR_ExpLevel,IF(NR_F_Exp="All","*",NR_F_Exp),NR_WorkMode,IF(NR_F_WM="All","*",NR_F_WM),NR_Industry,IF(NR_F_Ind="All","*",NR_F_Ind),NR_DupFlag,"Unique")
A44: Business Development | B44: =IFERROR(AVERAGEIFS(NR_SalaryMin,NR_RoleCategory,A44,NR_RoleCategory,IF(NR_F_Role="All","*",NR_F_Role),NR_Location,IF(NR_F_Loc="All","*",NR_F_Loc),NR_ExpLevel,IF(NR_F_Exp="All","*",NR_F_Exp),NR_WorkMode,IF(NR_F_WM="All","*",NR_F_WM),NR_Industry,IF(NR_F_Ind="All","*",NR_F_Ind),NR_DupFlag,"Unique"),"n/a") | C44: =IFERROR(AVERAGEIFS(NR_SalaryMax,NR_RoleCategory,A44,NR_RoleCategory,IF(NR_F_Role="All","*",NR_F_Role),NR_Location,IF(NR_F_Loc="All","*",NR_F_Loc),NR_ExpLevel,IF(NR_F_Exp="All","*",NR_F_Exp),NR_WorkMode,IF(NR_F_WM="All","*",NR_F_WM),NR_Industry,IF(NR_F_Ind="All","*",NR_F_Ind),NR_DupFlag,"Unique"),"n/a") | D44: =IFERROR(AVERAGEIFS(NR_AvgSalary,NR_RoleCategory,A44,NR_RoleCategory,IF(NR_F_Role="All","*",NR_F_Role),NR_Location,IF(NR_F_Loc="All","*",NR_F_Loc),NR_ExpLevel,IF(NR_F_Exp="All","*",NR_F_Exp),NR_WorkMode,IF(NR_F_WM="All","*",NR_F_WM),NR_Industry,IF(NR_F_Ind="All","*",NR_F_Ind),NR_DupFlag,"Unique"),"n/a") | F44: Team Handling | G44: =COUNTIFS(NR_Skills,"*"&F44&"*",NR_RoleCategory,IF(NR_F_Role="All","*",NR_F_Role),NR_Location,IF(NR_F_Loc="All","*",NR_F_Loc),NR_ExpLevel,IF(NR_F_Exp="All","*",NR_F_Exp),NR_WorkMode,IF(NR_F_WM="All","*",NR_F_WM),NR_Industry,IF(NR_F_Ind="All","*",NR_F_Ind),NR_DupFlag,"Unique")
A45: Teacher / Trainer | B45: =IFERROR(AVERAGEIFS(NR_SalaryMin,NR_RoleCategory,A45,NR_RoleCategory,IF(NR_F_Role="All","*",NR_F_Role),NR_Location,IF(NR_F_Loc="All","*",NR_F_Loc),NR_ExpLevel,IF(NR_F_Exp="All","*",NR_F_Exp),NR_WorkMode,IF(NR_F_WM="All","*",NR_F_WM),NR_Industry,IF(NR_F_Ind="All","*",NR_F_Ind),NR_DupFlag,"Unique"),"n/a") | C45: =IFERROR(AVERAGEIFS(NR_SalaryMax,NR_RoleCategory,A45,NR_RoleCategory,IF(NR_F_Role="All","*",NR_F_Role),NR_Location,IF(NR_F_Loc="All","*",NR_F_Loc),NR_ExpLevel,IF(NR_F_Exp="All","*",NR_F_Exp),NR_WorkMode,IF(NR_F_WM="All","*",NR_F_WM),NR_Industry,IF(NR_F_Ind="All","*",NR_F_Ind),NR_DupFlag,"Unique"),"n/a") | D45: =IFERROR(AVERAGEIFS(NR_AvgSalary,NR_RoleCategory,A45,NR_RoleCategory,IF(NR_F_Role="All","*",NR_F_Role),NR_Location,IF(NR_F_Loc="All","*",NR_F_Loc),NR_ExpLevel,IF(NR_F_Exp="All","*",NR_F_Exp),NR_WorkMode,IF(NR_F_WM="All","*",NR_F_WM),NR_Industry,IF(NR_F_Ind="All","*",NR_F_Ind),NR_DupFlag,"Unique"),"n/a") | F45: Communication Skills | G45: =COUNTIFS(NR_Skills,"*"&F45&"*",NR_RoleCategory,IF(NR_F_Role="All","*",NR_F_Role),NR_Location,IF(NR_F_Loc="All","*",NR_F_Loc),NR_ExpLevel,IF(NR_F_Exp="All","*",NR_F_Exp),NR_WorkMode,IF(NR_F_WM="All","*",NR_F_WM),NR_Industry,IF(NR_F_Ind="All","*",NR_F_Ind),NR_DupFlag,"Unique")
A46: Marketing Executive | B46: =IFERROR(AVERAGEIFS(NR_SalaryMin,NR_RoleCategory,A46,NR_RoleCategory,IF(NR_F_Role="All","*",NR_F_Role),NR_Location,IF(NR_F_Loc="All","*",NR_F_Loc),NR_ExpLevel,IF(NR_F_Exp="All","*",NR_F_Exp),NR_WorkMode,IF(NR_F_WM="All","*",NR_F_WM),NR_Industry,IF(NR_F_Ind="All","*",NR_F_Ind),NR_DupFlag,"Unique"),"n/a") | C46: =IFERROR(AVERAGEIFS(NR_SalaryMax,NR_RoleCategory,A46,NR_RoleCategory,IF(NR_F_Role="All","*",NR_F_Role),NR_Location,IF(NR_F_Loc="All","*",NR_F_Loc),NR_ExpLevel,IF(NR_F_Exp="All","*",NR_F_Exp),NR_WorkMode,IF(NR_F_WM="All","*",NR_F_WM),NR_Industry,IF(NR_F_Ind="All","*",NR_F_Ind),NR_DupFlag,"Unique"),"n/a") | D46: =IFERROR(AVERAGEIFS(NR_AvgSalary,NR_RoleCategory,A46,NR_RoleCategory,IF(NR_F_Role="All","*",NR_F_Role),NR_Location,IF(NR_F_Loc="All","*",NR_F_Loc),NR_ExpLevel,IF(NR_F_Exp="All","*",NR_F_Exp),NR_WorkMode,IF(NR_F_WM="All","*",NR_F_WM),NR_Industry,IF(NR_F_Ind="All","*",NR_F_Ind),NR_DupFlag,"Unique"),"n/a") | F46: BPO | G46: =COUNTIFS(NR_Skills,"*"&F46&"*",NR_RoleCategory,IF(NR_F_Role="All","*",NR_F_Role),NR_Location,IF(NR_F_Loc="All","*",NR_F_Loc),NR_ExpLevel,IF(NR_F_Exp="All","*",NR_F_Exp),NR_WorkMode,IF(NR_F_WM="All","*",NR_F_WM),NR_Industry,IF(NR_F_Ind="All","*",NR_F_Ind),NR_DupFlag,"Unique")
A47: Healthcare | B47: =IFERROR(AVERAGEIFS(NR_SalaryMin,NR_RoleCategory,A47,NR_RoleCategory,IF(NR_F_Role="All","*",NR_F_Role),NR_Location,IF(NR_F_Loc="All","*",NR_F_Loc),NR_ExpLevel,IF(NR_F_Exp="All","*",NR_F_Exp),NR_WorkMode,IF(NR_F_WM="All","*",NR_F_WM),NR_Industry,IF(NR_F_Ind="All","*",NR_F_Ind),NR_DupFlag,"Unique"),"n/a") | C47: =IFERROR(AVERAGEIFS(NR_SalaryMax,NR_RoleCategory,A47,NR_RoleCategory,IF(NR_F_Role="All","*",NR_F_Role),NR_Location,IF(NR_F_Loc="All","*",NR_F_Loc),NR_ExpLevel,IF(NR_F_Exp="All","*",NR_F_Exp),NR_WorkMode,IF(NR_F_WM="All","*",NR_F_WM),NR_Industry,IF(NR_F_Ind="All","*",NR_F_Ind),NR_DupFlag,"Unique"),"n/a") | D47: =IFERROR(AVERAGEIFS(NR_AvgSalary,NR_RoleCategory,A47,NR_RoleCategory,IF(NR_F_Role="All","*",NR_F_Role),NR_Location,IF(NR_F_Loc="All","*",NR_F_Loc),NR_ExpLevel,IF(NR_F_Exp="All","*",NR_F_Exp),NR_WorkMode,IF(NR_F_WM="All","*",NR_F_WM),NR_Industry,IF(NR_F_Ind="All","*",NR_F_Ind),NR_DupFlag,"Unique"),"n/a") | F47: Data Analysis | G47: =COUNTIFS(NR_Skills,"*"&F47&"*",NR_RoleCategory,IF(NR_F_Role="All","*",NR_F_Role),NR_Location,IF(NR_F_Loc="All","*",NR_F_Loc),NR_ExpLevel,IF(NR_F_Exp="All","*",NR_F_Exp),NR_WorkMode,IF(NR_F_WM="All","*",NR_F_WM),NR_Industry,IF(NR_F_Ind="All","*",NR_F_Ind),NR_DupFlag,"Unique")
A48: Data Analyst | B48: =IFERROR(AVERAGEIFS(NR_SalaryMin,NR_RoleCategory,A48,NR_RoleCategory,IF(NR_F_Role="All","*",NR_F_Role),NR_Location,IF(NR_F_Loc="All","*",NR_F_Loc),NR_ExpLevel,IF(NR_F_Exp="All","*",NR_F_Exp),NR_WorkMode,IF(NR_F_WM="All","*",NR_F_WM),NR_Industry,IF(NR_F_Ind="All","*",NR_F_Ind),NR_DupFlag,"Unique"),"n/a") | C48: =IFERROR(AVERAGEIFS(NR_SalaryMax,NR_RoleCategory,A48,NR_RoleCategory,IF(NR_F_Role="All","*",NR_F_Role),NR_Location,IF(NR_F_Loc="All","*",NR_F_Loc),NR_ExpLevel,IF(NR_F_Exp="All","*",NR_F_Exp),NR_WorkMode,IF(NR_F_WM="All","*",NR_F_WM),NR_Industry,IF(NR_F_Ind="All","*",NR_F_Ind),NR_DupFlag,"Unique"),"n/a") | D48: =IFERROR(AVERAGEIFS(NR_AvgSalary,NR_RoleCategory,A48,NR_RoleCategory,IF(NR_F_Role="All","*",NR_F_Role),NR_Location,IF(NR_F_Loc="All","*",NR_F_Loc),NR_ExpLevel,IF(NR_F_Exp="All","*",NR_F_Exp),NR_WorkMode,IF(NR_F_WM="All","*",NR_F_WM),NR_Industry,IF(NR_F_Ind="All","*",NR_F_Ind),NR_DupFlag,"Unique"),"n/a") | F48: AutoCAD | G48: =COUNTIFS(NR_Skills,"*"&F48&"*",NR_RoleCategory,IF(NR_F_Role="All","*",NR_F_Role),NR_Location,IF(NR_F_Loc="All","*",NR_F_Loc),NR_ExpLevel,IF(NR_F_Exp="All","*",NR_F_Exp),NR_WorkMode,IF(NR_F_WM="All","*",NR_F_WM),NR_Industry,IF(NR_F_Ind="All","*",NR_F_Ind),NR_DupFlag,"Unique")
A49: Other | B49: =IFERROR(AVERAGEIFS(NR_SalaryMin,NR_RoleCategory,A49,NR_RoleCategory,IF(NR_F_Role="All","*",NR_F_Role),NR_Location,IF(NR_F_Loc="All","*",NR_F_Loc),NR_ExpLevel,IF(NR_F_Exp="All","*",NR_F_Exp),NR_WorkMode,IF(NR_F_WM="All","*",NR_F_WM),NR_Industry,IF(NR_F_Ind="All","*",NR_F_Ind),NR_DupFlag,"Unique"),"n/a") | C49: =IFERROR(AVERAGEIFS(NR_SalaryMax,NR_RoleCategory,A49,NR_RoleCategory,IF(NR_F_Role="All","*",NR_F_Role),NR_Location,IF(NR_F_Loc="All","*",NR_F_Loc),NR_ExpLevel,IF(NR_F_Exp="All","*",NR_F_Exp),NR_WorkMode,IF(NR_F_WM="All","*",NR_F_WM),NR_Industry,IF(NR_F_Ind="All","*",NR_F_Ind),NR_DupFlag,"Unique"),"n/a") | D49: =IFERROR(AVERAGEIFS(NR_AvgSalary,NR_RoleCategory,A49,NR_RoleCategory,IF(NR_F_Role="All","*",NR_F_Role),NR_Location,IF(NR_F_Loc="All","*",NR_F_Loc),NR_ExpLevel,IF(NR_F_Exp="All","*",NR_F_Exp),NR_WorkMode,IF(NR_F_WM="All","*",NR_F_WM),NR_Industry,IF(NR_F_Ind="All","*",NR_F_Ind),NR_DupFlag,"Unique"),"n/a")

Sheet Dashboard
A1: Job Market Analysis Dashboard
A3: Job Role | D3: Location | G3: Experience | J3: Work Mode | M3: Industry
B4: All | E4: All | H4: All | K4: All | N4: All
A6: Total Jobs | D6: Average Salary | G6: Most In-Demand Role | J6: Most Common Location | M6: Remote Job %
A7: =COUNTIFS(NR_RoleCategory,IF(NR_F_Role="All","*",NR_F_Role),NR_Location,IF(NR_F_Loc="All","*",NR_F_Loc),NR_ExpLevel,IF(NR_F_Exp="All","*",NR_F_Exp),NR_WorkMode,IF(NR_F_WM="All","*",NR_F_WM),NR_Industry,IF(NR_F_Ind="All","*",NR_F_Ind),NR_DupFlag,"Unique") | D7: =AVERAGEIFS(NR_AvgSalary,NR_RoleCategory,IF(NR_F_Role="All","*",NR_F_Role),NR_Location,IF(NR_F_Loc="All","*",NR_F_Loc),NR_ExpLevel,IF(NR_F_Exp="All","*",NR_F_Exp),NR_WorkMode,IF(NR_F_WM="All","*",NR_F_WM),NR_Industry,IF(NR_F_Ind="All","*",NR_F_Ind),NR_DupFlag,"Unique") | G7: =INDEX(Analysis!A5:A16,MATCH(MAX(Analysis!B5:B16),Analysis!B5:B16,0)) | J7: =INDEX(Analysis!D5:D24,MATCH(MAX(Analysis!E5:E24),Analysis!E5:E24,0)) | M7: =COUNTIFS(NR_WorkMode,"Remote",NR_RoleCategory,IF(NR_F_Role="All","*",NR_F_Role),NR_Location,IF(NR_F_Loc="All","*",NR_F_Loc),NR_ExpLevel,IF(NR_F_Exp="All","*",NR_F_Exp),NR_WorkMode,IF(NR_F_WM="All","*",NR_F_WM),NR_Industry,IF(NR_F_Ind="All","*",NR_F_Ind),NR_DupFlag,"Unique")/COUNTIFS(NR_RoleCategory,IF(NR_F_Role="All","*",NR_F_Role),NR_Location,IF(NR_F_Loc="All","*",NR_F_Loc),NR_ExpLevel,IF(NR_F_Exp="All","*",NR_F_Exp),NR_WorkMode,IF(NR_F_WM="All","*",NR_F_WM),NR_Industry,IF(NR_F_Ind="All","*",NR_F_Ind),NR_DupFlag,"Unique")

Sheet Filter_Lists
A1: Job Role | B1: Location | C1: Experience | D1: Work Mode | E1: Industry
A2: All | B2: All | C2: All | D2: All | E2: All
A3: =_xlfn.IFS(ISNUMBER(SEARCH("data analy",B100)),"Data Analyst",ISNUMBER(SEARCH("business analy",B100)),"Business Analyst",OR(ISNUMBER(SEARCH("developer",B100)),ISNUMBER(SEARCH("software engineer",B100)),ISNUMBER(SEARCH("programmer",B100))),"Software Developer",ISNUMBER(SEARCH("business development",B100)),"Business Development",ISNUMBER(SEARCH("sales",B100)),"Sales Executive",ISNUMBER(SEARCH("marketing",B100)),"Marketing Executive",OR(ISNUMBER(SEARCH("hr ",B100)),ISNUMBER(SEARCH("recruit",B100)),ISNUMBER(SEARCH("human resource",B100))),"HR / Recruiter",OR(ISNUMBER(SEARCH("account",B100)),ISNUMBER(SEARCH("finance",B100)),ISNUMBER(SEARCH("tax",B100)),ISNUMBER(SEARCH("audit",B100))),"Accountant / Finance",OR(ISNUMBER(SEARCH("customer service",B100)),ISNUMBER(SEARCH("customer support",B100)),ISNUMBER(SEARCH("customer care",B100)),ISNUMBER(SEARCH("voice process",B100)),ISNUMBER(SEARCH("bpo",B100))),"Customer Support",ISNUMBER(SEARCH("engineer",B100)),"Engineer (Technical)",ISNUMBER(SEARCH("manager",B100)),"Manager",OR(ISNUMBER(SEARCH("teacher",B100)),ISNUMBER(SEARCH("trainer",B100)),ISNUMBER(SEARCH("faculty",B100))),"Teacher / Trainer",OR(ISNUMBER(SEARCH("doctor",B100)),ISNUMBER(SEARCH("nurse",B100)),ISNUMBER(SEARCH("medical",B100)),ISNUMBER(SEARCH("pharma",B100)),ISNUMBER(SEARCH("clinical",B100))),"Healthcare",TRUE,"Other") | B3: =IF(PROPER(TRIM(Raw_Data!D10))="Bangalore","Bengaluru",IF(PROPER(TRIM(Raw_Data!D10))="Gurgaon","Gurugram",IF(OR(PROPER(TRIM(Raw_Data!D10))="New Delhi",PROPER(TRIM(Raw_Data!D10))="Delhi"),"Delhi",PROPER(TRIM(Raw_Data!D10))))) | C3: =IF(TRIM(Raw_Data!F10&"")="","Not Specified",Raw_Data!F10) | D3: =Raw_Data!H10 | E3: =Raw_Data!E10
A4: =_xlfn.IFS(ISNUMBER(SEARCH("data analy",B101)),"Data Analyst",ISNUMBER(SEARCH("business analy",B101)),"Business Analyst",OR(ISNUMBER(SEARCH("developer",B101)),ISNUMBER(SEARCH("software engineer",B101)),ISNUMBER(SEARCH("programmer",B101))),"Software Developer",ISNUMBER(SEARCH("business development",B101)),"Business Development",ISNUMBER(SEARCH("sales",B101)),"Sales Executive",ISNUMBER(SEARCH("marketing",B101)),"Marketing Executive",OR(ISNUMBER(SEARCH("hr ",B101)),ISNUMBER(SEARCH("recruit",B101)),ISNUMBER(SEARCH("human resource",B101))),"HR / Recruiter",OR(ISNUMBER(SEARCH("account",B101)),ISNUMBER(SEARCH("finance",B101)),ISNUMBER(SEARCH("tax",B101)),ISNUMBER(SEARCH("audit",B101))),"Accountant / Finance",OR(ISNUMBER(SEARCH("customer service",B101)),ISNUMBER(SEARCH("customer support",B101)),ISNUMBER(SEARCH("customer care",B101)),ISNUMBER(SEARCH("voice process",B101)),ISNUMBER(SEARCH("bpo",B101))),"Customer Support",ISNUMBER(SEARCH("engineer",B101)),"Engineer (Technical)",ISNUMBER(SEARCH("manager",B101)),"Manager",OR(ISNUMBER(SEARCH("teacher",B101)),ISNUMBER(SEARCH("trainer",B101)),ISNUMBER(SEARCH("faculty",B101))),"Teacher / Trainer",OR(ISNUMBER(SEARCH("doctor",B101)),ISNUMBER(SEARCH("nurse",B101)),ISNUMBER(SEARCH("medical",B101)),ISNUMBER(SEARCH("pharma",B101)),ISNUMBER(SEARCH("clinical",B101))),"Healthcare",TRUE,"Other") | B4: =IF(PROPER(TRIM(Raw_Data!D100))="Bangalore","Bengaluru",IF(PROPER(TRIM(Raw_Data!D100))="Gurgaon","Gurugram",IF(OR(PROPER(TRIM(Raw_Data!D100))="New Delhi",PROPER(TRIM(Raw_Data!D100))="Delhi"),"Delhi",PROPER(TRIM(Raw_Data!D100))))) | C4: =IF(TRIM(Raw_Data!F100&"")="","Not Specified",Raw_Data!F100) | D4: =Raw_Data!H100 | E4: =Raw_Data!E100
A5: =_xlfn.IFS(ISNUMBER(SEARCH("data analy",B102)),"Data Analyst",ISNUMBER(SEARCH("business analy",B102)),"Business Analyst",OR(ISNUMBER(SEARCH("developer",B102)),ISNUMBER(SEARCH("software engineer",B102)),ISNUMBER(SEARCH("programmer",B102))),"Software Developer",ISNUMBER(SEARCH("business development",B102)),"Business Development",ISNUMBER(SEARCH("sales",B102)),"Sales Executive",ISNUMBER(SEARCH("marketing",B102)),"Marketing Executive",OR(ISNUMBER(SEARCH("hr ",B102)),ISNUMBER(SEARCH("recruit",B102)),ISNUMBER(SEARCH("human resource",B102))),"HR / Recruiter",OR(ISNUMBER(SEARCH("account",B102)),ISNUMBER(SEARCH("finance",B102)),ISNUMBER(SEARCH("tax",B102)),ISNUMBER(SEARCH("audit",B102))),"Accountant / Finance",OR(ISNUMBER(SEARCH("customer service",B102)),ISNUMBER(SEARCH("customer support",B102)),ISNUMBER(SEARCH("customer care",B102)),ISNUMBER(SEARCH("voice process",B102)),ISNUMBER(SEARCH("bpo",B102))),"Customer Support",ISNUMBER(SEARCH("engineer",B102)),"Engineer (Technical)",ISNUMBER(SEARCH("manager",B102)),"Manager",OR(ISNUMBER(SEARCH("teacher",B102)),ISNUMBER(SEARCH("trainer",B102)),ISNUMBER(SEARCH("faculty",B102))),"Teacher / Trainer",OR(ISNUMBER(SEARCH("doctor",B102)),ISNUMBER(SEARCH("nurse",B102)),ISNUMBER(SEARCH("medical",B102)),ISNUMBER(SEARCH("pharma",B102)),ISNUMBER(SEARCH("clinical",B102))),"Healthcare",TRUE,"Other") | B5: =IF(PROPER(TRIM(Raw_Data!D101))="Bangalore","Bengaluru",IF(PROPER(TRIM(Raw_Data!D101))="Gurgaon","Gurugram",IF(OR(PROPER(TRIM(Raw_Data!D101))="New Delhi",PROPER(TRIM(Raw_Data!D101))="Delhi"),"Delhi",PROPER(TRIM(Raw_Data!D101))))) | C5: =IF(TRIM(Raw_Data!F101&"")="","Not Specified",Raw_Data!F101) | D5: =Raw_Data!H101 | E5: =Raw_Data!E101
A6: =_xlfn.IFS(ISNUMBER(SEARCH("data analy",B103)),"Data Analyst",ISNUMBER(SEARCH("business analy",B103)),"Business Analyst",OR(ISNUMBER(SEARCH("developer",B103)),ISNUMBER(SEARCH("software engineer",B103)),ISNUMBER(SEARCH("programmer",B103))),"Software Developer",ISNUMBER(SEARCH("business development",B103)),"Business Development",ISNUMBER(SEARCH("sales",B103)),"Sales Executive",ISNUMBER(SEARCH("marketing",B103)),"Marketing Executive",OR(ISNUMBER(SEARCH("hr ",B103)),ISNUMBER(SEARCH("recruit",B103)),ISNUMBER(SEARCH("human resource",B103))),"HR / Recruiter",OR(ISNUMBER(SEARCH("account",B103)),ISNUMBER(SEARCH("finance",B103)),ISNUMBER(SEARCH("tax",B103)),ISNUMBER(SEARCH("audit",B103))),"Accountant / Finance",OR(ISNUMBER(SEARCH("customer service",B103)),ISNUMBER(SEARCH("customer support",B103)),ISNUMBER(SEARCH("customer care",B103)),ISNUMBER(SEARCH("voice process",B103)),ISNUMBER(SEARCH("bpo",B103))),"Customer Support",ISNUMBER(SEARCH("engineer",B103)),"Engineer (Technical)",ISNUMBER(SEARCH("manager",B103)),"Manager",OR(ISNUMBER(SEARCH("teacher",B103)),ISNUMBER(SEARCH("trainer",B103)),ISNUMBER(SEARCH("faculty",B103))),"Teacher / Trainer",OR(ISNUMBER(SEARCH("doctor",B103)),ISNUMBER(SEARCH("nurse",B103)),ISNUMBER(SEARCH("medical",B103)),ISNUMBER(SEARCH("pharma",B103)),ISNUMBER(SEARCH("clinical",B103))),"Healthcare",TRUE,"Other") | B6: =IF(PROPER(TRIM(Raw_Data!D102))="Bangalore","Bengaluru",IF(PROPER(TRIM(Raw_Data!D102))="Gurgaon","Gurugram",IF(OR(PROPER(TRIM(Raw_Data!D102))="New Delhi",PROPER(TRIM(Raw_Data!D102))="Delhi"),"Delhi",PROPER(TRIM(Raw_Data!D102))))) | C6: =IF(TRIM(Raw_Data!F102&"")="","Not Specified",Raw_Data!F102) | D6: =Raw_Data!H102 | E6: =Raw_Data!E102
A7: =_xlfn.IFS(ISNUMBER(SEARCH("data analy",B104)),"Data Analyst",ISNUMBER(SEARCH("business analy",B104)),"Business Analyst",OR(ISNUMBER(SEARCH("developer",B104)),ISNUMBER(SEARCH("software engineer",B104)),ISNUMBER(SEARCH("programmer",B104))),"Software Developer",ISNUMBER(SEARCH("business development",B104)),"Business Development",ISNUMBER(SEARCH("sales",B104)),"Sales Executive",ISNUMBER(SEARCH("marketing",B104)),"Marketing Executive",OR(ISNUMBER(SEARCH("hr ",B104)),ISNUMBER(SEARCH("recruit",B104)),ISNUMBER(SEARCH("human resource",B104))),"HR / Recruiter",OR(ISNUMBER(SEARCH("account",B104)),ISNUMBER(SEARCH("finance",B104)),ISNUMBER(SEARCH("tax",B104)),ISNUMBER(SEARCH("audit",B104))),"Accountant / Finance",OR(ISNUMBER(SEARCH("customer service",B104)),ISNUMBER(SEARCH("customer support",B104)),ISNUMBER(SEARCH("customer care",B104)),ISNUMBER(SEARCH("voice process",B104)),ISNUMBER(SEARCH("bpo",B104))),"Customer Support",ISNUMBER(SEARCH("engineer",B104)),"Engineer (Technical)",ISNUMBER(SEARCH("manager",B104)),"Manager",OR(ISNUMBER(SEARCH("teacher",B104)),ISNUMBER(SEARCH("trainer",B104)),ISNUMBER(SEARCH("faculty",B104))),"Teacher / Trainer",OR(ISNUMBER(SEARCH("doctor",B104)),ISNUMBER(SEARCH("nurse",B104)),ISNUMBER(SEARCH("medical",B104)),ISNUMBER(SEARCH("pharma",B104)),ISNUMBER(SEARCH("clinical",B104))),"Healthcare",TRUE,"Other") | B7: =IF(PROPER(TRIM(Raw_Data!D103))="Bangalore","Bengaluru",IF(PROPER(TRIM(Raw_Data!D103))="Gurgaon","Gurugram",IF(OR(PROPER(TRIM(Raw_Data!D103))="New Delhi",PROPER(TRIM(Raw_Data!D103))="Delhi"),"Delhi",PROPER(TRIM(Raw_Data!D103))))) | C7: =IF(TRIM(Raw_Data!F103&"")="","Not Specified",Raw_Data!F103) | D7: =Raw_Data!H103 | E7: =Raw_Data!E103
A8: =_xlfn.IFS(ISNUMBER(SEARCH("data analy",B105)),"Data Analyst",ISNUMBER(SEARCH("business analy",B105)),"Business Analyst",OR(ISNUMBER(SEARCH("developer",B105)),ISNUMBER(SEARCH("software engineer",B105)),ISNUMBER(SEARCH("programmer",B105))),"Software Developer",ISNUMBER(SEARCH("business development",B105)),"Business Development",ISNUMBER(SEARCH("sales",B105)),"Sales Executive",ISNUMBER(SEARCH("marketing",B105)),"Marketing Executive",OR(ISNUMBER(SEARCH("hr ",B105)),ISNUMBER(SEARCH("recruit",B105)),ISNUMBER(SEARCH("human resource",B105))),"HR / Recruiter",OR(ISNUMBER(SEARCH("account",B105)),ISNUMBER(SEARCH("finance",B105)),ISNUMBER(SEARCH("tax",B105)),ISNUMBER(SEARCH("audit",B105))),"Accountant / Finance",OR(ISNUMBER(SEARCH("customer service",B105)),ISNUMBER(SEARCH("customer support",B105)),ISNUMBER(SEARCH("customer care",B105)),ISNUMBER(SEARCH("voice process",B105)),ISNUMBER(SEARCH("bpo",B105))),"Customer Support",ISNUMBER(SEARCH("engineer",B105)),"Engineer (Technical)",ISNUMBER(SEARCH("manager",B105)),"Manager",OR(ISNUMBER(SEARCH("teacher",B105)),ISNUMBER(SEARCH("trainer",B105)),ISNUMBER(SEARCH("faculty",B105))),"Teacher / Trainer",OR(ISNUMBER(SEARCH("doctor",B105)),ISNUMBER(SEARCH("nurse",B105)),ISNUMBER(SEARCH("medical",B105)),ISNUMBER(SEARCH("pharma",B105)),ISNUMBER(SEARCH("clinical",B105))),"Healthcare",TRUE,"Other") | B8: =IF(PROPER(TRIM(Raw_Data!D104))="Bangalore","Bengaluru",IF(PROPER(TRIM(Raw_Data!D104))="Gurgaon","Gurugram",IF(OR(PROPER(TRIM(Raw_Data!D104))="New Delhi",PROPER(TRIM(Raw_Data!D104))="Delhi"),"Delhi",PROPER(TRIM(Raw_Data!D104))))) | C8: =IF(TRIM(Raw_Data!F104&"")="","Not Specified",Raw_Data!F104) | D8: =Raw_Data!H104 | E8: =Raw_Data!E104
A9: =_xlfn.IFS(ISNUMBER(SEARCH("data analy",B106)),"Data Analyst",ISNUMBER(SEARCH("business analy",B106)),"Business Analyst",OR(ISNUMBER(SEARCH("developer",B106)),ISNUMBER(SEARCH("software engineer",B106)),ISNUMBER(SEARCH("programmer",B106))),"Software Developer",ISNUMBER(SEARCH("business development",B106)),"Business Development",ISNUMBER(SEARCH("sales",B106)),"Sales Executive",ISNUMBER(SEARCH("marketing",B106)),"Marketing Executive",OR(ISNUMBER(SEARCH("hr ",B106)),ISNUMBER(SEARCH("recruit",B106)),ISNUMBER(SEARCH("human resource",B106))),"HR / Recruiter",OR(ISNUMBER(SEARCH("account",B106)),ISNUMBER(SEARCH("finance",B106)),ISNUMBER(SEARCH("tax",B106)),ISNUMBER(SEARCH("audit",B106))),"Accountant / Finance",OR(ISNUMBER(SEARCH("customer service",B106)),ISNUMBER(SEARCH("customer support",B106)),ISNUMBER(SEARCH("customer care",B106)),ISNUMBER(SEARCH("voice process",B106)),ISNUMBER(SEARCH("bpo",B106))),"Customer Support",ISNUMBER(SEARCH("engineer",B106)),"Engineer (Technical)",ISNUMBER(SEARCH("manager",B106)),"Manager",OR(ISNUMBER(SEARCH("teacher",B106)),ISNUMBER(SEARCH("trainer",B106)),ISNUMBER(SEARCH("faculty",B106))),"Teacher / Trainer",OR(ISNUMBER(SEARCH("doctor",B106)),ISNUMBER(SEARCH("nurse",B106)),ISNUMBER(SEARCH("medical",B106)),ISNUMBER(SEARCH("pharma",B106)),ISNUMBER(SEARCH("clinical",B106))),"Healthcare",TRUE,"Other") | B9: =IF(PROPER(TRIM(Raw_Data!D105))="Bangalore","Bengaluru",IF(PROPER(TRIM(Raw_Data!D105))="Gurgaon","Gurugram",IF(OR(PROPER(TRIM(Raw_Data!D105))="New Delhi",PROPER(TRIM(Raw_Data!D105))="Delhi"),"Delhi",PROPER(TRIM(Raw_Data!D105))))) | C9: =IF(TRIM(Raw_Data!F105&"")="","Not Specified",Raw_Data!F105) | D9: =Raw_Data!H105 | E9: =Raw_Data!E105
A10: =_xlfn.IFS(ISNUMBER(SEARCH("data analy",B107)),"Data Analyst",ISNUMBER(SEARCH("business analy",B107)),"Business Analyst",OR(ISNUMBER(SEARCH("developer",B107)),ISNUMBER(SEARCH("software engineer",B107)),ISNUMBER(SEARCH("programmer",B107))),"Software Developer",ISNUMBER(SEARCH("business development",B107)),"Business Development",ISNUMBER(SEARCH("sales",B107)),"Sales Executive",ISNUMBER(SEARCH("marketing",B107)),"Marketing Executive",OR(ISNUMBER(SEARCH("hr ",B107)),ISNUMBER(SEARCH("recruit",B107)),ISNUMBER(SEARCH("human resource",B107))),"HR / Recruiter",OR(ISNUMBER(SEARCH("account",B107)),ISNUMBER(SEARCH("finance",B107)),ISNUMBER(SEARCH("tax",B107)),ISNUMBER(SEARCH("audit",B107))),"Accountant / Finance",OR(ISNUMBER(SEARCH("customer service",B107)),ISNUMBER(SEARCH("customer support",B107)),ISNUMBER(SEARCH("customer care",B107)),ISNUMBER(SEARCH("voice process",B107)),ISNUMBER(SEARCH("bpo",B107))),"Customer Support",ISNUMBER(SEARCH("engineer",B107)),"Engineer (Technical)",ISNUMBER(SEARCH("manager",B107)),"Manager",OR(ISNUMBER(SEARCH("teacher",B107)),ISNUMBER(SEARCH("trainer",B107)),ISNUMBER(SEARCH("faculty",B107))),"Teacher / Trainer",OR(ISNUMBER(SEARCH("doctor",B107)),ISNUMBER(SEARCH("nurse",B107)),ISNUMBER(SEARCH("medical",B107)),ISNUMBER(SEARCH("pharma",B107)),ISNUMBER(SEARCH("clinical",B107))),"Healthcare",TRUE,"Other") | B10: =IF(PROPER(TRIM(Raw_Data!D106))="Bangalore","Bengaluru",IF(PROPER(TRIM(Raw_Data!D106))="Gurgaon","Gurugram",IF(OR(PROPER(TRIM(Raw_Data!D106))="New Delhi",PROPER(TRIM(Raw_Data!D106))="Delhi"),"Delhi",PROPER(TRIM(Raw_Data!D106))))) | C10: =IF(TRIM(Raw_Data!F106&"")="","Not Specified",Raw_Data!F106) | D10: =Raw_Data!H106 | E10: =Raw_Data!E106
A11: =_xlfn.IFS(ISNUMBER(SEARCH("data analy",B108)),"Data Analyst",ISNUMBER(SEARCH("business analy",B108)),"Business Analyst",OR(ISNUMBER(SEARCH("developer",B108)),ISNUMBER(SEARCH("software engineer",B108)),ISNUMBER(SEARCH("programmer",B108))),"Software Developer",ISNUMBER(SEARCH("business development",B108)),"Business Development",ISNUMBER(SEARCH("sales",B108)),"Sales Executive",ISNUMBER(SEARCH("marketing",B108)),"Marketing Executive",OR(ISNUMBER(SEARCH("hr ",B108)),ISNUMBER(SEARCH("recruit",B108)),ISNUMBER(SEARCH("human resource",B108))),"HR / Recruiter",OR(ISNUMBER(SEARCH("account",B108)),ISNUMBER(SEARCH("finance",B108)),ISNUMBER(SEARCH("tax",B108)),ISNUMBER(SEARCH("audit",B108))),"Accountant / Finance",OR(ISNUMBER(SEARCH("customer service",B108)),ISNUMBER(SEARCH("customer support",B108)),ISNUMBER(SEARCH("customer care",B108)),ISNUMBER(SEARCH("voice process",B108)),ISNUMBER(SEARCH("bpo",B108))),"Customer Support",ISNUMBER(SEARCH("engineer",B108)),"Engineer (Technical)",ISNUMBER(SEARCH("manager",B108)),"Manager",OR(ISNUMBER(SEARCH("teacher",B108)),ISNUMBER(SEARCH("trainer",B108)),ISNUMBER(SEARCH("faculty",B108))),"Teacher / Trainer",OR(ISNUMBER(SEARCH("doctor",B108)),ISNUMBER(SEARCH("nurse",B108)),ISNUMBER(SEARCH("medical",B108)),ISNUMBER(SEARCH("pharma",B108)),ISNUMBER(SEARCH("clinical",B108))),"Healthcare",TRUE,"Other") | B11: =IF(PROPER(TRIM(Raw_Data!D107))="Bangalore","Bengaluru",IF(PROPER(TRIM(Raw_Data!D107))="Gurgaon","Gurugram",IF(OR(PROPER(TRIM(Raw_Data!D107))="New Delhi",PROPER(TRIM(Raw_Data!D107))="Delhi"),"Delhi",PROPER(TRIM(Raw_Data!D107))))) | C11: =IF(TRIM(Raw_Data!F107&"")="","Not Specified",Raw_Data!F107) | D11: =Raw_Data!H107 | E11: =Raw_Data!E107
A12: =_xlfn.IFS(ISNUMBER(SEARCH("data analy",B109)),"Data Analyst",ISNUMBER(SEARCH("business analy",B109)),"Business Analyst",OR(ISNUMBER(SEARCH("developer",B109)),ISNUMBER(SEARCH("software engineer",B109)),ISNUMBER(SEARCH("programmer",B109))),"Software Developer",ISNUMBER(SEARCH("business development",B109)),"Business Development",ISNUMBER(SEARCH("sales",B109)),"Sales Executive",ISNUMBER(SEARCH("marketing",B109)),"Marketing Executive",OR(ISNUMBER(SEARCH("hr ",B109)),ISNUMBER(SEARCH("recruit",B109)),ISNUMBER(SEARCH("human resource",B109))),"HR / Recruiter",OR(ISNUMBER(SEARCH("account",B109)),ISNUMBER(SEARCH("finance",B109)),ISNUMBER(SEARCH("tax",B109)),ISNUMBER(SEARCH("audit",B109))),"Accountant / Finance",OR(ISNUMBER(SEARCH("customer service",B109)),ISNUMBER(SEARCH("customer support",B109)),ISNUMBER(SEARCH("customer care",B109)),ISNUMBER(SEARCH("voice process",B109)),ISNUMBER(SEARCH("bpo",B109))),"Customer Support",ISNUMBER(SEARCH("engineer",B109)),"Engineer (Technical)",ISNUMBER(SEARCH("manager",B109)),"Manager",OR(ISNUMBER(SEARCH("teacher",B109)),ISNUMBER(SEARCH("trainer",B109)),ISNUMBER(SEARCH("faculty",B109))),"Teacher / Trainer",OR(ISNUMBER(SEARCH("doctor",B109)),ISNUMBER(SEARCH("nurse",B109)),ISNUMBER(SEARCH("medical",B109)),ISNUMBER(SEARCH("pharma",B109)),ISNUMBER(SEARCH("clinical",B109))),"Healthcare",TRUE,"Other") | B12: =IF(PROPER(TRIM(Raw_Data!D108))="Bangalore","Bengaluru",IF(PROPER(TRIM(Raw_Data!D108))="Gurgaon","Gurugram",IF(OR(PROPER(TRIM(Raw_Data!D108))="New Delhi",PROPER(TRIM(Raw_Data!D108))="Delhi"),"Delhi",PROPER(TRIM(Raw_Data!D108))))) | C12: =IF(TRIM(Raw_Data!F108&"")="","Not Specified",Raw_Data!F108) | D12: =Raw_Data!H108 | E12: =Raw_Data!E108
A13: =_xlfn.IFS(ISNUMBER(SEARCH("data analy",B11)),"Data Analyst",ISNUMBER(SEARCH("business analy",B11)),"Business Analyst",OR(ISNUMBER(SEARCH("developer",B11)),ISNUMBER(SEARCH("software engineer",B11)),ISNUMBER(SEARCH("programmer",B11))),"Software Developer",ISNUMBER(SEARCH("business development",B11)),"Business Development",ISNUMBER(SEARCH("sales",B11)),"Sales Executive",ISNUMBER(SEARCH("marketing",B11)),"Marketing Executive",OR(ISNUMBER(SEARCH("hr ",B11)),ISNUMBER(SEARCH("recruit",B11)),ISNUMBER(SEARCH("human resource",B11))),"HR / Recruiter",OR(ISNUMBER(SEARCH("account",B11)),ISNUMBER(SEARCH("finance",B11)),ISNUMBER(SEARCH("tax",B11)),ISNUMBER(SEARCH("audit",B11))),"Accountant / Finance",OR(ISNUMBER(SEARCH("customer service",B11)),ISNUMBER(SEARCH("customer support",B11)),ISNUMBER(SEARCH("customer care",B11)),ISNUMBER(SEARCH("voice process",B11)),ISNUMBER(SEARCH("bpo",B11))),"Customer Support",ISNUMBER(SEARCH("engineer",B11)),"Engineer (Technical)",ISNUMBER(SEARCH("manager",B11)),"Manager",OR(ISNUMBER(SEARCH("teacher",B11)),ISNUMBER(SEARCH("trainer",B11)),ISNUMBER(SEARCH("faculty",B11))),"Teacher / Trainer",OR(ISNUMBER(SEARCH("doctor",B11)),ISNUMBER(SEARCH("nurse",B11)),ISNUMBER(SEARCH("medical",B11)),ISNUMBER(SEARCH("pharma",B11)),ISNUMBER(SEARCH("clinical",B11))),"Healthcare",TRUE,"Other") | B13: =IF(PROPER(TRIM(Raw_Data!D109))="Bangalore","Bengaluru",IF(PROPER(TRIM(Raw_Data!D109))="Gurgaon","Gurugram",IF(OR(PROPER(TRIM(Raw_Data!D109))="New Delhi",PROPER(TRIM(Raw_Data!D109))="Delhi"),"Delhi",PROPER(TRIM(Raw_Data!D109))))) | C13: =IF(TRIM(Raw_Data!F109&"")="","Not Specified",Raw_Data!F109) | D13: =Raw_Data!H109 | E13: =Raw_Data!E109
A14: =_xlfn.IFS(ISNUMBER(SEARCH("data analy",B110)),"Data Analyst",ISNUMBER(SEARCH("business analy",B110)),"Business Analyst",OR(ISNUMBER(SEARCH("developer",B110)),ISNUMBER(SEARCH("software engineer",B110)),ISNUMBER(SEARCH("programmer",B110))),"Software Developer",ISNUMBER(SEARCH("business development",B110)),"Business Development",ISNUMBER(SEARCH("sales",B110)),"Sales Executive",ISNUMBER(SEARCH("marketing",B110)),"Marketing Executive",OR(ISNUMBER(SEARCH("hr ",B110)),ISNUMBER(SEARCH("recruit",B110)),ISNUMBER(SEARCH("human resource",B110))),"HR / Recruiter",OR(ISNUMBER(SEARCH("account",B110)),ISNUMBER(SEARCH("finance",B110)),ISNUMBER(SEARCH("tax",B110)),ISNUMBER(SEARCH("audit",B110))),"Accountant / Finance",OR(ISNUMBER(SEARCH("customer service",B110)),ISNUMBER(SEARCH("customer support",B110)),ISNUMBER(SEARCH("customer care",B110)),ISNUMBER(SEARCH("voice process",B110)),ISNUMBER(SEARCH("bpo",B110))),"Customer Support",ISNUMBER(SEARCH("engineer",B110)),"Engineer (Technical)",ISNUMBER(SEARCH("manager",B110)),"Manager",OR(ISNUMBER(SEARCH("teacher",B110)),ISNUMBER(SEARCH("trainer",B110)),ISNUMBER(SEARCH("faculty",B110))),"Teacher / Trainer",OR(ISNUMBER(SEARCH("doctor",B110)),ISNUMBER(SEARCH("nurse",B110)),ISNUMBER(SEARCH("medical",B110)),ISNUMBER(SEARCH("pharma",B110)),ISNUMBER(SEARCH("clinical",B110))),"Healthcare",TRUE,"Other") | B14: =IF(PROPER(TRIM(Raw_Data!D11))="Bangalore","Bengaluru",IF(PROPER(TRIM(Raw_Data!D11))="Gurgaon","Gurugram",IF(OR(PROPER(TRIM(Raw_Data!D11))="New Delhi",PROPER(TRIM(Raw_Data!D11))="Delhi"),"Delhi",PROPER(TRIM(Raw_Data!D11))))) | C14: =IF(TRIM(Raw_Data!F11&"")="","Not Specified",Raw_Data!F11) | D14: =Raw_Data!H11 | E14: =Raw_Data!E11
A15: =_xlfn.IFS(ISNUMBER(SEARCH("data analy",B111)),"Data Analyst",ISNUMBER(SEARCH("business analy",B111)),"Business Analyst",OR(ISNUMBER(SEARCH("developer",B111)),ISNUMBER(SEARCH("software engineer",B111)),ISNUMBER(SEARCH("programmer",B111))),"Software Developer",ISNUMBER(SEARCH("business development",B111)),"Business Development",ISNUMBER(SEARCH("sales",B111)),"Sales Executive",ISNUMBER(SEARCH("marketing",B111)),"Marketing Executive",OR(ISNUMBER(SEARCH("hr ",B111)),ISNUMBER(SEARCH("recruit",B111)),ISNUMBER(SEARCH("human resource",B111))),"HR / Recruiter",OR(ISNUMBER(SEARCH("account",B111)),ISNUMBER(SEARCH("finance",B111)),ISNUMBER(SEARCH("tax",B111)),ISNUMBER(SEARCH("audit",B111))),"Accountant / Finance",OR(ISNUMBER(SEARCH("customer service",B111)),ISNUMBER(SEARCH("customer support",B111)),ISNUMBER(SEARCH("customer care",B111)),ISNUMBER(SEARCH("voice process",B111)),ISNUMBER(SEARCH("bpo",B111))),"Customer Support",ISNUMBER(SEARCH("engineer",B111)),"Engineer (Technical)",ISNUMBER(SEARCH("manager",B111)),"Manager",OR(ISNUMBER(SEARCH("teacher",B111)),ISNUMBER(SEARCH("trainer",B111)),ISNUMBER(SEARCH("faculty",B111))),"Teacher / Trainer",OR(ISNUMBER(SEARCH("doctor",B111)),ISNUMBER(SEARCH("nurse",B111)),ISNUMBER(SEARCH("medical",B111)),ISNUMBER(SEARCH("pharma",B111)),ISNUMBER(SEARCH("clinical",B111))),"Healthcare",TRUE,"Other") | B15: =IF(PROPER(TRIM(Raw_Data!D110))="Bangalore","Bengaluru",IF(PROPER(TRIM(Raw_Data!D110))="Gurgaon","Gurugram",IF(OR(PROPER(TRIM(Raw_Data!D110))="New Delhi",PROPER(TRIM(Raw_Data!D110))="Delhi"),"Delhi",PROPER(TRIM(Raw_Data!D110))))) | C15: =IF(TRIM(Raw_Data!F110&"")="","Not Specified",Raw_Data!F110) | D15: =Raw_Data!H110 | E15: =Raw_Data!E110
A16: =_xlfn.IFS(ISNUMBER(SEARCH("data analy",B112)),"Data Analyst",ISNUMBER(SEARCH("business analy",B112)),"Business Analyst",OR(ISNUMBER(SEARCH("developer",B112)),ISNUMBER(SEARCH("software engineer",B112)),ISNUMBER(SEARCH("programmer",B112))),"Software Developer",ISNUMBER(SEARCH("business development",B112)),"Business Development",ISNUMBER(SEARCH("sales",B112)),"Sales Executive",ISNUMBER(SEARCH("marketing",B112)),"Marketing Executive",OR(ISNUMBER(SEARCH("hr ",B112)),ISNUMBER(SEARCH("recruit",B112)),ISNUMBER(SEARCH("human resource",B112))),"HR / Recruiter",OR(ISNUMBER(SEARCH("account",B112)),ISNUMBER(SEARCH("finance",B112)),ISNUMBER(SEARCH("tax",B112)),ISNUMBER(SEARCH("audit",B112))),"Accountant / Finance",OR(ISNUMBER(SEARCH("customer service",B112)),ISNUMBER(SEARCH("customer support",B112)),ISNUMBER(SEARCH("customer care",B112)),ISNUMBER(SEARCH("voice process",B112)),ISNUMBER(SEARCH("bpo",B112))),"Customer Support",ISNUMBER(SEARCH("engineer",B112)),"Engineer (Technical)",ISNUMBER(SEARCH("manager",B112)),"Manager",OR(ISNUMBER(SEARCH("teacher",B112)),ISNUMBER(SEARCH("trainer",B112)),ISNUMBER(SEARCH("faculty",B112))),"Teacher / Trainer",OR(ISNUMBER(SEARCH("doctor",B112)),ISNUMBER(SEARCH("nurse",B112)),ISNUMBER(SEARCH("medical",B112)),ISNUMBER(SEARCH("pharma",B112)),ISNUMBER(SEARCH("clinical",B112))),"Healthcare",TRUE,"Other") | B16: =IF(PROPER(TRIM(Raw_Data!D111))="Bangalore","Bengaluru",IF(PROPER(TRIM(Raw_Data!D111))="Gurgaon","Gurugram",IF(OR(PROPER(TRIM(Raw_Data!D111))="New Delhi",PROPER(TRIM(Raw_Data!D111))="Delhi"),"Delhi",PROPER(TRIM(Raw_Data!D111))))) | C16: =IF(TRIM(Raw_Data!F111&"")="","Not Specified",Raw_Data!F111) | D16: =Raw_Data!H111 | E16: =Raw_Data!E111
A17: =_xlfn.IFS(ISNUMBER(SEARCH("data analy",B113)),"Data Analyst",ISNUMBER(SEARCH("business analy",B113)),"Business Analyst",OR(ISNUMBER(SEARCH("developer",B113)),ISNUMBER(SEARCH("software engineer",B113)),ISNUMBER(SEARCH("programmer",B113))),"Software Developer",ISNUMBER(SEARCH("business development",B113)),"Business Development",ISNUMBER(SEARCH("sales",B113)),"Sales Executive",ISNUMBER(SEARCH("marketing",B113)),"Marketing Executive",OR(ISNUMBER(SEARCH("hr ",B113)),ISNUMBER(SEARCH("recruit",B113)),ISNUMBER(SEARCH("human resource",B113))),"HR / Recruiter",OR(ISNUMBER(SEARCH("account",B113)),ISNUMBER(SEARCH("finance",B113)),ISNUMBER(SEARCH("tax",B113)),ISNUMBER(SEARCH("audit",B113))),"Accountant / Finance",OR(ISNUMBER(SEARCH("customer service",B113)),ISNUMBER(SEARCH("customer support",B113)),ISNUMBER(SEARCH("customer care",B113)),ISNUMBER(SEARCH("voice process",B113)),ISNUMBER(SEARCH("bpo",B113))),"Customer Support",ISNUMBER(SEARCH("engineer",B113)),"Engineer (Technical)",ISNUMBER(SEARCH("manager",B113)),"Manager",OR(ISNUMBER(SEARCH("teacher",B113)),ISNUMBER(SEARCH("trainer",B113)),ISNUMBER(SEARCH("faculty",B113))),"Teacher / Trainer",OR(ISNUMBER(SEARCH("doctor",B113)),ISNUMBER(SEARCH("nurse",B113)),ISNUMBER(SEARCH("medical",B113)),ISNUMBER(SEARCH("pharma",B113)),ISNUMBER(SEARCH("clinical",B113))),"Healthcare",TRUE,"Other") | B17: =IF(PROPER(TRIM(Raw_Data!D112))="Bangalore","Bengaluru",IF(PROPER(TRIM(Raw_Data!D112))="Gurgaon","Gurugram",IF(OR(PROPER(TRIM(Raw_Data!D112))="New Delhi",PROPER(TRIM(Raw_Data!D112))="Delhi"),"Delhi",PROPER(TRIM(Raw_Data!D112))))) | C17: =IF(TRIM(Raw_Data!F112&"")="","Not Specified",Raw_Data!F112) | D17: =Raw_Data!H112 | E17: =Raw_Data!E112
A18: =_xlfn.IFS(ISNUMBER(SEARCH("data analy",B114)),"Data Analyst",ISNUMBER(SEARCH("business analy",B114)),"Business Analyst",OR(ISNUMBER(SEARCH("developer",B114)),ISNUMBER(SEARCH("software engineer",B114)),ISNUMBER(SEARCH("programmer",B114))),"Software Developer",ISNUMBER(SEARCH("business development",B114)),"Business Development",ISNUMBER(SEARCH("sales",B114)),"Sales Executive",ISNUMBER(SEARCH("marketing",B114)),"Marketing Executive",OR(ISNUMBER(SEARCH("hr ",B114)),ISNUMBER(SEARCH("recruit",B114)),ISNUMBER(SEARCH("human resource",B114))),"HR / Recruiter",OR(ISNUMBER(SEARCH("account",B114)),ISNUMBER(SEARCH("finance",B114)),ISNUMBER(SEARCH("tax",B114)),ISNUMBER(SEARCH("audit",B114))),"Accountant / Finance",OR(ISNUMBER(SEARCH("customer service",B114)),ISNUMBER(SEARCH("customer support",B114)),ISNUMBER(SEARCH("customer care",B114)),ISNUMBER(SEARCH("voice process",B114)),ISNUMBER(SEARCH("bpo",B114))),"Customer Support",ISNUMBER(SEARCH("engineer",B114)),"Engineer (Technical)",ISNUMBER(SEARCH("manager",B114)),"Manager",OR(ISNUMBER(SEARCH("teacher",B114)),ISNUMBER(SEARCH("trainer",B114)),ISNUMBER(SEARCH("faculty",B114))),"Teacher / Trainer",OR(ISNUMBER(SEARCH("doctor",B114)),ISNUMBER(SEARCH("nurse",B114)),ISNUMBER(SEARCH("medical",B114)),ISNUMBER(SEARCH("pharma",B114)),ISNUMBER(SEARCH("clinical",B114))),"Healthcare",TRUE,"Other") | B18: =IF(PROPER(TRIM(Raw_Data!D113))="Bangalore","Bengaluru",IF(PROPER(TRIM(Raw_Data!D113))="Gurgaon","Gurugram",IF(OR(PROPER(TRIM(Raw_Data!D113))="New Delhi",PROPER(TRIM(Raw_Data!D113))="Delhi"),"Delhi",PROPER(TRIM(Raw_Data!D113))))) | C18: =IF(TRIM(Raw_Data!F113&"")="","Not Specified",Raw_Data!F113) | D18: =Raw_Data!H113 | E18: =Raw_Data!E113
A19: =_xlfn.IFS(ISNUMBER(SEARCH("data analy",B115)),"Data Analyst",ISNUMBER(SEARCH("business analy",B115)),"Business Analyst",OR(ISNUMBER(SEARCH("developer",B115)),ISNUMBER(SEARCH("software engineer",B115)),ISNUMBER(SEARCH("programmer",B115))),"Software Developer",ISNUMBER(SEARCH("business development",B115)),"Business Development",ISNUMBER(SEARCH("sales",B115)),"Sales Executive",ISNUMBER(SEARCH("marketing",B115)),"Marketing Executive",OR(ISNUMBER(SEARCH("hr ",B115)),ISNUMBER(SEARCH("recruit",B115)),ISNUMBER(SEARCH("human resource",B115))),"HR / Recruiter",OR(ISNUMBER(SEARCH("account",B115)),ISNUMBER(SEARCH("finance",B115)),ISNUMBER(SEARCH("tax",B115)),ISNUMBER(SEARCH("audit",B115))),"Accountant / Finance",OR(ISNUMBER(SEARCH("customer service",B115)),ISNUMBER(SEARCH("customer support",B115)),ISNUMBER(SEARCH("customer care",B115)),ISNUMBER(SEARCH("voice process",B115)),ISNUMBER(SEARCH("bpo",B115))),"Customer Support",ISNUMBER(SEARCH("engineer",B115)),"Engineer (Technical)",ISNUMBER(SEARCH("manager",B115)),"Manager",OR(ISNUMBER(SEARCH("teacher",B115)),ISNUMBER(SEARCH("trainer",B115)),ISNUMBER(SEARCH("faculty",B115))),"Teacher / Trainer",OR(ISNUMBER(SEARCH("doctor",B115)),ISNUMBER(SEARCH("nurse",B115)),ISNUMBER(SEARCH("medical",B115)),ISNUMBER(SEARCH("pharma",B115)),ISNUMBER(SEARCH("clinical",B115))),"Healthcare",TRUE,"Other") | B19: =IF(PROPER(TRIM(Raw_Data!D114))="Bangalore","Bengaluru",IF(PROPER(TRIM(Raw_Data!D114))="Gurgaon","Gurugram",IF(OR(PROPER(TRIM(Raw_Data!D114))="New Delhi",PROPER(TRIM(Raw_Data!D114))="Delhi"),"Delhi",PROPER(TRIM(Raw_Data!D114))))) | C19: =IF(TRIM(Raw_Data!F114&"")="","Not Specified",Raw_Data!F114) | D19: =Raw_Data!H114 | E19: =Raw_Data!E114
A20: =_xlfn.IFS(ISNUMBER(SEARCH("data analy",B116)),"Data Analyst",ISNUMBER(SEARCH("business analy",B116)),"Business Analyst",OR(ISNUMBER(SEARCH("developer",B116)),ISNUMBER(SEARCH("software engineer",B116)),ISNUMBER(SEARCH("programmer",B116))),"Software Developer",ISNUMBER(SEARCH("business development",B116)),"Business Development",ISNUMBER(SEARCH("sales",B116)),"Sales Executive",ISNUMBER(SEARCH("marketing",B116)),"Marketing Executive",OR(ISNUMBER(SEARCH("hr ",B116)),ISNUMBER(SEARCH("recruit",B116)),ISNUMBER(SEARCH("human resource",B116))),"HR / Recruiter",OR(ISNUMBER(SEARCH("account",B116)),ISNUMBER(SEARCH("finance",B116)),ISNUMBER(SEARCH("tax",B116)),ISNUMBER(SEARCH("audit",B116))),"Accountant / Finance",OR(ISNUMBER(SEARCH("customer service",B116)),ISNUMBER(SEARCH("customer support",B116)),ISNUMBER(SEARCH("customer care",B116)),ISNUMBER(SEARCH("voice process",B116)),ISNUMBER(SEARCH("bpo",B116))),"Customer Support",ISNUMBER(SEARCH("engineer",B116)),"Engineer (Technical)",ISNUMBER(SEARCH("manager",B116)),"Manager",OR(ISNUMBER(SEARCH("teacher",B116)),ISNUMBER(SEARCH("trainer",B116)),ISNUMBER(SEARCH("faculty",B116))),"Teacher / Trainer",OR(ISNUMBER(SEARCH("doctor",B116)),ISNUMBER(SEARCH("nurse",B116)),ISNUMBER(SEARCH("medical",B116)),ISNUMBER(SEARCH("pharma",B116)),ISNUMBER(SEARCH("clinical",B116))),"Healthcare",TRUE,"Other") | B20: =IF(PROPER(TRIM(Raw_Data!D115))="Bangalore","Bengaluru",IF(PROPER(TRIM(Raw_Data!D115))="Gurgaon","Gurugram",IF(OR(PROPER(TRIM(Raw_Data!D115))="New Delhi",PROPER(TRIM(Raw_Data!D115))="Delhi"),"Delhi",PROPER(TRIM(Raw_Data!D115))))) | C20: =IF(TRIM(Raw_Data!F115&"")="","Not Specified",Raw_Data!F115) | D20: =Raw_Data!H115 | E20: =Raw_Data!E115
A21: =_xlfn.IFS(ISNUMBER(SEARCH("data analy",B117)),"Data Analyst",ISNUMBER(SEARCH("business analy",B117)),"Business Analyst",OR(ISNUMBER(SEARCH("developer",B117)),ISNUMBER(SEARCH("software engineer",B117)),ISNUMBER(SEARCH("programmer",B117))),"Software Developer",ISNUMBER(SEARCH("business development",B117)),"Business Development",ISNUMBER(SEARCH("sales",B117)),"Sales Executive",ISNUMBER(SEARCH("marketing",B117)),"Marketing Executive",OR(ISNUMBER(SEARCH("hr ",B117)),ISNUMBER(SEARCH("recruit",B117)),ISNUMBER(SEARCH("human resource",B117))),"HR / Recruiter",OR(ISNUMBER(SEARCH("account",B117)),ISNUMBER(SEARCH("finance",B117)),ISNUMBER(SEARCH("tax",B117)),ISNUMBER(SEARCH("audit",B117))),"Accountant / Finance",OR(ISNUMBER(SEARCH("customer service",B117)),ISNUMBER(SEARCH("customer support",B117)),ISNUMBER(SEARCH("customer care",B117)),ISNUMBER(SEARCH("voice process",B117)),ISNUMBER(SEARCH("bpo",B117))),"Customer Support",ISNUMBER(SEARCH("engineer",B117)),"Engineer (Technical)",ISNUMBER(SEARCH("manager",B117)),"Manager",OR(ISNUMBER(SEARCH("teacher",B117)),ISNUMBER(SEARCH("trainer",B117)),ISNUMBER(SEARCH("faculty",B117))),"Teacher / Trainer",OR(ISNUMBER(SEARCH("doctor",B117)),ISNUMBER(SEARCH("nurse",B117)),ISNUMBER(SEARCH("medical",B117)),ISNUMBER(SEARCH("pharma",B117)),ISNUMBER(SEARCH("clinical",B117))),"Healthcare",TRUE,"Other") | B21: =IF(PROPER(TRIM(Raw_Data!D116))="Bangalore","Bengaluru",IF(PROPER(TRIM(Raw_Data!D116))="Gurgaon","Gurugram",IF(OR(PROPER(TRIM(Raw_Data!D116))="New Delhi",PROPER(TRIM(Raw_Data!D116))="Delhi"),"Delhi",PROPER(TRIM(Raw_Data!D116))))) | C21: =IF(TRIM(Raw_Data!F116&"")="","Not Specified",Raw_Data!F116) | D21: =Raw_Data!H116 | E21: =Raw_Data!E116
A22: =_xlfn.IFS(ISNUMBER(SEARCH("data analy",B118)),"Data Analyst",ISNUMBER(SEARCH("business analy",B118)),"Business Analyst",OR(ISNUMBER(SEARCH("developer",B118)),ISNUMBER(SEARCH("software engineer",B118)),ISNUMBER(SEARCH("programmer",B118))),"Software Developer",ISNUMBER(SEARCH("business development",B118)),"Business Development",ISNUMBER(SEARCH("sales",B118)),"Sales Executive",ISNUMBER(SEARCH("marketing",B118)),"Marketing Executive",OR(ISNUMBER(SEARCH("hr ",B118)),ISNUMBER(SEARCH("recruit",B118)),ISNUMBER(SEARCH("human resource",B118))),"HR / Recruiter",OR(ISNUMBER(SEARCH("account",B118)),ISNUMBER(SEARCH("finance",B118)),ISNUMBER(SEARCH("tax",B118)),ISNUMBER(SEARCH("audit",B118))),"Accountant / Finance",OR(ISNUMBER(SEARCH("customer service",B118)),ISNUMBER(SEARCH("customer support",B118)),ISNUMBER(SEARCH("customer care",B118)),ISNUMBER(SEARCH("voice process",B118)),ISNUMBER(SEARCH("bpo",B118))),"Customer Support",ISNUMBER(SEARCH("engineer",B118)),"Engineer (Technical)",ISNUMBER(SEARCH("manager",B118)),"Manager",OR(ISNUMBER(SEARCH("teacher",B118)),ISNUMBER(SEARCH("trainer",B118)),ISNUMBER(SEARCH("faculty",B118))),"Teacher / Trainer",OR(ISNUMBER(SEARCH("doctor",B118)),ISNUMBER(SEARCH("nurse",B118)),ISNUMBER(SEARCH("medical",B118)),ISNUMBER(SEARCH("pharma",B118)),ISNUMBER(SEARCH("clinical",B118))),"Healthcare",TRUE,"Other") | B22: =IF(PROPER(TRIM(Raw_Data!D117))="Bangalore","Bengaluru",IF(PROPER(TRIM(Raw_Data!D117))="Gurgaon","Gurugram",IF(OR(PROPER(TRIM(Raw_Data!D117))="New Delhi",PROPER(TRIM(Raw_Data!D117))="Delhi"),"Delhi",PROPER(TRIM(Raw_Data!D117))))) | C22: =IF(TRIM(Raw_Data!F117&"")="","Not Specified",Raw_Data!F117) | D22: =Raw_Data!H117 | E22: =Raw_Data!E117
A23: =_xlfn.IFS(ISNUMBER(SEARCH("data analy",B119)),"Data Analyst",ISNUMBER(SEARCH("business analy",B119)),"Business Analyst",OR(ISNUMBER(SEARCH("developer",B119)),ISNUMBER(SEARCH("software engineer",B119)),ISNUMBER(SEARCH("programmer",B119))),"Software Developer",ISNUMBER(SEARCH("business development",B119)),"Business Development",ISNUMBER(SEARCH("sales",B119)),"Sales Executive",ISNUMBER(SEARCH("marketing",B119)),"Marketing Executive",OR(ISNUMBER(SEARCH("hr ",B119)),ISNUMBER(SEARCH("recruit",B119)),ISNUMBER(SEARCH("human resource",B119))),"HR / Recruiter",OR(ISNUMBER(SEARCH("account",B119)),ISNUMBER(SEARCH("finance",B119)),ISNUMBER(SEARCH("tax",B119)),ISNUMBER(SEARCH("audit",B119))),"Accountant / Finance",OR(ISNUMBER(SEARCH("customer service",B119)),ISNUMBER(SEARCH("customer support",B119)),ISNUMBER(SEARCH("customer care",B119)),ISNUMBER(SEARCH("voice process",B119)),ISNUMBER(SEARCH("bpo",B119))),"Customer Support",ISNUMBER(SEARCH("engineer",B119)),"Engineer (Technical)",ISNUMBER(SEARCH("manager",B119)),"Manager",OR(ISNUMBER(SEARCH("teacher",B119)),ISNUMBER(SEARCH("trainer",B119)),ISNUMBER(SEARCH("faculty",B119))),"Teacher / Trainer",OR(ISNUMBER(SEARCH("doctor",B119)),ISNUMBER(SEARCH("nurse",B119)),ISNUMBER(SEARCH("medical",B119)),ISNUMBER(SEARCH("pharma",B119)),ISNUMBER(SEARCH("clinical",B119))),"Healthcare",TRUE,"Other") | B23: =IF(PROPER(TRIM(Raw_Data!D118))="Bangalore","Bengaluru",IF(PROPER(TRIM(Raw_Data!D118))="Gurgaon","Gurugram",IF(OR(PROPER(TRIM(Raw_Data!D118))="New Delhi",PROPER(TRIM(Raw_Data!D118))="Delhi"),"Delhi",PROPER(TRIM(Raw_Data!D118))))) | C23: =IF(TRIM(Raw_Data!F118&"")="","Not Specified",Raw_Data!F118) | D23: =Raw_Data!H118 | E23: =Raw_Data!E118
A24: =_xlfn.IFS(ISNUMBER(SEARCH("data analy",B12)),"Data Analyst",ISNUMBER(SEARCH("business analy",B12)),"Business Analyst",OR(ISNUMBER(SEARCH("developer",B12)),ISNUMBER(SEARCH("software engineer",B12)),ISNUMBER(SEARCH("programmer",B12))),"Software Developer",ISNUMBER(SEARCH("business development",B12)),"Business Development",ISNUMBER(SEARCH("sales",B12)),"Sales Executive",ISNUMBER(SEARCH("marketing",B12)),"Marketing Executive",OR(ISNUMBER(SEARCH("hr ",B12)),ISNUMBER(SEARCH("recruit",B12)),ISNUMBER(SEARCH("human resource",B12))),"HR / Recruiter",OR(ISNUMBER(SEARCH("account",B12)),ISNUMBER(SEARCH("finance",B12)),ISNUMBER(SEARCH("tax",B12)),ISNUMBER(SEARCH("audit",B12))),"Accountant / Finance",OR(ISNUMBER(SEARCH("customer service",B12)),ISNUMBER(SEARCH("customer support",B12)),ISNUMBER(SEARCH("customer care",B12)),ISNUMBER(SEARCH("voice process",B12)),ISNUMBER(SEARCH("bpo",B12))),"Customer Support",ISNUMBER(SEARCH("engineer",B12)),"Engineer (Technical)",ISNUMBER(SEARCH("manager",B12)),"Manager",OR(ISNUMBER(SEARCH("teacher",B12)),ISNUMBER(SEARCH("trainer",B12)),ISNUMBER(SEARCH("faculty",B12))),"Teacher / Trainer",OR(ISNUMBER(SEARCH("doctor",B12)),ISNUMBER(SEARCH("nurse",B12)),ISNUMBER(SEARCH("medical",B12)),ISNUMBER(SEARCH("pharma",B12)),ISNUMBER(SEARCH("clinical",B12))),"Healthcare",TRUE,"Other") | B24: =IF(PROPER(TRIM(Raw_Data!D119))="Bangalore","Bengaluru",IF(PROPER(TRIM(Raw_Data!D119))="Gurgaon","Gurugram",IF(OR(PROPER(TRIM(Raw_Data!D119))="New Delhi",PROPER(TRIM(Raw_Data!D119))="Delhi"),"Delhi",PROPER(TRIM(Raw_Data!D119))))) | C24: =IF(TRIM(Raw_Data!F119&"")="","Not Specified",Raw_Data!F119) | D24: =Raw_Data!H119 | E24: =Raw_Data!E119
A25: =_xlfn.IFS(ISNUMBER(SEARCH("data analy",B120)),"Data Analyst",ISNUMBER(SEARCH("business analy",B120)),"Business Analyst",OR(ISNUMBER(SEARCH("developer",B120)),ISNUMBER(SEARCH("software engineer",B120)),ISNUMBER(SEARCH("programmer",B120))),"Software Developer",ISNUMBER(SEARCH("business development",B120)),"Business Development",ISNUMBER(SEARCH("sales",B120)),"Sales Executive",ISNUMBER(SEARCH("marketing",B120)),"Marketing Executive",OR(ISNUMBER(SEARCH("hr ",B120)),ISNUMBER(SEARCH("recruit",B120)),ISNUMBER(SEARCH("human resource",B120))),"HR / Recruiter",OR(ISNUMBER(SEARCH("account",B120)),ISNUMBER(SEARCH("finance",B120)),ISNUMBER(SEARCH("tax",B120)),ISNUMBER(SEARCH("audit",B120))),"Accountant / Finance",OR(ISNUMBER(SEARCH("customer service",B120)),ISNUMBER(SEARCH("customer support",B120)),ISNUMBER(SEARCH("customer care",B120)),ISNUMBER(SEARCH("voice process",B120)),ISNUMBER(SEARCH("bpo",B120))),"Customer Support",ISNUMBER(SEARCH("engineer",B120)),"Engineer (Technical)",ISNUMBER(SEARCH("manager",B120)),"Manager",OR(ISNUMBER(SEARCH("teacher",B120)),ISNUMBER(SEARCH("trainer",B120)),ISNUMBER(SEARCH("faculty",B120))),"Teacher / Trainer",OR(ISNUMBER(SEARCH("doctor",B120)),ISNUMBER(SEARCH("nurse",B120)),ISNUMBER(SEARCH("medical",B120)),ISNUMBER(SEARCH("pharma",B120)),ISNUMBER(SEARCH("clinical",B120))),"Healthcare",TRUE,"Other") | B25: =IF(PROPER(TRIM(Raw_Data!D12))="Bangalore","Bengaluru",IF(PROPER(TRIM(Raw_Data!D12))="Gurgaon","Gurugram",IF(OR(PROPER(TRIM(Raw_Data!D12))="New Delhi",PROPER(TRIM(Raw_Data!D12))="Delhi"),"Delhi",PROPER(TRIM(Raw_Data!D12))))) | C25: =IF(TRIM(Raw_Data!F12&"")="","Not Specified",Raw_Data!F12) | D25: =Raw_Data!H12 | E25: =Raw_Data!E12
A26: =_xlfn.IFS(ISNUMBER(SEARCH("data analy",B121)),"Data Analyst",ISNUMBER(SEARCH("business analy",B121)),"Business Analyst",OR(ISNUMBER(SEARCH("developer",B121)),ISNUMBER(SEARCH("software engineer",B121)),ISNUMBER(SEARCH("programmer",B121))),"Software Developer",ISNUMBER(SEARCH("business development",B121)),"Business Development",ISNUMBER(SEARCH("sales",B121)),"Sales Executive",ISNUMBER(SEARCH("marketing",B121)),"Marketing Executive",OR(ISNUMBER(SEARCH("hr ",B121)),ISNUMBER(SEARCH("recruit",B121)),ISNUMBER(SEARCH("human resource",B121))),"HR / Recruiter",OR(ISNUMBER(SEARCH("account",B121)),ISNUMBER(SEARCH("finance",B121)),ISNUMBER(SEARCH("tax",B121)),ISNUMBER(SEARCH("audit",B121))),"Accountant / Finance",OR(ISNUMBER(SEARCH("customer service",B121)),ISNUMBER(SEARCH("customer support",B121)),ISNUMBER(SEARCH("customer care",B121)),ISNUMBER(SEARCH("voice process",B121)),ISNUMBER(SEARCH("bpo",B121))),"Customer Support",ISNUMBER(SEARCH("engineer",B121)),"Engineer (Technical)",ISNUMBER(SEARCH("manager",B121)),"Manager",OR(ISNUMBER(SEARCH("teacher",B121)),ISNUMBER(SEARCH("trainer",B121)),ISNUMBER(SEARCH("faculty",B121))),"Teacher / Trainer",OR(ISNUMBER(SEARCH("doctor",B121)),ISNUMBER(SEARCH("nurse",B121)),ISNUMBER(SEARCH("medical",B121)),ISNUMBER(SEARCH("pharma",B121)),ISNUMBER(SEARCH("clinical",B121))),"Healthcare",TRUE,"Other") | B26: =IF(PROPER(TRIM(Raw_Data!D120))="Bangalore","Bengaluru",IF(PROPER(TRIM(Raw_Data!D120))="Gurgaon","Gurugram",IF(OR(PROPER(TRIM(Raw_Data!D120))="New Delhi",PROPER(TRIM(Raw_Data!D120))="Delhi"),"Delhi",PROPER(TRIM(Raw_Data!D120))))) | C26: =IF(TRIM(Raw_Data!F120&"")="","Not Specified",Raw_Data!F120) | D26: =Raw_Data!H120 | E26: =Raw_Data!E120
A27: =_xlfn.IFS(ISNUMBER(SEARCH("data analy",B122)),"Data Analyst",ISNUMBER(SEARCH("business analy",B122)),"Business Analyst",OR(ISNUMBER(SEARCH("developer",B122)),ISNUMBER(SEARCH("software engineer",B122)),ISNUMBER(SEARCH("programmer",B122))),"Software Developer",ISNUMBER(SEARCH("business development",B122)),"Business Development",ISNUMBER(SEARCH("sales",B122)),"Sales Executive",ISNUMBER(SEARCH("marketing",B122)),"Marketing Executive",OR(ISNUMBER(SEARCH("hr ",B122)),ISNUMBER(SEARCH("recruit",B122)),ISNUMBER(SEARCH("human resource",B122))),"HR / Recruiter",OR(ISNUMBER(SEARCH("account",B122)),ISNUMBER(SEARCH("finance",B122)),ISNUMBER(SEARCH("tax",B122)),ISNUMBER(SEARCH("audit",B122))),"Accountant / Finance",OR(ISNUMBER(SEARCH("customer service",B122)),ISNUMBER(SEARCH("customer support",B122)),ISNUMBER(SEARCH("customer care",B122)),ISNUMBER(SEARCH("voice process",B122)),ISNUMBER(SEARCH("bpo",B122))),"Customer Support",ISNUMBER(SEARCH("engineer",B122)),"Engineer (Technical)",ISNUMBER(SEARCH("manager",B122)),"Manager",OR(ISNUMBER(SEARCH("teacher",B122)),ISNUMBER(SEARCH("trainer",B122)),ISNUMBER(SEARCH("faculty",B122))),"Teacher / Trainer",OR(ISNUMBER(SEARCH("doctor",B122)),ISNUMBER(SEARCH("nurse",B122)),ISNUMBER(SEARCH("medical",B122)),ISNUMBER(SEARCH("pharma",B122)),ISNUMBER(SEARCH("clinical",B122))),"Healthcare",TRUE,"Other") | B27: =IF(PROPER(TRIM(Raw_Data!D121))="Bangalore","Bengaluru",IF(PROPER(TRIM(Raw_Data!D121))="Gurgaon","Gurugram",IF(OR(PROPER(TRIM(Raw_Data!D121))="New Delhi",PROPER(TRIM(Raw_Data!D121))="Delhi"),"Delhi",PROPER(TRIM(Raw_Data!D121))))) | C27: =IF(TRIM(Raw_Data!F121&"")="","Not Specified",Raw_Data!F121) | D27: =Raw_Data!H121 | E27: =Raw_Data!E121
A28: =_xlfn.IFS(ISNUMBER(SEARCH("data analy",B123)),"Data Analyst",ISNUMBER(SEARCH("business analy",B123)),"Business Analyst",OR(ISNUMBER(SEARCH("developer",B123)),ISNUMBER(SEARCH("software engineer",B123)),ISNUMBER(SEARCH("programmer",B123))),"Software Developer",ISNUMBER(SEARCH("business development",B123)),"Business Development",ISNUMBER(SEARCH("sales",B123)),"Sales Executive",ISNUMBER(SEARCH("marketing",B123)),"Marketing Executive",OR(ISNUMBER(SEARCH("hr ",B123)),ISNUMBER(SEARCH("recruit",B123)),ISNUMBER(SEARCH("human resource",B123))),"HR / Recruiter",OR(ISNUMBER(SEARCH("account",B123)),ISNUMBER(SEARCH("finance",B123)),ISNUMBER(SEARCH("tax",B123)),ISNUMBER(SEARCH("audit",B123))),"Accountant / Finance",OR(ISNUMBER(SEARCH("customer service",B123)),ISNUMBER(SEARCH("customer support",B123)),ISNUMBER(SEARCH("customer care",B123)),ISNUMBER(SEARCH("voice process",B123)),ISNUMBER(SEARCH("bpo",B123))),"Customer Support",ISNUMBER(SEARCH("engineer",B123)),"Engineer (Technical)",ISNUMBER(SEARCH("manager",B123)),"Manager",OR(ISNUMBER(SEARCH("teacher",B123)),ISNUMBER(SEARCH("trainer",B123)),ISNUMBER(SEARCH("faculty",B123))),"Teacher / Trainer",OR(ISNUMBER(SEARCH("doctor",B123)),ISNUMBER(SEARCH("nurse",B123)),ISNUMBER(SEARCH("medical",B123)),ISNUMBER(SEARCH("pharma",B123)),ISNUMBER(SEARCH("clinical",B123))),"Healthcare",TRUE,"Other") | B28: =IF(PROPER(TRIM(Raw_Data!D122))="Bangalore","Bengaluru",IF(PROPER(TRIM(Raw_Data!D122))="Gurgaon","Gurugram",IF(OR(PROPER(TRIM(Raw_Data!D122))="New Delhi",PROPER(TRIM(Raw_Data!D122))="Delhi"),"Delhi",PROPER(TRIM(Raw_Data!D122))))) | C28: =IF(TRIM(Raw_Data!F122&"")="","Not Specified",Raw_Data!F122) | D28: =Raw_Data!H122 | E28: =Raw_Data!E122
A29: =_xlfn.IFS(ISNUMBER(SEARCH("data analy",B124)),"Data Analyst",ISNUMBER(SEARCH("business analy",B124)),"Business Analyst",OR(ISNUMBER(SEARCH("developer",B124)),ISNUMBER(SEARCH("software engineer",B124)),ISNUMBER(SEARCH("programmer",B124))),"Software Developer",ISNUMBER(SEARCH("business development",B124)),"Business Development",ISNUMBER(SEARCH("sales",B124)),"Sales Executive",ISNUMBER(SEARCH("marketing",B124)),"Marketing Executive",OR(ISNUMBER(SEARCH("hr ",B124)),ISNUMBER(SEARCH("recruit",B124)),ISNUMBER(SEARCH("human resource",B124))),"HR / Recruiter",OR(ISNUMBER(SEARCH("account",B124)),ISNUMBER(SEARCH("finance",B124)),ISNUMBER(SEARCH("tax",B124)),ISNUMBER(SEARCH("audit",B124))),"Accountant / Finance",OR(ISNUMBER(SEARCH("customer service",B124)),ISNUMBER(SEARCH("customer support",B124)),ISNUMBER(SEARCH("customer care",B124)),ISNUMBER(SEARCH("voice process",B124)),ISNUMBER(SEARCH("bpo",B124))),"Customer Support",ISNUMBER(SEARCH("engineer",B124)),"Engineer (Technical)",ISNUMBER(SEARCH("manager",B124)),"Manager",OR(ISNUMBER(SEARCH("teacher",B124)),ISNUMBER(SEARCH("trainer",B124)),ISNUMBER(SEARCH("faculty",B124))),"Teacher / Trainer",OR(ISNUMBER(SEARCH("doctor",B124)),ISNUMBER(SEARCH("nurse",B124)),ISNUMBER(SEARCH("medical",B124)),ISNUMBER(SEARCH("pharma",B124)),ISNUMBER(SEARCH("clinical",B124))),"Healthcare",TRUE,"Other") | B29: =IF(PROPER(TRIM(Raw_Data!D123))="Bangalore","Bengaluru",IF(PROPER(TRIM(Raw_Data!D123))="Gurgaon","Gurugram",IF(OR(PROPER(TRIM(Raw_Data!D123))="New Delhi",PROPER(TRIM(Raw_Data!D123))="Delhi"),"Delhi",PROPER(TRIM(Raw_Data!D123))))) | C29: =IF(TRIM(Raw_Data!F123&"")="","Not Specified",Raw_Data!F123) | D29: =Raw_Data!H123 | E29: =Raw_Data!E123
A30: =_xlfn.IFS(ISNUMBER(SEARCH("data analy",B125)),"Data Analyst",ISNUMBER(SEARCH("business analy",B125)),"Business Analyst",OR(ISNUMBER(SEARCH("developer",B125)),ISNUMBER(SEARCH("software engineer",B125)),ISNUMBER(SEARCH("programmer",B125))),"Software Developer",ISNUMBER(SEARCH("business development",B125)),"Business Development",ISNUMBER(SEARCH("sales",B125)),"Sales Executive",ISNUMBER(SEARCH("marketing",B125)),"Marketing Executive",OR(ISNUMBER(SEARCH("hr ",B125)),ISNUMBER(SEARCH("recruit",B125)),ISNUMBER(SEARCH("human resource",B125))),"HR / Recruiter",OR(ISNUMBER(SEARCH("account",B125)),ISNUMBER(SEARCH("finance",B125)),ISNUMBER(SEARCH("tax",B125)),ISNUMBER(SEARCH("audit",B125))),"Accountant / Finance",OR(ISNUMBER(SEARCH("customer service",B125)),ISNUMBER(SEARCH("customer support",B125)),ISNUMBER(SEARCH("customer care",B125)),ISNUMBER(SEARCH("voice process",B125)),ISNUMBER(SEARCH("bpo",B125))),"Customer Support",ISNUMBER(SEARCH("engineer",B125)),"Engineer (Technical)",ISNUMBER(SEARCH("manager",B125)),"Manager",OR(ISNUMBER(SEARCH("teacher",B125)),ISNUMBER(SEARCH("trainer",B125)),ISNUMBER(SEARCH("faculty",B125))),"Teacher / Trainer",OR(ISNUMBER(SEARCH("doctor",B125)),ISNUMBER(SEARCH("nurse",B125)),ISNUMBER(SEARCH("medical",B125)),ISNUMBER(SEARCH("pharma",B125)),ISNUMBER(SEARCH("clinical",B125))),"Healthcare",TRUE,"Other") | B30: =IF(PROPER(TRIM(Raw_Data!D124))="Bangalore","Bengaluru",IF(PROPER(TRIM(Raw_Data!D124))="Gurgaon","Gurugram",IF(OR(PROPER(TRIM(Raw_Data!D124))="New Delhi",PROPER(TRIM(Raw_Data!D124))="Delhi"),"Delhi",PROPER(TRIM(Raw_Data!D124))))) | C30: =IF(TRIM(Raw_Data!F124&"")="","Not Specified",Raw_Data!F124) | D30: =Raw_Data!H124 | E30: =Raw_Data!E124
A31: =_xlfn.IFS(ISNUMBER(SEARCH("data analy",B126)),"Data Analyst",ISNUMBER(SEARCH("business analy",B126)),"Business Analyst",OR(ISNUMBER(SEARCH("developer",B126)),ISNUMBER(SEARCH("software engineer",B126)),ISNUMBER(SEARCH("programmer",B126))),"Software Developer",ISNUMBER(SEARCH("business development",B126)),"Business Development",ISNUMBER(SEARCH("sales",B126)),"Sales Executive",ISNUMBER(SEARCH("marketing",B126)),"Marketing Executive",OR(ISNUMBER(SEARCH("hr ",B126)),ISNUMBER(SEARCH("recruit",B126)),ISNUMBER(SEARCH("human resource",B126))),"HR / Recruiter",OR(ISNUMBER(SEARCH("account",B126)),ISNUMBER(SEARCH("finance",B126)),ISNUMBER(SEARCH("tax",B126)),ISNUMBER(SEARCH("audit",B126))),"Accountant / Finance",OR(ISNUMBER(SEARCH("customer service",B126)),ISNUMBER(SEARCH("customer support",B126)),ISNUMBER(SEARCH("customer care",B126)),ISNUMBER(SEARCH("voice process",B126)),ISNUMBER(SEARCH("bpo",B126))),"Customer Support",ISNUMBER(SEARCH("engineer",B126)),"Engineer (Technical)",ISNUMBER(SEARCH("manager",B126)),"Manager",OR(ISNUMBER(SEARCH("teacher",B126)),ISNUMBER(SEARCH("trainer",B126)),ISNUMBER(SEARCH("faculty",B126))),"Teacher / Trainer",OR(ISNUMBER(SEARCH("doctor",B126)),ISNUMBER(SEARCH("nurse",B126)),ISNUMBER(SEARCH("medical",B126)),ISNUMBER(SEARCH("pharma",B126)),ISNUMBER(SEARCH("clinical",B126))),"Healthcare",TRUE,"Other") | B31: =IF(PROPER(TRIM(Raw_Data!D125))="Bangalore","Bengaluru",IF(PROPER(TRIM(Raw_Data!D125))="Gurgaon","Gurugram",IF(OR(PROPER(TRIM(Raw_Data!D125))="New Delhi",PROPER(TRIM(Raw_Data!D125))="Delhi"),"Delhi",PROPER(TRIM(Raw_Data!D125))))) | C31: =IF(TRIM(Raw_Data!F125&"")="","Not Specified",Raw_Data!F125) | D31: =Raw_Data!H125 | E31: =Raw_Data!E125
A32: =_xlfn.IFS(ISNUMBER(SEARCH("data analy",B127)),"Data Analyst",ISNUMBER(SEARCH("business analy",B127)),"Business Analyst",OR(ISNUMBER(SEARCH("developer",B127)),ISNUMBER(SEARCH("software engineer",B127)),ISNUMBER(SEARCH("programmer",B127))),"Software Developer",ISNUMBER(SEARCH("business development",B127)),"Business Development",ISNUMBER(SEARCH("sales",B127)),"Sales Executive",ISNUMBER(SEARCH("marketing",B127)),"Marketing Executive",OR(ISNUMBER(SEARCH("hr ",B127)),ISNUMBER(SEARCH("recruit",B127)),ISNUMBER(SEARCH("human resource",B127))),"HR / Recruiter",OR(ISNUMBER(SEARCH("account",B127)),ISNUMBER(SEARCH("finance",B127)),ISNUMBER(SEARCH("tax",B127)),ISNUMBER(SEARCH("audit",B127))),"Accountant / Finance",OR(ISNUMBER(SEARCH("customer service",B127)),ISNUMBER(SEARCH("customer support",B127)),ISNUMBER(SEARCH("customer care",B127)),ISNUMBER(SEARCH("voice process",B127)),ISNUMBER(SEARCH("bpo",B127))),"Customer Support",ISNUMBER(SEARCH("engineer",B127)),"Engineer (Technical)",ISNUMBER(SEARCH("manager",B127)),"Manager",OR(ISNUMBER(SEARCH("teacher",B127)),ISNUMBER(SEARCH("trainer",B127)),ISNUMBER(SEARCH("faculty",B127))),"Teacher / Trainer",OR(ISNUMBER(SEARCH("doctor",B127)),ISNUMBER(SEARCH("nurse",B127)),ISNUMBER(SEARCH("medical",B127)),ISNUMBER(SEARCH("pharma",B127)),ISNUMBER(SEARCH("clinical",B127))),"Healthcare",TRUE,"Other") | B32: =IF(PROPER(TRIM(Raw_Data!D126))="Bangalore","Bengaluru",IF(PROPER(TRIM(Raw_Data!D126))="Gurgaon","Gurugram",IF(OR(PROPER(TRIM(Raw_Data!D126))="New Delhi",PROPER(TRIM(Raw_Data!D126))="Delhi"),"Delhi",PROPER(TRIM(Raw_Data!D126))))) | C32: =IF(TRIM(Raw_Data!F126&"")="","Not Specified",Raw_Data!F126) | D32: =Raw_Data!H126 | E32: =Raw_Data!E126
A33: =_xlfn.IFS(ISNUMBER(SEARCH("data analy",B128)),"Data Analyst",ISNUMBER(SEARCH("business analy",B128)),"Business Analyst",OR(ISNUMBER(SEARCH("developer",B128)),ISNUMBER(SEARCH("software engineer",B128)),ISNUMBER(SEARCH("programmer",B128))),"Software Developer",ISNUMBER(SEARCH("business development",B128)),"Business Development",ISNUMBER(SEARCH("sales",B128)),"Sales Executive",ISNUMBER(SEARCH("marketing",B128)),"Marketing Executive",OR(ISNUMBER(SEARCH("hr ",B128)),ISNUMBER(SEARCH("recruit",B128)),ISNUMBER(SEARCH("human resource",B128))),"HR / Recruiter",OR(ISNUMBER(SEARCH("account",B128)),ISNUMBER(SEARCH("finance",B128)),ISNUMBER(SEARCH("tax",B128)),ISNUMBER(SEARCH("audit",B128))),"Accountant / Finance",OR(ISNUMBER(SEARCH("customer service",B128)),ISNUMBER(SEARCH("customer support",B128)),ISNUMBER(SEARCH("customer care",B128)),ISNUMBER(SEARCH("voice process",B128)),ISNUMBER(SEARCH("bpo",B128))),"Customer Support",ISNUMBER(SEARCH("engineer",B128)),"Engineer (Technical)",ISNUMBER(SEARCH("manager",B128)),"Manager",OR(ISNUMBER(SEARCH("teacher",B128)),ISNUMBER(SEARCH("trainer",B128)),ISNUMBER(SEARCH("faculty",B128))),"Teacher / Trainer",OR(ISNUMBER(SEARCH("doctor",B128)),ISNUMBER(SEARCH("nurse",B128)),ISNUMBER(SEARCH("medical",B128)),ISNUMBER(SEARCH("pharma",B128)),ISNUMBER(SEARCH("clinical",B128))),"Healthcare",TRUE,"Other") | B33: =IF(PROPER(TRIM(Raw_Data!D127))="Bangalore","Bengaluru",IF(PROPER(TRIM(Raw_Data!D127))="Gurgaon","Gurugram",IF(OR(PROPER(TRIM(Raw_Data!D127))="New Delhi",PROPER(TRIM(Raw_Data!D127))="Delhi"),"Delhi",PROPER(TRIM(Raw_Data!D127))))) | C33: =IF(TRIM(Raw_Data!F127&"")="","Not Specified",Raw_Data!F127) | D33: =Raw_Data!H127 | E33: =Raw_Data!E127
A34: =_xlfn.IFS(ISNUMBER(SEARCH("data analy",B129)),"Data Analyst",ISNUMBER(SEARCH("business analy",B129)),"Business Analyst",OR(ISNUMBER(SEARCH("developer",B129)),ISNUMBER(SEARCH("software engineer",B129)),ISNUMBER(SEARCH("programmer",B129))),"Software Developer",ISNUMBER(SEARCH("business development",B129)),"Business Development",ISNUMBER(SEARCH("sales",B129)),"Sales Executive",ISNUMBER(SEARCH("marketing",B129)),"Marketing Executive",OR(ISNUMBER(SEARCH("hr ",B129)),ISNUMBER(SEARCH("recruit",B129)),ISNUMBER(SEARCH("human resource",B129))),"HR / Recruiter",OR(ISNUMBER(SEARCH("account",B129)),ISNUMBER(SEARCH("finance",B129)),ISNUMBER(SEARCH("tax",B129)),ISNUMBER(SEARCH("audit",B129))),"Accountant / Finance",OR(ISNUMBER(SEARCH("customer service",B129)),ISNUMBER(SEARCH("customer support",B129)),ISNUMBER(SEARCH("customer care",B129)),ISNUMBER(SEARCH("voice process",B129)),ISNUMBER(SEARCH("bpo",B129))),"Customer Support",ISNUMBER(SEARCH("engineer",B129)),"Engineer (Technical)",ISNUMBER(SEARCH("manager",B129)),"Manager",OR(ISNUMBER(SEARCH("teacher",B129)),ISNUMBER(SEARCH("trainer",B129)),ISNUMBER(SEARCH("faculty",B129))),"Teacher / Trainer",OR(ISNUMBER(SEARCH("doctor",B129)),ISNUMBER(SEARCH("nurse",B129)),ISNUMBER(SEARCH("medical",B129)),ISNUMBER(SEARCH("pharma",B129)),ISNUMBER(SEARCH("clinical",B129))),"Healthcare",TRUE,"Other") | B34: =IF(PROPER(TRIM(Raw_Data!D128))="Bangalore","Bengaluru",IF(PROPER(TRIM(Raw_Data!D128))="Gurgaon","Gurugram",IF(OR(PROPER(TRIM(Raw_Data!D128))="New Delhi",PROPER(TRIM(Raw_Data!D128))="Delhi"),"Delhi",PROPER(TRIM(Raw_Data!D128))))) | C34: =IF(TRIM(Raw_Data!F128&"")="","Not Specified",Raw_Data!F128) | D34: =Raw_Data!H128 | E34: =Raw_Data!E128
A35: =_xlfn.IFS(ISNUMBER(SEARCH("data analy",B13)),"Data Analyst",ISNUMBER(SEARCH("business analy",B13)),"Business Analyst",OR(ISNUMBER(SEARCH("developer",B13)),ISNUMBER(SEARCH("software engineer",B13)),ISNUMBER(SEARCH("programmer",B13))),"Software Developer",ISNUMBER(SEARCH("business development",B13)),"Business Development",ISNUMBER(SEARCH("sales",B13)),"Sales Executive",ISNUMBER(SEARCH("marketing",B13)),"Marketing Executive",OR(ISNUMBER(SEARCH("hr ",B13)),ISNUMBER(SEARCH("recruit",B13)),ISNUMBER(SEARCH("human resource",B13))),"HR / Recruiter",OR(ISNUMBER(SEARCH("account",B13)),ISNUMBER(SEARCH("finance",B13)),ISNUMBER(SEARCH("tax",B13)),ISNUMBER(SEARCH("audit",B13))),"Accountant / Finance",OR(ISNUMBER(SEARCH("customer service",B13)),ISNUMBER(SEARCH("customer support",B13)),ISNUMBER(SEARCH("customer care",B13)),ISNUMBER(SEARCH("voice process",B13)),ISNUMBER(SEARCH("bpo",B13))),"Customer Support",ISNUMBER(SEARCH("engineer",B13)),"Engineer (Technical)",ISNUMBER(SEARCH("manager",B13)),"Manager",OR(ISNUMBER(SEARCH("teacher",B13)),ISNUMBER(SEARCH("trainer",B13)),ISNUMBER(SEARCH("faculty",B13))),"Teacher / Trainer",OR(ISNUMBER(SEARCH("doctor",B13)),ISNUMBER(SEARCH("nurse",B13)),ISNUMBER(SEARCH("medical",B13)),ISNUMBER(SEARCH("pharma",B13)),ISNUMBER(SEARCH("clinical",B13))),"Healthcare",TRUE,"Other") | B35: =IF(PROPER(TRIM(Raw_Data!D129))="Bangalore","Bengaluru",IF(PROPER(TRIM(Raw_Data!D129))="Gurgaon","Gurugram",IF(OR(PROPER(TRIM(Raw_Data!D129))="New Delhi",PROPER(TRIM(Raw_Data!D129))="Delhi"),"Delhi",PROPER(TRIM(Raw_Data!D129))))) | C35: =IF(TRIM(Raw_Data!F129&"")="","Not Specified",Raw_Data!F129) | D35: =Raw_Data!H129 | E35: =Raw_Data!E129
A36: =_xlfn.IFS(ISNUMBER(SEARCH("data analy",B130)),"Data Analyst",ISNUMBER(SEARCH("business analy",B130)),"Business Analyst",OR(ISNUMBER(SEARCH("developer",B130)),ISNUMBER(SEARCH("software engineer",B130)),ISNUMBER(SEARCH("programmer",B130))),"Software Developer",ISNUMBER(SEARCH("business development",B130)),"Business Development",ISNUMBER(SEARCH("sales",B130)),"Sales Executive",ISNUMBER(SEARCH("marketing",B130)),"Marketing Executive",OR(ISNUMBER(SEARCH("hr ",B130)),ISNUMBER(SEARCH("recruit",B130)),ISNUMBER(SEARCH("human resource",B130))),"HR / Recruiter",OR(ISNUMBER(SEARCH("account",B130)),ISNUMBER(SEARCH("finance",B130)),ISNUMBER(SEARCH("tax",B130)),ISNUMBER(SEARCH("audit",B130))),"Accountant / Finance",OR(ISNUMBER(SEARCH("customer service",B130)),ISNUMBER(SEARCH("customer support",B130)),ISNUMBER(SEARCH("customer care",B130)),ISNUMBER(SEARCH("voice process",B130)),ISNUMBER(SEARCH("bpo",B130))),"Customer Support",ISNUMBER(SEARCH("engineer",B130)),"Engineer (Technical)",ISNUMBER(SEARCH("manager",B130)),"Manager",OR(ISNUMBER(SEARCH("teacher",B130)),ISNUMBER(SEARCH("trainer",B130)),ISNUMBER(SEARCH("faculty",B130))),"Teacher / Trainer",OR(ISNUMBER(SEARCH("doctor",B130)),ISNUMBER(SEARCH("nurse",B130)),ISNUMBER(SEARCH("medical",B130)),ISNUMBER(SEARCH("pharma",B130)),ISNUMBER(SEARCH("clinical",B130))),"Healthcare",TRUE,"Other") | B36: =IF(PROPER(TRIM(Raw_Data!D13))="Bangalore","Bengaluru",IF(PROPER(TRIM(Raw_Data!D13))="Gurgaon","Gurugram",IF(OR(PROPER(TRIM(Raw_Data!D13))="New Delhi",PROPER(TRIM(Raw_Data!D13))="Delhi"),"Delhi",PROPER(TRIM(Raw_Data!D13))))) | C36: =IF(TRIM(Raw_Data!F13&"")="","Not Specified",Raw_Data!F13) | D36: =Raw_Data!H13 | E36: =Raw_Data!E13
A37: =_xlfn.IFS(ISNUMBER(SEARCH("data analy",B131)),"Data Analyst",ISNUMBER(SEARCH("business analy",B131)),"Business Analyst",OR(ISNUMBER(SEARCH("developer",B131)),ISNUMBER(SEARCH("software engineer",B131)),ISNUMBER(SEARCH("programmer",B131))),"Software Developer",ISNUMBER(SEARCH("business development",B131)),"Business Development",ISNUMBER(SEARCH("sales",B131)),"Sales Executive",ISNUMBER(SEARCH("marketing",B131)),"Marketing Executive",OR(ISNUMBER(SEARCH("hr ",B131)),ISNUMBER(SEARCH("recruit",B131)),ISNUMBER(SEARCH("human resource",B131))),"HR / Recruiter",OR(ISNUMBER(SEARCH("account",B131)),ISNUMBER(SEARCH("finance",B131)),ISNUMBER(SEARCH("tax",B131)),ISNUMBER(SEARCH("audit",B131))),"Accountant / Finance",OR(ISNUMBER(SEARCH("customer service",B131)),ISNUMBER(SEARCH("customer support",B131)),ISNUMBER(SEARCH("customer care",B131)),ISNUMBER(SEARCH("voice process",B131)),ISNUMBER(SEARCH("bpo",B131))),"Customer Support",ISNUMBER(SEARCH("engineer",B131)),"Engineer (Technical)",ISNUMBER(SEARCH("manager",B131)),"Manager",OR(ISNUMBER(SEARCH("teacher",B131)),ISNUMBER(SEARCH("trainer",B131)),ISNUMBER(SEARCH("faculty",B131))),"Teacher / Trainer",OR(ISNUMBER(SEARCH("doctor",B131)),ISNUMBER(SEARCH("nurse",B131)),ISNUMBER(SEARCH("medical",B131)),ISNUMBER(SEARCH("pharma",B131)),ISNUMBER(SEARCH("clinical",B131))),"Healthcare",TRUE,"Other") | B37: =IF(PROPER(TRIM(Raw_Data!D130))="Bangalore","Bengaluru",IF(PROPER(TRIM(Raw_Data!D130))="Gurgaon","Gurugram",IF(OR(PROPER(TRIM(Raw_Data!D130))="New Delhi",PROPER(TRIM(Raw_Data!D130))="Delhi"),"Delhi",PROPER(TRIM(Raw_Data!D130))))) | C37: =IF(TRIM(Raw_Data!F130&"")="","Not Specified",Raw_Data!F130) | D37: =Raw_Data!H130 | E37: =Raw_Data!E130
A38: =_xlfn.IFS(ISNUMBER(SEARCH("data analy",B132)),"Data Analyst",ISNUMBER(SEARCH("business analy",B132)),"Business Analyst",OR(ISNUMBER(SEARCH("developer",B132)),ISNUMBER(SEARCH("software engineer",B132)),ISNUMBER(SEARCH("programmer",B132))),"Software Developer",ISNUMBER(SEARCH("business development",B132)),"Business Development",ISNUMBER(SEARCH("sales",B132)),"Sales Executive",ISNUMBER(SEARCH("marketing",B132)),"Marketing Executive",OR(ISNUMBER(SEARCH("hr ",B132)),ISNUMBER(SEARCH("recruit",B132)),ISNUMBER(SEARCH("human resource",B132))),"HR / Recruiter",OR(ISNUMBER(SEARCH("account",B132)),ISNUMBER(SEARCH("finance",B132)),ISNUMBER(SEARCH("tax",B132)),ISNUMBER(SEARCH("audit",B132))),"Accountant / Finance",OR(ISNUMBER(SEARCH("customer service",B132)),ISNUMBER(SEARCH("customer support",B132)),ISNUMBER(SEARCH("customer care",B132)),ISNUMBER(SEARCH("voice process",B132)),ISNUMBER(SEARCH("bpo",B132))),"Customer Support",ISNUMBER(SEARCH("engineer",B132)),"Engineer (Technical)",ISNUMBER(SEARCH("manager",B132)),"Manager",OR(ISNUMBER(SEARCH("teacher",B132)),ISNUMBER(SEARCH("trainer",B132)),ISNUMBER(SEARCH("faculty",B132))),"Teacher / Trainer",OR(ISNUMBER(SEARCH("doctor",B132)),ISNUMBER(SEARCH("nurse",B132)),ISNUMBER(SEARCH("medical",B132)),ISNUMBER(SEARCH("pharma",B132)),ISNUMBER(SEARCH("clinical",B132))),"Healthcare",TRUE,"Other") | B38: =IF(PROPER(TRIM(Raw_Data!D131))="Bangalore","Bengaluru",IF(PROPER(TRIM(Raw_Data!D131))="Gurgaon","Gurugram",IF(OR(PROPER(TRIM(Raw_Data!D131))="New Delhi",PROPER(TRIM(Raw_Data!D131))="Delhi"),"Delhi",PROPER(TRIM(Raw_Data!D131))))) | C38: =IF(TRIM(Raw_Data!F131&"")="","Not Specified",Raw_Data!F131) | D38: =Raw_Data!H131 | E38: =Raw_Data!E131
A39: =_xlfn.IFS(ISNUMBER(SEARCH("data analy",B133)),"Data Analyst",ISNUMBER(SEARCH("business analy",B133)),"Business Analyst",OR(ISNUMBER(SEARCH("developer",B133)),ISNUMBER(SEARCH("software engineer",B133)),ISNUMBER(SEARCH("programmer",B133))),"Software Developer",ISNUMBER(SEARCH("business development",B133)),"Business Development",ISNUMBER(SEARCH("sales",B133)),"Sales Executive",ISNUMBER(SEARCH("marketing",B133)),"Marketing Executive",OR(ISNUMBER(SEARCH("hr ",B133)),ISNUMBER(SEARCH("recruit",B133)),ISNUMBER(SEARCH("human resource",B133))),"HR / Recruiter",OR(ISNUMBER(SEARCH("account",B133)),ISNUMBER(SEARCH("finance",B133)),ISNUMBER(SEARCH("tax",B133)),ISNUMBER(SEARCH("audit",B133))),"Accountant / Finance",OR(ISNUMBER(SEARCH("customer service",B133)),ISNUMBER(SEARCH("customer support",B133)),ISNUMBER(SEARCH("customer care",B133)),ISNUMBER(SEARCH("voice process",B133)),ISNUMBER(SEARCH("bpo",B133))),"Customer Support",ISNUMBER(SEARCH("engineer",B133)),"Engineer (Technical)",ISNUMBER(SEARCH("manager",B133)),"Manager",OR(ISNUMBER(SEARCH("teacher",B133)),ISNUMBER(SEARCH("trainer",B133)),ISNUMBER(SEARCH("faculty",B133))),"Teacher / Trainer",OR(ISNUMBER(SEARCH("doctor",B133)),ISNUMBER(SEARCH("nurse",B133)),ISNUMBER(SEARCH("medical",B133)),ISNUMBER(SEARCH("pharma",B133)),ISNUMBER(SEARCH("clinical",B133))),"Healthcare",TRUE,"Other") | B39: =IF(PROPER(TRIM(Raw_Data!D132))="Bangalore","Bengaluru",IF(PROPER(TRIM(Raw_Data!D132))="Gurgaon","Gurugram",IF(OR(PROPER(TRIM(Raw_Data!D132))="New Delhi",PROPER(TRIM(Raw_Data!D132))="Delhi"),"Delhi",PROPER(TRIM(Raw_Data!D132))))) | C39: =IF(TRIM(Raw_Data!F132&"")="","Not Specified",Raw_Data!F132) | D39: =Raw_Data!H132 | E39: =Raw_Data!E132
A40: =_xlfn.IFS(ISNUMBER(SEARCH("data analy",B134)),"Data Analyst",ISNUMBER(SEARCH("business analy",B134)),"Business Analyst",OR(ISNUMBER(SEARCH("developer",B134)),ISNUMBER(SEARCH("software engineer",B134)),ISNUMBER(SEARCH("programmer",B134))),"Software Developer",ISNUMBER(SEARCH("business development",B134)),"Business Development",ISNUMBER(SEARCH("sales",B134)),"Sales Executive",ISNUMBER(SEARCH("marketing",B134)),"Marketing Executive",OR(ISNUMBER(SEARCH("hr ",B134)),ISNUMBER(SEARCH("recruit",B134)),ISNUMBER(SEARCH("human resource",B134))),"HR / Recruiter",OR(ISNUMBER(SEARCH("account",B134)),ISNUMBER(SEARCH("finance",B134)),ISNUMBER(SEARCH("tax",B134)),ISNUMBER(SEARCH("audit",B134))),"Accountant / Finance",OR(ISNUMBER(SEARCH("customer service",B134)),ISNUMBER(SEARCH("customer support",B134)),ISNUMBER(SEARCH("customer care",B134)),ISNUMBER(SEARCH("voice process",B134)),ISNUMBER(SEARCH("bpo",B134))),"Customer Support",ISNUMBER(SEARCH("engineer",B134)),"Engineer (Technical)",ISNUMBER(SEARCH("manager",B134)),"Manager",OR(ISNUMBER(SEARCH("teacher",B134)),ISNUMBER(SEARCH("trainer",B134)),ISNUMBER(SEARCH("faculty",B134))),"Teacher / Trainer",OR(ISNUMBER(SEARCH("doctor",B134)),ISNUMBER(SEARCH("nurse",B134)),ISNUMBER(SEARCH("medical",B134)),ISNUMBER(SEARCH("pharma",B134)),ISNUMBER(SEARCH("clinical",B134))),"Healthcare",TRUE,"Other") | B40: =IF(PROPER(TRIM(Raw_Data!D133))="Bangalore","Bengaluru",IF(PROPER(TRIM(Raw_Data!D133))="Gurgaon","Gurugram",IF(OR(PROPER(TRIM(Raw_Data!D133))="New Delhi",PROPER(TRIM(Raw_Data!D133))="Delhi"),"Delhi",PROPER(TRIM(Raw_Data!D133))))) | C40: =IF(TRIM(Raw_Data!F133&"")="","Not Specified",Raw_Data!F133) | D40: =Raw_Data!H133 | E40: =Raw_Data!E133
A41: =_xlfn.IFS(ISNUMBER(SEARCH("data analy",B135)),"Data Analyst",ISNUMBER(SEARCH("business analy",B135)),"Business Analyst",OR(ISNUMBER(SEARCH("developer",B135)),ISNUMBER(SEARCH("software engineer",B135)),ISNUMBER(SEARCH("programmer",B135))),"Software Developer",ISNUMBER(SEARCH("business development",B135)),"Business Development",ISNUMBER(SEARCH("sales",B135)),"Sales Executive",ISNUMBER(SEARCH("marketing",B135)),"Marketing Executive",OR(ISNUMBER(SEARCH("hr ",B135)),ISNUMBER(SEARCH("recruit",B135)),ISNUMBER(SEARCH("human resource",B135))),"HR / Recruiter",OR(ISNUMBER(SEARCH("account",B135)),ISNUMBER(SEARCH("finance",B135)),ISNUMBER(SEARCH("tax",B135)),ISNUMBER(SEARCH("audit",B135))),"Accountant / Finance",OR(ISNUMBER(SEARCH("customer service",B135)),ISNUMBER(SEARCH("customer support",B135)),ISNUMBER(SEARCH("customer care",B135)),ISNUMBER(SEARCH("voice process",B135)),ISNUMBER(SEARCH("bpo",B135))),"Customer Support",ISNUMBER(SEARCH("engineer",B135)),"Engineer (Technical)",ISNUMBER(SEARCH("manager",B135)),"Manager",OR(ISNUMBER(SEARCH("teacher",B135)),ISNUMBER(SEARCH("trainer",B135)),ISNUMBER(SEARCH("faculty",B135))),"Teacher / Trainer",OR(ISNUMBER(SEARCH("doctor",B135)),ISNUMBER(SEARCH("nurse",B135)),ISNUMBER(SEARCH("medical",B135)),ISNUMBER(SEARCH("pharma",B135)),ISNUMBER(SEARCH("clinical",B135))),"Healthcare",TRUE,"Other") | B41: =IF(PROPER(TRIM(Raw_Data!D134))="Bangalore","Bengaluru",IF(PROPER(TRIM(Raw_Data!D134))="Gurgaon","Gurugram",IF(OR(PROPER(TRIM(Raw_Data!D134))="New Delhi",PROPER(TRIM(Raw_Data!D134))="Delhi"),"Delhi",PROPER(TRIM(Raw_Data!D134))))) | C41: =IF(TRIM(Raw_Data!F134&"")="","Not Specified",Raw_Data!F134) | D41: =Raw_Data!H134 | E41: =Raw_Data!E134
A42: =_xlfn.IFS(ISNUMBER(SEARCH("data analy",B136)),"Data Analyst",ISNUMBER(SEARCH("business analy",B136)),"Business Analyst",OR(ISNUMBER(SEARCH("developer",B136)),ISNUMBER(SEARCH("software engineer",B136)),ISNUMBER(SEARCH("programmer",B136))),"Software Developer",ISNUMBER(SEARCH("business development",B136)),"Business Development",ISNUMBER(SEARCH("sales",B136)),"Sales Executive",ISNUMBER(SEARCH("marketing",B136)),"Marketing Executive",OR(ISNUMBER(SEARCH("hr ",B136)),ISNUMBER(SEARCH("recruit",B136)),ISNUMBER(SEARCH("human resource",B136))),"HR / Recruiter",OR(ISNUMBER(SEARCH("account",B136)),ISNUMBER(SEARCH("finance",B136)),ISNUMBER(SEARCH("tax",B136)),ISNUMBER(SEARCH("audit",B136))),"Accountant / Finance",OR(ISNUMBER(SEARCH("customer service",B136)),ISNUMBER(SEARCH("customer support",B136)),ISNUMBER(SEARCH("customer care",B136)),ISNUMBER(SEARCH("voice process",B136)),ISNUMBER(SEARCH("bpo",B136))),"Customer Support",ISNUMBER(SEARCH("engineer",B136)),"Engineer (Technical)",ISNUMBER(SEARCH("manager",B136)),"Manager",OR(ISNUMBER(SEARCH("teacher",B136)),ISNUMBER(SEARCH("trainer",B136)),ISNUMBER(SEARCH("faculty",B136))),"Teacher / Trainer",OR(ISNUMBER(SEARCH("doctor",B136)),ISNUMBER(SEARCH("nurse",B136)),ISNUMBER(SEARCH("medical",B136)),ISNUMBER(SEARCH("pharma",B136)),ISNUMBER(SEARCH("clinical",B136))),"Healthcare",TRUE,"Other") | B42: =IF(PROPER(TRIM(Raw_Data!D135))="Bangalore","Bengaluru",IF(PROPER(TRIM(Raw_Data!D135))="Gurgaon","Gurugram",IF(OR(PROPER(TRIM(Raw_Data!D135))="New Delhi",PROPER(TRIM(Raw_Data!D135))="Delhi"),"Delhi",PROPER(TRIM(Raw_Data!D135))))) | C42: =IF(TRIM(Raw_Data!F135&"")="","Not Specified",Raw_Data!F135) | D42: =Raw_Data!H135 | E42: =Raw_Data!E135
A43: =_xlfn.IFS(ISNUMBER(SEARCH("data analy",B137)),"Data Analyst",ISNUMBER(SEARCH("business analy",B137)),"Business Analyst",OR(ISNUMBER(SEARCH("developer",B137)),ISNUMBER(SEARCH("software engineer",B137)),ISNUMBER(SEARCH("programmer",B137))),"Software Developer",ISNUMBER(SEARCH("business development",B137)),"Business Development",ISNUMBER(SEARCH("sales",B137)),"Sales Executive",ISNUMBER(SEARCH("marketing",B137)),"Marketing Executive",OR(ISNUMBER(SEARCH("hr ",B137)),ISNUMBER(SEARCH("recruit",B137)),ISNUMBER(SEARCH("human resource",B137))),"HR / Recruiter",OR(ISNUMBER(SEARCH("account",B137)),ISNUMBER(SEARCH("finance",B137)),ISNUMBER(SEARCH("tax",B137)),ISNUMBER(SEARCH("audit",B137))),"Accountant / Finance",OR(ISNUMBER(SEARCH("customer service",B137)),ISNUMBER(SEARCH("customer support",B137)),ISNUMBER(SEARCH("customer care",B137)),ISNUMBER(SEARCH("voice process",B137)),ISNUMBER(SEARCH("bpo",B137))),"Customer Support",ISNUMBER(SEARCH("engineer",B137)),"Engineer (Technical)",ISNUMBER(SEARCH("manager",B137)),"Manager",OR(ISNUMBER(SEARCH("teacher",B137)),ISNUMBER(SEARCH("trainer",B137)),ISNUMBER(SEARCH("faculty",B137))),"Teacher / Trainer",OR(ISNUMBER(SEARCH("doctor",B137)),ISNUMBER(SEARCH("nurse",B137)),ISNUMBER(SEARCH("medical",B137)),ISNUMBER(SEARCH("pharma",B137)),ISNUMBER(SEARCH("clinical",B137))),"Healthcare",TRUE,"Other") | B43: =IF(PROPER(TRIM(Raw_Data!D136))="Bangalore","Bengaluru",IF(PROPER(TRIM(Raw_Data!D136))="Gurgaon","Gurugram",IF(OR(PROPER(TRIM(Raw_Data!D136))="New Delhi",PROPER(TRIM(Raw_Data!D136))="Delhi"),"Delhi",PROPER(TRIM(Raw_Data!D136))))) | C43: =IF(TRIM(Raw_Data!F136&"")="","Not Specified",Raw_Data!F136) | D43: =Raw_Data!H136 | E43: =Raw_Data!E136
A44: =_xlfn.IFS(ISNUMBER(SEARCH("data analy",B138)),"Data Analyst",ISNUMBER(SEARCH("business analy",B138)),"Business Analyst",OR(ISNUMBER(SEARCH("developer",B138)),ISNUMBER(SEARCH("software engineer",B138)),ISNUMBER(SEARCH("programmer",B138))),"Software Developer",ISNUMBER(SEARCH("business development",B138)),"Business Development",ISNUMBER(SEARCH("sales",B138)),"Sales Executive",ISNUMBER(SEARCH("marketing",B138)),"Marketing Executive",OR(ISNUMBER(SEARCH("hr ",B138)),ISNUMBER(SEARCH("recruit",B138)),ISNUMBER(SEARCH("human resource",B138))),"HR / Recruiter",OR(ISNUMBER(SEARCH("account",B138)),ISNUMBER(SEARCH("finance",B138)),ISNUMBER(SEARCH("tax",B138)),ISNUMBER(SEARCH("audit",B138))),"Accountant / Finance",OR(ISNUMBER(SEARCH("customer service",B138)),ISNUMBER(SEARCH("customer support",B138)),ISNUMBER(SEARCH("customer care",B138)),ISNUMBER(SEARCH("voice process",B138)),ISNUMBER(SEARCH("bpo",B138))),"Customer Support",ISNUMBER(SEARCH("engineer",B138)),"Engineer (Technical)",ISNUMBER(SEARCH("manager",B138)),"Manager",OR(ISNUMBER(SEARCH("teacher",B138)),ISNUMBER(SEARCH("trainer",B138)),ISNUMBER(SEARCH("faculty",B138))),"Teacher / Trainer",OR(ISNUMBER(SEARCH("doctor",B138)),ISNUMBER(SEARCH("nurse",B138)),ISNUMBER(SEARCH("medical",B138)),ISNUMBER(SEARCH("pharma",B138)),ISNUMBER(SEARCH("clinical",B138))),"Healthcare",TRUE,"Other") | B44: =IF(PROPER(TRIM(Raw_Data!D137))="Bangalore","Bengaluru",IF(PROPER(TRIM(Raw_Data!D137))="Gurgaon","Gurugram",IF(OR(PROPER(TRIM(Raw_Data!D137))="New Delhi",PROPER(TRIM(Raw_Data!D137))="Delhi"),"Delhi",PROPER(TRIM(Raw_Data!D137))))) | C44: =IF(TRIM(Raw_Data!F137&"")="","Not Specified",Raw_Data!F137) | D44: =Raw_Data!H137 | E44: =Raw_Data!E137
A45: =_xlfn.IFS(ISNUMBER(SEARCH("data analy",B139)),"Data Analyst",ISNUMBER(SEARCH("business analy",B139)),"Business Analyst",OR(ISNUMBER(SEARCH("developer",B139)),ISNUMBER(SEARCH("software engineer",B139)),ISNUMBER(SEARCH("programmer",B139))),"Software Developer",ISNUMBER(SEARCH("business development",B139)),"Business Development",ISNUMBER(SEARCH("sales",B139)),"Sales Executive",ISNUMBER(SEARCH("marketing",B139)),"Marketing Executive",OR(ISNUMBER(SEARCH("hr ",B139)),ISNUMBER(SEARCH("recruit",B139)),ISNUMBER(SEARCH("human resource",B139))),"HR / Recruiter",OR(ISNUMBER(SEARCH("account",B139)),ISNUMBER(SEARCH("finance",B139)),ISNUMBER(SEARCH("tax",B139)),ISNUMBER(SEARCH("audit",B139))),"Accountant / Finance",OR(ISNUMBER(SEARCH("customer service",B139)),ISNUMBER(SEARCH("customer support",B139)),ISNUMBER(SEARCH("customer care",B139)),ISNUMBER(SEARCH("voice process",B139)),ISNUMBER(SEARCH("bpo",B139))),"Customer Support",ISNUMBER(SEARCH("engineer",B139)),"Engineer (Technical)",ISNUMBER(SEARCH("manager",B139)),"Manager",OR(ISNUMBER(SEARCH("teacher",B139)),ISNUMBER(SEARCH("trainer",B139)),ISNUMBER(SEARCH("faculty",B139))),"Teacher / Trainer",OR(ISNUMBER(SEARCH("doctor",B139)),ISNUMBER(SEARCH("nurse",B139)),ISNUMBER(SEARCH("medical",B139)),ISNUMBER(SEARCH("pharma",B139)),ISNUMBER(SEARCH("clinical",B139))),"Healthcare",TRUE,"Other") | B45: =IF(PROPER(TRIM(Raw_Data!D138))="Bangalore","Bengaluru",IF(PROPER(TRIM(Raw_Data!D138))="Gurgaon","Gurugram",IF(OR(PROPER(TRIM(Raw_Data!D138))="New Delhi",PROPER(TRIM(Raw_Data!D138))="Delhi"),"Delhi",PROPER(TRIM(Raw_Data!D138))))) | C45: =IF(TRIM(Raw_Data!F138&"")="","Not Specified",Raw_Data!F138) | D45: =Raw_Data!H138 | E45: =Raw_Data!E138
A46: =_xlfn.IFS(ISNUMBER(SEARCH("data analy",B14)),"Data Analyst",ISNUMBER(SEARCH("business analy",B14)),"Business Analyst",OR(ISNUMBER(SEARCH("developer",B14)),ISNUMBER(SEARCH("software engineer",B14)),ISNUMBER(SEARCH("programmer",B14))),"Software Developer",ISNUMBER(SEARCH("business development",B14)),"Business Development",ISNUMBER(SEARCH("sales",B14)),"Sales Executive",ISNUMBER(SEARCH("marketing",B14)),"Marketing Executive",OR(ISNUMBER(SEARCH("hr ",B14)),ISNUMBER(SEARCH("recruit",B14)),ISNUMBER(SEARCH("human resource",B14))),"HR / Recruiter",OR(ISNUMBER(SEARCH("account",B14)),ISNUMBER(SEARCH("finance",B14)),ISNUMBER(SEARCH("tax",B14)),ISNUMBER(SEARCH("audit",B14))),"Accountant / Finance",OR(ISNUMBER(SEARCH("customer service",B14)),ISNUMBER(SEARCH("customer support",B14)),ISNUMBER(SEARCH("customer care",B14)),ISNUMBER(SEARCH("voice process",B14)),ISNUMBER(SEARCH("bpo",B14))),"Customer Support",ISNUMBER(SEARCH("engineer",B14)),"Engineer (Technical)",ISNUMBER(SEARCH("manager",B14)),"Manager",OR(ISNUMBER(SEARCH("teacher",B14)),ISNUMBER(SEARCH("trainer",B14)),ISNUMBER(SEARCH("faculty",B14))),"Teacher / Trainer",OR(ISNUMBER(SEARCH("doctor",B14)),ISNUMBER(SEARCH("nurse",B14)),ISNUMBER(SEARCH("medical",B14)),ISNUMBER(SEARCH("pharma",B14)),ISNUMBER(SEARCH("clinical",B14))),"Healthcare",TRUE,"Other") | B46: =IF(PROPER(TRIM(Raw_Data!D139))="Bangalore","Bengaluru",IF(PROPER(TRIM(Raw_Data!D139))="Gurgaon","Gurugram",IF(OR(PROPER(TRIM(Raw_Data!D139))="New Delhi",PROPER(TRIM(Raw_Data!D139))="Delhi"),"Delhi",PROPER(TRIM(Raw_Data!D139))))) | C46: =IF(TRIM(Raw_Data!F139&"")="","Not Specified",Raw_Data!F139) | D46: =Raw_Data!H139 | E46: =Raw_Data!E139
A47: =_xlfn.IFS(ISNUMBER(SEARCH("data analy",B140)),"Data Analyst",ISNUMBER(SEARCH("business analy",B140)),"Business Analyst",OR(ISNUMBER(SEARCH("developer",B140)),ISNUMBER(SEARCH("software engineer",B140)),ISNUMBER(SEARCH("programmer",B140))),"Software Developer",ISNUMBER(SEARCH("business development",B140)),"Business Development",ISNUMBER(SEARCH("sales",B140)),"Sales Executive",ISNUMBER(SEARCH("marketing",B140)),"Marketing Executive",OR(ISNUMBER(SEARCH("hr ",B140)),ISNUMBER(SEARCH("recruit",B140)),ISNUMBER(SEARCH("human resource",B140))),"HR / Recruiter",OR(ISNUMBER(SEARCH("account",B140)),ISNUMBER(SEARCH("finance",B140)),ISNUMBER(SEARCH("tax",B140)),ISNUMBER(SEARCH("audit",B140))),"Accountant / Finance",OR(ISNUMBER(SEARCH("customer service",B140)),ISNUMBER(SEARCH("customer support",B140)),ISNUMBER(SEARCH("customer care",B140)),ISNUMBER(SEARCH("voice process",B140)),ISNUMBER(SEARCH("bpo",B140))),"Customer Support",ISNUMBER(SEARCH("engineer",B140)),"Engineer (Technical)",ISNUMBER(SEARCH("manager",B140)),"Manager",OR(ISNUMBER(SEARCH("teacher",B140)),ISNUMBER(SEARCH("trainer",B140)),ISNUMBER(SEARCH("faculty",B140))),"Teacher / Trainer",OR(ISNUMBER(SEARCH("doctor",B140)),ISNUMBER(SEARCH("nurse",B140)),ISNUMBER(SEARCH("medical",B140)),ISNUMBER(SEARCH("pharma",B140)),ISNUMBER(SEARCH("clinical",B140))),"Healthcare",TRUE,"Other") | B47: =IF(PROPER(TRIM(Raw_Data!D14))="Bangalore","Bengaluru",IF(PROPER(TRIM(Raw_Data!D14))="Gurgaon","Gurugram",IF(OR(PROPER(TRIM(Raw_Data!D14))="New Delhi",PROPER(TRIM(Raw_Data!D14))="Delhi"),"Delhi",PROPER(TRIM(Raw_Data!D14))))) | C47: =IF(TRIM(Raw_Data!F14&"")="","Not Specified",Raw_Data!F14) | D47: =Raw_Data!H14 | E47: =Raw_Data!E14
A48: =_xlfn.IFS(ISNUMBER(SEARCH("data analy",B141)),"Data Analyst",ISNUMBER(SEARCH("business analy",B141)),"Business Analyst",OR(ISNUMBER(SEARCH("developer",B141)),ISNUMBER(SEARCH("software engineer",B141)),ISNUMBER(SEARCH("programmer",B141))),"Software Developer",ISNUMBER(SEARCH("business development",B141)),"Business Development",ISNUMBER(SEARCH("sales",B141)),"Sales Executive",ISNUMBER(SEARCH("marketing",B141)),"Marketing Executive",OR(ISNUMBER(SEARCH("hr ",B141)),ISNUMBER(SEARCH("recruit",B141)),ISNUMBER(SEARCH("human resource",B141))),"HR / Recruiter",OR(ISNUMBER(SEARCH("account",B141)),ISNUMBER(SEARCH("finance",B141)),ISNUMBER(SEARCH("tax",B141)),ISNUMBER(SEARCH("audit",B141))),"Accountant / Finance",OR(ISNUMBER(SEARCH("customer service",B141)),ISNUMBER(SEARCH("customer support",B141)),ISNUMBER(SEARCH("customer care",B141)),ISNUMBER(SEARCH("voice process",B141)),ISNUMBER(SEARCH("bpo",B141))),"Customer Support",ISNUMBER(SEARCH("engineer",B141)),"Engineer (Technical)",ISNUMBER(SEARCH("manager",B141)),"Manager",OR(ISNUMBER(SEARCH("teacher",B141)),ISNUMBER(SEARCH("trainer",B141)),ISNUMBER(SEARCH("faculty",B141))),"Teacher / Trainer",OR(ISNUMBER(SEARCH("doctor",B141)),ISNUMBER(SEARCH("nurse",B141)),ISNUMBER(SEARCH("medical",B141)),ISNUMBER(SEARCH("pharma",B141)),ISNUMBER(SEARCH("clinical",B141))),"Healthcare",TRUE,"Other") | B48: =IF(PROPER(TRIM(Raw_Data!D140))="Bangalore","Bengaluru",IF(PROPER(TRIM(Raw_Data!D140))="Gurgaon","Gurugram",IF(OR(PROPER(TRIM(Raw_Data!D140))="New Delhi",PROPER(TRIM(Raw_Data!D140))="Delhi"),"Delhi",PROPER(TRIM(Raw_Data!D140))))) | C48: =IF(TRIM(Raw_Data!F140&"")="","Not Specified",Raw_Data!F140) | D48: =Raw_Data!H140 | E48: =Raw_Data!E140
A49: =_xlfn.IFS(ISNUMBER(SEARCH("data analy",B142)),"Data Analyst",ISNUMBER(SEARCH("business analy",B142)),"Business Analyst",OR(ISNUMBER(SEARCH("developer",B142)),ISNUMBER(SEARCH("software engineer",B142)),ISNUMBER(SEARCH("programmer",B142))),"Software Developer",ISNUMBER(SEARCH("business development",B142)),"Business Development",ISNUMBER(SEARCH("sales",B142)),"Sales Executive",ISNUMBER(SEARCH("marketing",B142)),"Marketing Executive",OR(ISNUMBER(SEARCH("hr ",B142)),ISNUMBER(SEARCH("recruit",B142)),ISNUMBER(SEARCH("human resource",B142))),"HR / Recruiter",OR(ISNUMBER(SEARCH("account",B142)),ISNUMBER(SEARCH("finance",B142)),ISNUMBER(SEARCH("tax",B142)),ISNUMBER(SEARCH("audit",B142))),"Accountant / Finance",OR(ISNUMBER(SEARCH("customer service",B142)),ISNUMBER(SEARCH("customer support",B142)),ISNUMBER(SEARCH("customer care",B142)),ISNUMBER(SEARCH("voice process",B142)),ISNUMBER(SEARCH("bpo",B142))),"Customer Support",ISNUMBER(SEARCH("engineer",B142)),"Engineer (Technical)",ISNUMBER(SEARCH("manager",B142)),"Manager",OR(ISNUMBER(SEARCH("teacher",B142)),ISNUMBER(SEARCH("trainer",B142)),ISNUMBER(SEARCH("faculty",B142))),"Teacher / Trainer",OR(ISNUMBER(SEARCH("doctor",B142)),ISNUMBER(SEARCH("nurse",B142)),ISNUMBER(SEARCH("medical",B142)),ISNUMBER(SEARCH("pharma",B142)),ISNUMBER(SEARCH("clinical",B142))),"Healthcare",TRUE,"Other") | B49: =IF(PROPER(TRIM(Raw_Data!D141))="Bangalore","Bengaluru",IF(PROPER(TRIM(Raw_Data!D141))="Gurgaon","Gurugram",IF(OR(PROPER(TRIM(Raw_Data!D141))="New Delhi",PROPER(TRIM(Raw_Data!D141))="Delhi"),"Delhi",PROPER(TRIM(Raw_Data!D141))))) | C49: =IF(TRIM(Raw_Data!F141&"")="","Not Specified",Raw_Data!F141) | D49: =Raw_Data!H141 | E49: =Raw_Data!E141
A50: =_xlfn.IFS(ISNUMBER(SEARCH("data analy",B143)),"Data Analyst",ISNUMBER(SEARCH("business analy",B143)),"Business Analyst",OR(ISNUMBER(SEARCH("developer",B143)),ISNUMBER(SEARCH("software engineer",B143)),ISNUMBER(SEARCH("programmer",B143))),"Software Developer",ISNUMBER(SEARCH("business development",B143)),"Business Development",ISNUMBER(SEARCH("sales",B143)),"Sales Executive",ISNUMBER(SEARCH("marketing",B143)),"Marketing Executive",OR(ISNUMBER(SEARCH("hr ",B143)),ISNUMBER(SEARCH("recruit",B143)),ISNUMBER(SEARCH("human resource",B143))),"HR / Recruiter",OR(ISNUMBER(SEARCH("account",B143)),ISNUMBER(SEARCH("finance",B143)),ISNUMBER(SEARCH("tax",B143)),ISNUMBER(SEARCH("audit",B143))),"Accountant / Finance",OR(ISNUMBER(SEARCH("customer service",B143)),ISNUMBER(SEARCH("customer support",B143)),ISNUMBER(SEARCH("customer care",B143)),ISNUMBER(SEARCH("voice process",B143)),ISNUMBER(SEARCH("bpo",B143))),"Customer Support",ISNUMBER(SEARCH("engineer",B143)),"Engineer (Technical)",ISNUMBER(SEARCH("manager",B143)),"Manager",OR(ISNUMBER(SEARCH("teacher",B143)),ISNUMBER(SEARCH("trainer",B143)),ISNUMBER(SEARCH("faculty",B143))),"Teacher / Trainer",OR(ISNUMBER(SEARCH("doctor",B143)),ISNUMBER(SEARCH("nurse",B143)),ISNUMBER(SEARCH("medical",B143)),ISNUMBER(SEARCH("pharma",B143)),ISNUMBER(SEARCH("clinical",B143))),"Healthcare",TRUE,"Other") | B50: =IF(PROPER(TRIM(Raw_Data!D142))="Bangalore","Bengaluru",IF(PROPER(TRIM(Raw_Data!D142))="Gurgaon","Gurugram",IF(OR(PROPER(TRIM(Raw_Data!D142))="New Delhi",PROPER(TRIM(Raw_Data!D142))="Delhi"),"Delhi",PROPER(TRIM(Raw_Data!D142))))) | C50: =IF(TRIM(Raw_Data!F142&"")="","Not Specified",Raw_Data!F142) | D50: =Raw_Data!H142 | E50: =Raw_Data!E142
A51: =_xlfn.IFS(ISNUMBER(SEARCH("data analy",B144)),"Data Analyst",ISNUMBER(SEARCH("business analy",B144)),"Business Analyst",OR(ISNUMBER(SEARCH("developer",B144)),ISNUMBER(SEARCH("software engineer",B144)),ISNUMBER(SEARCH("programmer",B144))),"Software Developer",ISNUMBER(SEARCH("business development",B144)),"Business Development",ISNUMBER(SEARCH("sales",B144)),"Sales Executive",ISNUMBER(SEARCH("marketing",B144)),"Marketing Executive",OR(ISNUMBER(SEARCH("hr ",B144)),ISNUMBER(SEARCH("recruit",B144)),ISNUMBER(SEARCH("human resource",B144))),"HR / Recruiter",OR(ISNUMBER(SEARCH("account",B144)),ISNUMBER(SEARCH("finance",B144)),ISNUMBER(SEARCH("tax",B144)),ISNUMBER(SEARCH("audit",B144))),"Accountant / Finance",OR(ISNUMBER(SEARCH("customer service",B144)),ISNUMBER(SEARCH("customer support",B144)),ISNUMBER(SEARCH("customer care",B144)),ISNUMBER(SEARCH("voice process",B144)),ISNUMBER(SEARCH("bpo",B144))),"Customer Support",ISNUMBER(SEARCH("engineer",B144)),"Engineer (Technical)",ISNUMBER(SEARCH("manager",B144)),"Manager",OR(ISNUMBER(SEARCH("teacher",B144)),ISNUMBER(SEARCH("trainer",B144)),ISNUMBER(SEARCH("faculty",B144))),"Teacher / Trainer",OR(ISNUMBER(SEARCH("doctor",B144)),ISNUMBER(SEARCH("nurse",B144)),ISNUMBER(SEARCH("medical",B144)),ISNUMBER(SEARCH("pharma",B144)),ISNUMBER(SEARCH("clinical",B144))),"Healthcare",TRUE,"Other") | B51: =IF(PROPER(TRIM(Raw_Data!D143))="Bangalore","Bengaluru",IF(PROPER(TRIM(Raw_Data!D143))="Gurgaon","Gurugram",IF(OR(PROPER(TRIM(Raw_Data!D143))="New Delhi",PROPER(TRIM(Raw_Data!D143))="Delhi"),"Delhi",PROPER(TRIM(Raw_Data!D143))))) | C51: =IF(TRIM(Raw_Data!F143&"")="","Not Specified",Raw_Data!F143) | D51: =Raw_Data!H143 | E51: =Raw_Data!E143
A52: =_xlfn.IFS(ISNUMBER(SEARCH("data analy",B145)),"Data Analyst",ISNUMBER(SEARCH("business analy",B145)),"Business Analyst",OR(ISNUMBER(SEARCH("developer",B145)),ISNUMBER(SEARCH("software engineer",B145)),ISNUMBER(SEARCH("programmer",B145))),"Software Developer",ISNUMBER(SEARCH("business development",B145)),"Business Development",ISNUMBER(SEARCH("sales",B145)),"Sales Executive",ISNUMBER(SEARCH("marketing",B145)),"Marketing Executive",OR(ISNUMBER(SEARCH("hr ",B145)),ISNUMBER(SEARCH("recruit",B145)),ISNUMBER(SEARCH("human resource",B145))),"HR / Recruiter",OR(ISNUMBER(SEARCH("account",B145)),ISNUMBER(SEARCH("finance",B145)),ISNUMBER(SEARCH("tax",B145)),ISNUMBER(SEARCH("audit",B145))),"Accountant / Finance",OR(ISNUMBER(SEARCH("customer service",B145)),ISNUMBER(SEARCH("customer support",B145)),ISNUMBER(SEARCH("customer care",B145)),ISNUMBER(SEARCH("voice process",B145)),ISNUMBER(SEARCH("bpo",B145))),"Customer Support",ISNUMBER(SEARCH("engineer",B145)),"Engineer (Technical)",ISNUMBER(SEARCH("manager",B145)),"Manager",OR(ISNUMBER(SEARCH("teacher",B145)),ISNUMBER(SEARCH("trainer",B145)),ISNUMBER(SEARCH("faculty",B145))),"Teacher / Trainer",OR(ISNUMBER(SEARCH("doctor",B145)),ISNUMBER(SEARCH("nurse",B145)),ISNUMBER(SEARCH("medical",B145)),ISNUMBER(SEARCH("pharma",B145)),ISNUMBER(SEARCH("clinical",B145))),"Healthcare",TRUE,"Other") | B52: =IF(PROPER(TRIM(Raw_Data!D144))="Bangalore","Bengaluru",IF(PROPER(TRIM(Raw_Data!D144))="Gurgaon","Gurugram",IF(OR(PROPER(TRIM(Raw_Data!D144))="New Delhi",PROPER(TRIM(Raw_Data!D144))="Delhi"),"Delhi",PROPER(TRIM(Raw_Data!D144))))) | C52: =IF(TRIM(Raw_Data!F144&"")="","Not Specified",Raw_Data!F144) | D52: =Raw_Data!H144 | E52: =Raw_Data!E144
A53: =_xlfn.IFS(ISNUMBER(SEARCH("data analy",B146)),"Data Analyst",ISNUMBER(SEARCH("business analy",B146)),"Business Analyst",OR(ISNUMBER(SEARCH("developer",B146)),ISNUMBER(SEARCH("software engineer",B146)),ISNUMBER(SEARCH("programmer",B146))),"Software Developer",ISNUMBER(SEARCH("business development",B146)),"Business Development",ISNUMBER(SEARCH("sales",B146)),"Sales Executive",ISNUMBER(SEARCH("marketing",B146)),"Marketing Executive",OR(ISNUMBER(SEARCH("hr ",B146)),ISNUMBER(SEARCH("recruit",B146)),ISNUMBER(SEARCH("human resource",B146))),"HR / Recruiter",OR(ISNUMBER(SEARCH("account",B146)),ISNUMBER(SEARCH("finance",B146)),ISNUMBER(SEARCH("tax",B146)),ISNUMBER(SEARCH("audit",B146))),"Accountant / Finance",OR(ISNUMBER(SEARCH("customer service",B146)),ISNUMBER(SEARCH("customer support",B146)),ISNUMBER(SEARCH("customer care",B146)),ISNUMBER(SEARCH("voice process",B146)),ISNUMBER(SEARCH("bpo",B146))),"Customer Support",ISNUMBER(SEARCH("engineer",B146)),"Engineer (Technical)",ISNUMBER(SEARCH("manager",B146)),"Manager",OR(ISNUMBER(SEARCH("teacher",B146)),ISNUMBER(SEARCH("trainer",B146)),ISNUMBER(SEARCH("faculty",B146))),"Teacher / Trainer",OR(ISNUMBER(SEARCH("doctor",B146)),ISNUMBER(SEARCH("nurse",B146)),ISNUMBER(SEARCH("medical",B146)),ISNUMBER(SEARCH("pharma",B146)),ISNUMBER(SEARCH("clinical",B146))),"Healthcare",TRUE,"Other") | B53: =IF(PROPER(TRIM(Raw_Data!D145))="Bangalore","Bengaluru",IF(PROPER(TRIM(Raw_Data!D145))="Gurgaon","Gurugram",IF(OR(PROPER(TRIM(Raw_Data!D145))="New Delhi",PROPER(TRIM(Raw_Data!D145))="Delhi"),"Delhi",PROPER(TRIM(Raw_Data!D145))))) | C53: =IF(TRIM(Raw_Data!F145&"")="","Not Specified",Raw_Data!F145) | D53: =Raw_Data!H145 | E53: =Raw_Data!E145
A54: =_xlfn.IFS(ISNUMBER(SEARCH("data analy",B147)),"Data Analyst",ISNUMBER(SEARCH("business analy",B147)),"Business Analyst",OR(ISNUMBER(SEARCH("developer",B147)),ISNUMBER(SEARCH("software engineer",B147)),ISNUMBER(SEARCH("programmer",B147))),"Software Developer",ISNUMBER(SEARCH("business development",B147)),"Business Development",ISNUMBER(SEARCH("sales",B147)),"Sales Executive",ISNUMBER(SEARCH("marketing",B147)),"Marketing Executive",OR(ISNUMBER(SEARCH("hr ",B147)),ISNUMBER(SEARCH("recruit",B147)),ISNUMBER(SEARCH("human resource",B147))),"HR / Recruiter",OR(ISNUMBER(SEARCH("account",B147)),ISNUMBER(SEARCH("finance",B147)),ISNUMBER(SEARCH("tax",B147)),ISNUMBER(SEARCH("audit",B147))),"Accountant / Finance",OR(ISNUMBER(SEARCH("customer service",B147)),ISNUMBER(SEARCH("customer support",B147)),ISNUMBER(SEARCH("customer care",B147)),ISNUMBER(SEARCH("voice process",B147)),ISNUMBER(SEARCH("bpo",B147))),"Customer Support",ISNUMBER(SEARCH("engineer",B147)),"Engineer (Technical)",ISNUMBER(SEARCH("manager",B147)),"Manager",OR(ISNUMBER(SEARCH("teacher",B147)),ISNUMBER(SEARCH("trainer",B147)),ISNUMBER(SEARCH("faculty",B147))),"Teacher / Trainer",OR(ISNUMBER(SEARCH("doctor",B147)),ISNUMBER(SEARCH("nurse",B147)),ISNUMBER(SEARCH("medical",B147)),ISNUMBER(SEARCH("pharma",B147)),ISNUMBER(SEARCH("clinical",B147))),"Healthcare",TRUE,"Other") | B54: =IF(PROPER(TRIM(Raw_Data!D146))="Bangalore","Bengaluru",IF(PROPER(TRIM(Raw_Data!D146))="Gurgaon","Gurugram",IF(OR(PROPER(TRIM(Raw_Data!D146))="New Delhi",PROPER(TRIM(Raw_Data!D146))="Delhi"),"Delhi",PROPER(TRIM(Raw_Data!D146))))) | C54: =IF(TRIM(Raw_Data!F146&"")="","Not Specified",Raw_Data!F146) | D54: =Raw_Data!H146 | E54: =Raw_Data!E146
A55: =_xlfn.IFS(ISNUMBER(SEARCH("data analy",B148)),"Data Analyst",ISNUMBER(SEARCH("business analy",B148)),"Business Analyst",OR(ISNUMBER(SEARCH("developer",B148)),ISNUMBER(SEARCH("software engineer",B148)),ISNUMBER(SEARCH("programmer",B148))),"Software Developer",ISNUMBER(SEARCH("business development",B148)),"Business Development",ISNUMBER(SEARCH("sales",B148)),"Sales Executive",ISNUMBER(SEARCH("marketing",B148)),"Marketing Executive",OR(ISNUMBER(SEARCH("hr ",B148)),ISNUMBER(SEARCH("recruit",B148)),ISNUMBER(SEARCH("human resource",B148))),"HR / Recruiter",OR(ISNUMBER(SEARCH("account",B148)),ISNUMBER(SEARCH("finance",B148)),ISNUMBER(SEARCH("tax",B148)),ISNUMBER(SEARCH("audit",B148))),"Accountant / Finance",OR(ISNUMBER(SEARCH("customer service",B148)),ISNUMBER(SEARCH("customer support",B148)),ISNUMBER(SEARCH("customer care",B148)),ISNUMBER(SEARCH("voice process",B148)),ISNUMBER(SEARCH("bpo",B148))),"Customer Support",ISNUMBER(SEARCH("engineer",B148)),"Engineer (Technical)",ISNUMBER(SEARCH("manager",B148)),"Manager",OR(ISNUMBER(SEARCH("teacher",B148)),ISNUMBER(SEARCH("trainer",B148)),ISNUMBER(SEARCH("faculty",B148))),"Teacher / Trainer",OR(ISNUMBER(SEARCH("doctor",B148)),ISNUMBER(SEARCH("nurse",B148)),ISNUMBER(SEARCH("medical",B148)),ISNUMBER(SEARCH("pharma",B148)),ISNUMBER(SEARCH("clinical",B148))),"Healthcare",TRUE,"Other") | B55: =IF(PROPER(TRIM(Raw_Data!D147))="Bangalore","Bengaluru",IF(PROPER(TRIM(Raw_Data!D147))="Gurgaon","Gurugram",IF(OR(PROPER(TRIM(Raw_Data!D147))="New Delhi",PROPER(TRIM(Raw_Data!D147))="Delhi"),"Delhi",PROPER(TRIM(Raw_Data!D147))))) | C55: =IF(TRIM(Raw_Data!F147&"")="","Not Specified",Raw_Data!F147) | D55: =Raw_Data!H147 | E55: =Raw_Data!E147
A56: =_xlfn.IFS(ISNUMBER(SEARCH("data analy",B149)),"Data Analyst",ISNUMBER(SEARCH("business analy",B149)),"Business Analyst",OR(ISNUMBER(SEARCH("developer",B149)),ISNUMBER(SEARCH("software engineer",B149)),ISNUMBER(SEARCH("programmer",B149))),"Software Developer",ISNUMBER(SEARCH("business development",B149)),"Business Development",ISNUMBER(SEARCH("sales",B149)),"Sales Executive",ISNUMBER(SEARCH("marketing",B149)),"Marketing Executive",OR(ISNUMBER(SEARCH("hr ",B149)),ISNUMBER(SEARCH("recruit",B149)),ISNUMBER(SEARCH("human resource",B149))),"HR / Recruiter",OR(ISNUMBER(SEARCH("account",B149)),ISNUMBER(SEARCH("finance",B149)),ISNUMBER(SEARCH("tax",B149)),ISNUMBER(SEARCH("audit",B149))),"Accountant / Finance",OR(ISNUMBER(SEARCH("customer service",B149)),ISNUMBER(SEARCH("customer support",B149)),ISNUMBER(SEARCH("customer care",B149)),ISNUMBER(SEARCH("voice process",B149)),ISNUMBER(SEARCH("bpo",B149))),"Customer Support",ISNUMBER(SEARCH("engineer",B149)),"Engineer (Technical)",ISNUMBER(SEARCH("manager",B149)),"Manager",OR(ISNUMBER(SEARCH("teacher",B149)),ISNUMBER(SEARCH("trainer",B149)),ISNUMBER(SEARCH("faculty",B149))),"Teacher / Trainer",OR(ISNUMBER(SEARCH("doctor",B149)),ISNUMBER(SEARCH("nurse",B149)),ISNUMBER(SEARCH("medical",B149)),ISNUMBER(SEARCH("pharma",B149)),ISNUMBER(SEARCH("clinical",B149))),"Healthcare",TRUE,"Other") | B56: =IF(PROPER(TRIM(Raw_Data!D148))="Bangalore","Bengaluru",IF(PROPER(TRIM(Raw_Data!D148))="Gurgaon","Gurugram",IF(OR(PROPER(TRIM(Raw_Data!D148))="New Delhi",PROPER(TRIM(Raw_Data!D148))="Delhi"),"Delhi",PROPER(TRIM(Raw_Data!D148))))) | C56: =IF(TRIM(Raw_Data!F148&"")="","Not Specified",Raw_Data!F148) | D56: =Raw_Data!H148 | E56: =Raw_Data!E148
A57: =_xlfn.IFS(ISNUMBER(SEARCH("data analy",B15)),"Data Analyst",ISNUMBER(SEARCH("business analy",B15)),"Business Analyst",OR(ISNUMBER(SEARCH("developer",B15)),ISNUMBER(SEARCH("software engineer",B15)),ISNUMBER(SEARCH("programmer",B15))),"Software Developer",ISNUMBER(SEARCH("business development",B15)),"Business Development",ISNUMBER(SEARCH("sales",B15)),"Sales Executive",ISNUMBER(SEARCH("marketing",B15)),"Marketing Executive",OR(ISNUMBER(SEARCH("hr ",B15)),ISNUMBER(SEARCH("recruit",B15)),ISNUMBER(SEARCH("human resource",B15))),"HR / Recruiter",OR(ISNUMBER(SEARCH("account",B15)),ISNUMBER(SEARCH("finance",B15)),ISNUMBER(SEARCH("tax",B15)),ISNUMBER(SEARCH("audit",B15))),"Accountant / Finance",OR(ISNUMBER(SEARCH("customer service",B15)),ISNUMBER(SEARCH("customer support",B15)),ISNUMBER(SEARCH("customer care",B15)),ISNUMBER(SEARCH("voice process",B15)),ISNUMBER(SEARCH("bpo",B15))),"Customer Support",ISNUMBER(SEARCH("engineer",B15)),"Engineer (Technical)",ISNUMBER(SEARCH("manager",B15)),"Manager",OR(ISNUMBER(SEARCH("teacher",B15)),ISNUMBER(SEARCH("trainer",B15)),ISNUMBER(SEARCH("faculty",B15))),"Teacher / Trainer",OR(ISNUMBER(SEARCH("doctor",B15)),ISNUMBER(SEARCH("nurse",B15)),ISNUMBER(SEARCH("medical",B15)),ISNUMBER(SEARCH("pharma",B15)),ISNUMBER(SEARCH("clinical",B15))),"Healthcare",TRUE,"Other") | B57: =IF(PROPER(TRIM(Raw_Data!D149))="Bangalore","Bengaluru",IF(PROPER(TRIM(Raw_Data!D149))="Gurgaon","Gurugram",IF(OR(PROPER(TRIM(Raw_Data!D149))="New Delhi",PROPER(TRIM(Raw_Data!D149))="Delhi"),"Delhi",PROPER(TRIM(Raw_Data!D149))))) | C57: =IF(TRIM(Raw_Data!F149&"")="","Not Specified",Raw_Data!F149) | D57: =Raw_Data!H149 | E57: =Raw_Data!E149
A58: =_xlfn.IFS(ISNUMBER(SEARCH("data analy",B150)),"Data Analyst",ISNUMBER(SEARCH("business analy",B150)),"Business Analyst",OR(ISNUMBER(SEARCH("developer",B150)),ISNUMBER(SEARCH("software engineer",B150)),ISNUMBER(SEARCH("programmer",B150))),"Software Developer",ISNUMBER(SEARCH("business development",B150)),"Business Development",ISNUMBER(SEARCH("sales",B150)),"Sales Executive",ISNUMBER(SEARCH("marketing",B150)),"Marketing Executive",OR(ISNUMBER(SEARCH("hr ",B150)),ISNUMBER(SEARCH("recruit",B150)),ISNUMBER(SEARCH("human resource",B150))),"HR / Recruiter",OR(ISNUMBER(SEARCH("account",B150)),ISNUMBER(SEARCH("finance",B150)),ISNUMBER(SEARCH("tax",B150)),ISNUMBER(SEARCH("audit",B150))),"Accountant / Finance",OR(ISNUMBER(SEARCH("customer service",B150)),ISNUMBER(SEARCH("customer support",B150)),ISNUMBER(SEARCH("customer care",B150)),ISNUMBER(SEARCH("voice process",B150)),ISNUMBER(SEARCH("bpo",B150))),"Customer Support",ISNUMBER(SEARCH("engineer",B150)),"Engineer (Technical)",ISNUMBER(SEARCH("manager",B150)),"Manager",OR(ISNUMBER(SEARCH("teacher",B150)),ISNUMBER(SEARCH("trainer",B150)),ISNUMBER(SEARCH("faculty",B150))),"Teacher / Trainer",OR(ISNUMBER(SEARCH("doctor",B150)),ISNUMBER(SEARCH("nurse",B150)),ISNUMBER(SEARCH("medical",B150)),ISNUMBER(SEARCH("pharma",B150)),ISNUMBER(SEARCH("clinical",B150))),"Healthcare",TRUE,"Other") | B58: =IF(PROPER(TRIM(Raw_Data!D15))="Bangalore","Bengaluru",IF(PROPER(TRIM(Raw_Data!D15))="Gurgaon","Gurugram",IF(OR(PROPER(TRIM(Raw_Data!D15))="New Delhi",PROPER(TRIM(Raw_Data!D15))="Delhi"),"Delhi",PROPER(TRIM(Raw_Data!D15))))) | C58: =IF(TRIM(Raw_Data!F15&"")="","Not Specified",Raw_Data!F15) | D58: =Raw_Data!H15 | E58: =Raw_Data!E15
A59: =_xlfn.IFS(ISNUMBER(SEARCH("data analy",B151)),"Data Analyst",ISNUMBER(SEARCH("business analy",B151)),"Business Analyst",OR(ISNUMBER(SEARCH("developer",B151)),ISNUMBER(SEARCH("software engineer",B151)),ISNUMBER(SEARCH("programmer",B151))),"Software Developer",ISNUMBER(SEARCH("business development",B151)),"Business Development",ISNUMBER(SEARCH("sales",B151)),"Sales Executive",ISNUMBER(SEARCH("marketing",B151)),"Marketing Executive",OR(ISNUMBER(SEARCH("hr ",B151)),ISNUMBER(SEARCH("recruit",B151)),ISNUMBER(SEARCH("human resource",B151))),"HR / Recruiter",OR(ISNUMBER(SEARCH("account",B151)),ISNUMBER(SEARCH("finance",B151)),ISNUMBER(SEARCH("tax",B151)),ISNUMBER(SEARCH("audit",B151))),"Accountant / Finance",OR(ISNUMBER(SEARCH("customer service",B151)),ISNUMBER(SEARCH("customer support",B151)),ISNUMBER(SEARCH("customer care",B151)),ISNUMBER(SEARCH("voice process",B151)),ISNUMBER(SEARCH("bpo",B151))),"Customer Support",ISNUMBER(SEARCH("engineer",B151)),"Engineer (Technical)",ISNUMBER(SEARCH("manager",B151)),"Manager",OR(ISNUMBER(SEARCH("teacher",B151)),ISNUMBER(SEARCH("trainer",B151)),ISNUMBER(SEARCH("faculty",B151))),"Teacher / Trainer",OR(ISNUMBER(SEARCH("doctor",B151)),ISNUMBER(SEARCH("nurse",B151)),ISNUMBER(SEARCH("medical",B151)),ISNUMBER(SEARCH("pharma",B151)),ISNUMBER(SEARCH("clinical",B151))),"Healthcare",TRUE,"Other") | B59: =IF(PROPER(TRIM(Raw_Data!D150))="Bangalore","Bengaluru",IF(PROPER(TRIM(Raw_Data!D150))="Gurgaon","Gurugram",IF(OR(PROPER(TRIM(Raw_Data!D150))="New Delhi",PROPER(TRIM(Raw_Data!D150))="Delhi"),"Delhi",PROPER(TRIM(Raw_Data!D150))))) | C59: =IF(TRIM(Raw_Data!F150&"")="","Not Specified",Raw_Data!F150) | D59: =Raw_Data!H150 | E59: =Raw_Data!E150
A60: =_xlfn.IFS(ISNUMBER(SEARCH("data analy",B152)),"Data Analyst",ISNUMBER(SEARCH("business analy",B152)),"Business Analyst",OR(ISNUMBER(SEARCH("developer",B152)),ISNUMBER(SEARCH("software engineer",B152)),ISNUMBER(SEARCH("programmer",B152))),"Software Developer",ISNUMBER(SEARCH("business development",B152)),"Business Development",ISNUMBER(SEARCH("sales",B152)),"Sales Executive",ISNUMBER(SEARCH("marketing",B152)),"Marketing Executive",OR(ISNUMBER(SEARCH("hr ",B152)),ISNUMBER(SEARCH("recruit",B152)),ISNUMBER(SEARCH("human resource",B152))),"HR / Recruiter",OR(ISNUMBER(SEARCH("account",B152)),ISNUMBER(SEARCH("finance",B152)),ISNUMBER(SEARCH("tax",B152)),ISNUMBER(SEARCH("audit",B152))),"Accountant / Finance",OR(ISNUMBER(SEARCH("customer service",B152)),ISNUMBER(SEARCH("customer support",B152)),ISNUMBER(SEARCH("customer care",B152)),ISNUMBER(SEARCH("voice process",B152)),ISNUMBER(SEARCH("bpo",B152))),"Customer Support",ISNUMBER(SEARCH("engineer",B152)),"Engineer (Technical)",ISNUMBER(SEARCH("manager",B152)),"Manager",OR(ISNUMBER(SEARCH("teacher",B152)),ISNUMBER(SEARCH("trainer",B152)),ISNUMBER(SEARCH("faculty",B152))),"Teacher / Trainer",OR(ISNUMBER(SEARCH("doctor",B152)),ISNUMBER(SEARCH("nurse",B152)),ISNUMBER(SEARCH("medical",B152)),ISNUMBER(SEARCH("pharma",B152)),ISNUMBER(SEARCH("clinical",B152))),"Healthcare",TRUE,"Other") | B60: =IF(PROPER(TRIM(Raw_Data!D151))="Bangalore","Bengaluru",IF(PROPER(TRIM(Raw_Data!D151))="Gurgaon","Gurugram",IF(OR(PROPER(TRIM(Raw_Data!D151))="New Delhi",PROPER(TRIM(Raw_Data!D151))="Delhi"),"Delhi",PROPER(TRIM(Raw_Data!D151))))) | C60: =IF(TRIM(Raw_Data!F151&"")="","Not Specified",Raw_Data!F151) | D60: =Raw_Data!H151 | E60: =Raw_Data!E151
A61: =_xlfn.IFS(ISNUMBER(SEARCH("data analy",B153)),"Data Analyst",ISNUMBER(SEARCH("business analy",B153)),"Business Analyst",OR(ISNUMBER(SEARCH("developer",B153)),ISNUMBER(SEARCH("software engineer",B153)),ISNUMBER(SEARCH("programmer",B153))),"Software Developer",ISNUMBER(SEARCH("business development",B153)),"Business Development",ISNUMBER(SEARCH("sales",B153)),"Sales Executive",ISNUMBER(SEARCH("marketing",B153)),"Marketing Executive",OR(ISNUMBER(SEARCH("hr ",B153)),ISNUMBER(SEARCH("recruit",B153)),ISNUMBER(SEARCH("human resource",B153))),"HR / Recruiter",OR(ISNUMBER(SEARCH("account",B153)),ISNUMBER(SEARCH("finance",B153)),ISNUMBER(SEARCH("tax",B153)),ISNUMBER(SEARCH("audit",B153))),"Accountant / Finance",OR(ISNUMBER(SEARCH("customer service",B153)),ISNUMBER(SEARCH("customer support",B153)),ISNUMBER(SEARCH("customer care",B153)),ISNUMBER(SEARCH("voice process",B153)),ISNUMBER(SEARCH("bpo",B153))),"Customer Support",ISNUMBER(SEARCH("engineer",B153)),"Engineer (Technical)",ISNUMBER(SEARCH("manager",B153)),"Manager",OR(ISNUMBER(SEARCH("teacher",B153)),ISNUMBER(SEARCH("trainer",B153)),ISNUMBER(SEARCH("faculty",B153))),"Teacher / Trainer",OR(ISNUMBER(SEARCH("doctor",B153)),ISNUMBER(SEARCH("nurse",B153)),ISNUMBER(SEARCH("medical",B153)),ISNUMBER(SEARCH("pharma",B153)),ISNUMBER(SEARCH("clinical",B153))),"Healthcare",TRUE,"Other") | B61: =IF(PROPER(TRIM(Raw_Data!D152))="Bangalore","Bengaluru",IF(PROPER(TRIM(Raw_Data!D152))="Gurgaon","Gurugram",IF(OR(PROPER(TRIM(Raw_Data!D152))="New Delhi",PROPER(TRIM(Raw_Data!D152))="Delhi"),"Delhi",PROPER(TRIM(Raw_Data!D152))))) | C61: =IF(TRIM(Raw_Data!F152&"")="","Not Specified",Raw_Data!F152) | D61: =Raw_Data!H152 | E61: =Raw_Data!E152
A62: =_xlfn.IFS(ISNUMBER(SEARCH("data analy",B154)),"Data Analyst",ISNUMBER(SEARCH("business analy",B154)),"Business Analyst",OR(ISNUMBER(SEARCH("developer",B154)),ISNUMBER(SEARCH("software engineer",B154)),ISNUMBER(SEARCH("programmer",B154))),"Software Developer",ISNUMBER(SEARCH("business development",B154)),"Business Development",ISNUMBER(SEARCH("sales",B154)),"Sales Executive",ISNUMBER(SEARCH("marketing",B154)),"Marketing Executive",OR(ISNUMBER(SEARCH("hr ",B154)),ISNUMBER(SEARCH("recruit",B154)),ISNUMBER(SEARCH("human resource",B154))),"HR / Recruiter",OR(ISNUMBER(SEARCH("account",B154)),ISNUMBER(SEARCH("finance",B154)),ISNUMBER(SEARCH("tax",B154)),ISNUMBER(SEARCH("audit",B154))),"Accountant / Finance",OR(ISNUMBER(SEARCH("customer service",B154)),ISNUMBER(SEARCH("customer support",B154)),ISNUMBER(SEARCH("customer care",B154)),ISNUMBER(SEARCH("voice process",B154)),ISNUMBER(SEARCH("bpo",B154))),"Customer Support",ISNUMBER(SEARCH("engineer",B154)),"Engineer (Technical)",ISNUMBER(SEARCH("manager",B154)),"Manager",OR(ISNUMBER(SEARCH("teacher",B154)),ISNUMBER(SEARCH("trainer",B154)),ISNUMBER(SEARCH("faculty",B154))),"Teacher / Trainer",OR(ISNUMBER(SEARCH("doctor",B154)),ISNUMBER(SEARCH("nurse",B154)),ISNUMBER(SEARCH("medical",B154)),ISNUMBER(SEARCH("pharma",B154)),ISNUMBER(SEARCH("clinical",B154))),"Healthcare",TRUE,"Other") | B62: =IF(PROPER(TRIM(Raw_Data!D153))="Bangalore","Bengaluru",IF(PROPER(TRIM(Raw_Data!D153))="Gurgaon","Gurugram",IF(OR(PROPER(TRIM(Raw_Data!D153))="New Delhi",PROPER(TRIM(Raw_Data!D153))="Delhi"),"Delhi",PROPER(TRIM(Raw_Data!D153))))) | C62: =IF(TRIM(Raw_Data!F153&"")="","Not Specified",Raw_Data!F153) | D62: =Raw_Data!H153 | E62: =Raw_Data!E153
A63: =_xlfn.IFS(ISNUMBER(SEARCH("data analy",B155)),"Data Analyst",ISNUMBER(SEARCH("business analy",B155)),"Business Analyst",OR(ISNUMBER(SEARCH("developer",B155)),ISNUMBER(SEARCH("software engineer",B155)),ISNUMBER(SEARCH("programmer",B155))),"Software Developer",ISNUMBER(SEARCH("business development",B155)),"Business Development",ISNUMBER(SEARCH("sales",B155)),"Sales Executive",ISNUMBER(SEARCH("marketing",B155)),"Marketing Executive",OR(ISNUMBER(SEARCH("hr ",B155)),ISNUMBER(SEARCH("recruit",B155)),ISNUMBER(SEARCH("human resource",B155))),"HR / Recruiter",OR(ISNUMBER(SEARCH("account",B155)),ISNUMBER(SEARCH("finance",B155)),ISNUMBER(SEARCH("tax",B155)),ISNUMBER(SEARCH("audit",B155))),"Accountant / Finance",OR(ISNUMBER(SEARCH("customer service",B155)),ISNUMBER(SEARCH("customer support",B155)),ISNUMBER(SEARCH("customer care",B155)),ISNUMBER(SEARCH("voice process",B155)),ISNUMBER(SEARCH("bpo",B155))),"Customer Support",ISNUMBER(SEARCH("engineer",B155)),"Engineer (Technical)",ISNUMBER(SEARCH("manager",B155)),"Manager",OR(ISNUMBER(SEARCH("teacher",B155)),ISNUMBER(SEARCH("trainer",B155)),ISNUMBER(SEARCH("faculty",B155))),"Teacher / Trainer",OR(ISNUMBER(SEARCH("doctor",B155)),ISNUMBER(SEARCH("nurse",B155)),ISNUMBER(SEARCH("medical",B155)),ISNUMBER(SEARCH("pharma",B155)),ISNUMBER(SEARCH("clinical",B155))),"Healthcare",TRUE,"Other") | B63: =IF(PROPER(TRIM(Raw_Data!D154))="Bangalore","Bengaluru",IF(PROPER(TRIM(Raw_Data!D154))="Gurgaon","Gurugram",IF(OR(PROPER(TRIM(Raw_Data!D154))="New Delhi",PROPER(TRIM(Raw_Data!D154))="Delhi"),"Delhi",PROPER(TRIM(Raw_Data!D154))))) | C63: =IF(TRIM(Raw_Data!F154&"")="","Not Specified",Raw_Data!F154) | D63: =Raw_Data!H154 | E63: =Raw_Data!E154
